Workbook

Sheet data
A1: Publisher ID | B1: Publisher Name | C1: Keyword ID | D1: Keyword | E1: Match Type | F1: Campaign | G1: Keyword Group | H1: Category | I1: Bid Strategy | J1: Keyword Type | K1: Status | L1: Search Engine Bid | M1: Clicks | N1: Click Charges | O1: Avg. Cost per Click | P1: Impressions | Q1: Engine Click Thru % | R1: Avg. Pos. | S1: Trans. Conv. % | T1: Total Cost/ Trans. | U1: Amount | V1: Total Cost | W1: Net Revenue | X1: Return on Ad Dollar Spent | Y1: Total Volume of Bookings | Z1: Avg. Revenue per Booking | AA1: Probability of Booking
A2: K2615 | B2: Yahoo - US | C2: 43000000039657988 | D2: fly to florence | E2: Advanced | F2: Western Europe Destinations | G2: Florence | H2: uncategorized | J2: Unassigned | K2: Live | L2: 6.25 | M2: 1 | N2: 2.3125 | O2: 2.3125 | P2: 11 | Q2: 9.0909091 | R2: 1.2727273 | S2: 900 | T2: =N2/Y2 -> 0.25694444 | U2: 8777.95 | V2: =N2 -> 2.3125 | W2: =U2-V2 -> 8775.6375 | X2: =IF(V2=0,0,(U2-V2)/V2) -> 3794.8703 | Y2: 9 | Z2: =IF(Y2=0,"NA",U2/Y2) -> 975.32778 | AA2: =(Q2/100*S2/100) -> 0.81818182
A3: K2615 | B3: Yahoo - US | C3: 43000000039651113 | D3: low international airfare | E3: Advanced | F3: Geo Targeted DC | G3: Low International DC | H3: uncategorized | J3: Unassigned | K3: Paused | L3: 6.25 | M3: 1 | N3: 0.625 | O3: 0.625 | P3: 6 | Q3: 16.666667 | R3: 1 | S3: 100 | T3: =N3/Y3 -> 0.625 | U3: 1574.2 | V3: =N3 -> 0.625 | W3: =U3-V3 -> 1573.575 | X3: =IF(V3=0,0,(U3-V3)/V3) -> 2517.72 | Y3: 1 | Z3: =IF(Y3=0,"NA",U3/Y3) -> 1574.2 | AA3: =(Q3/100*S3/100) -> 0.16666667
A4: K2003 | B4: MSN - Global | C4: 43000000019452431 | D4: air discount france ticket | E4: Broad | F4: Air France Brand & French Destinations | G4: France | H4: uncategorized | I4: Position 2-5 Bid Strategy | J4: Unassigned | K4: Deactivated | L4: 0 | M4: 1 | N4: 0.3875 | O4: 0.3875 | P4: 9 | Q4: 11.111111 | R4: 1.1111111 | S4: 100 | T4: =N4/Y4 -> 0.3875 | U4: 390.15 | V4: =N4 -> 0.3875 | W4: =U4-V4 -> 389.7625 | X4: =IF(V4=0,0,(U4-V4)/V4) -> 1005.8387 | Y4: 1 | Z4: =IF(Y4=0,"NA",U4/Y4) -> 390.15 | AA4: =(Q4/100*S4/100) -> 0.11111111
A5: K1175 | B5: Google - Global | C5: 43000000005663331 | D5: [airfrance] | E5: Exact | F5: Air France Global Campaign | G5: Air France | H5: airfrance | I5: Position 1- 3 | J5: Unassigned | K5: Unavailable | L5: 7.5 | M5: 59 | N5: 2.3124998 | O5: 0.039194912 | P5: 401 | Q5: 14.713217 | R5: 2 | S5: 3.3898305 | T5: =N5/Y5 -> 1.1562499 | U5: 1665.15 | V5: =N5 -> 2.3124998 | W5: =U5-V5 -> 1662.8375 | X5: =IF(V5=0,0,(U5-V5)/V5) -> 719.06492 | Y5: 2 | Z5: =IF(Y5=0,"NA",U5/Y5) -> 832.575 | AA5: =(Q5/100*S5/100) -> 0.0049875312
A6: K1123 | B6: Overture - Global | C6: 43000000005421354 | D6: air france online booking | E6: Standard | F6: Unassigned | G6: Unassigned | H6: airfrance | I6: Position 1-2 Target | J6: Unassigned | K6: Paused | L6: 0.25 | M6: 8 | N6: 2.2 | O6: 0.275 | P6: 318 | Q6: 2.5157233 | R6: 2.9757862 | S6: 12.5 | T6: =N6/Y6 -> 2.2 | U6: 935 | V6: =N6 -> 2.2 | W6: =U6-V6 -> 932.8 | X6: =IF(V6=0,0,(U6-V6)/V6) -> 424 | Y6: 1 | Z6: =IF(Y6=0,"NA",U6/Y6) -> 935 | AA6: =(Q6/100*S6/100) -> 0.0031446541
A7: K1123 | B7: Overture - Global | C7: 43000000005421146 | D7: airfrance,com | E7: Standard | F7: Unassigned | G7: Unassigned | H7: airfrancewebsite | I7: Position 1-2 Target | J7: Unassigned | K7: Paused | L7: 0.125 | M7: 42 | N7: 5.25 | O7: 0.125 | P7: 722 | Q7: 5.8171745 | R7: 1.1290859 | S7: 4.7619048 | T7: =N7/Y7 -> 2.625 | U7: 1817.3 | V7: =N7 -> 5.25 | W7: =U7-V7 -> 1812.05 | X7: =IF(V7=0,0,(U7-V7)/V7) -> 345.15238 | Y7: 2 | Z7: =IF(Y7=0,"NA",U7/Y7) -> 908.65 | AA7: =(Q7/100*S7/100) -> 0.0027700831
A8: K435 | B8: Google - US | C8: 43000000014110441 | D8: paris cheap airline | E8: Broad | F8: Geo Targeted San Francisco | G8: San Francisco to Paris Sale | H8: uncategorized | I8: Position 5-10 Bid Strategy | J8: Unassigned | K8: Paused | L8: 6.25 | M8: 3 | N8: 5.2125 | O8: 1.7375 | P8: 13 | Q8: 23.076923 | R8: 1 | S8: 33.333333 | T8: =N8/Y8 -> 5.2125 | U8: 1685.55 | V8: =N8 -> 5.2125 | W8: =U8-V8 -> 1680.3375 | X8: =IF(V8=0,0,(U8-V8)/V8) -> 322.36691 | Y8: 1 | Z8: =IF(Y8=0,"NA",U8/Y8) -> 1685.55 | AA8: =(Q8/100*S8/100) -> 0.076923077
A9: K1122 | B9: Overture - US | C9: 43000000014278681 | D9: airfrance.us | E9: Standard | F9: Unassigned | G9: Unassigned | H9: airfrance | I9: Position 1-4 Bid Strategy | J9: Unassigned | K9: Paused | L9: 0.325 | M9: 47 | N9: 11.8 | O9: 0.25106383 | P9: 547 | Q9: 8.5923218 | R9: 1.1819013 | S9: 4.2553191 | T9: =N9/Y9 -> 5.8999999 | U9: 3796.1 | V9: =N9 -> 11.8 | W9: =U9-V9 -> 3784.3 | X9: =IF(V9=0,0,(U9-V9)/V9) -> 320.7034 | Y9: 2 | Z9: =IF(Y9=0,"NA",U9/Y9) -> 1898.05 | AA9: =(Q9/100*S9/100) -> 0.0036563071
A10: K1123 | B10: Overture - Global | C10: 43000000005421374 | D10: air travel to paris | E10: Standard | F10: Unassigned | G10: Unassigned | H10: paris | I10: Position 1-2 Target | J10: Unassigned | K10: Unavailable | L10: 7.5 | M10: 13 | N10: 5.2125 | O10: 0.40096154 | P10: 448 | Q10: 2.9017857 | R10: 1.8564732 | S10: 7.6923077 | T10: =N10/Y10 -> 5.2125 | U10: 1513 | V10: =N10 -> 5.2125 | W10: =U10-V10 -> 1507.7875 | X10: =IF(V10=0,0,(U10-V10)/V10) -> 289.26379 | Y10: 1 | Z10: =IF(Y10=0,"NA",U10/Y10) -> 1513 | AA10: =(Q10/100*S10/100) -> 0.0022321429
A11: K1175 | B11: Google - Global | C11: 43000000019449172 | D11: air france site | E11: Broad | F11: Air France Brand & French Destinations | G11: Air France Website | H11: uncategorized | J11: Unassigned | K11: Unavailable | L11: 5 | M11: 19 | N11: 8.2374999 | O11: 0.43355262 | P11: 129 | Q11: 14.728682 | R11: 1.0302326 | S11: 5.2631579 | T11: =N11/Y11 -> 8.2374999 | U11: 2348.55 | V11: =N11 -> 8.2374999 | W11: =U11-V11 -> 2340.3125 | X11: =IF(V11=0,0,(U11-V11)/V11) -> 284.10471 | Y11: 1 | Z11: =IF(Y11=0,"NA",U11/Y11) -> 2348.55 | AA11: =(Q11/100*S11/100) -> 0.007751938
A12: K1123 | B12: Overture - Global | C12: 43000000005421298 | D12: cheap fare to paris | E12: Advanced | F12: Unassigned | G12: Unassigned | H12: paris | I12: Position 1-2 Target | J12: Unassigned | K12: Sent | L12: 0.6875 | M12: 29 | N12: 26.6125 | O12: 0.91767241 | P12: 559 | Q12: 5.1878354 | R12: 2.3334526 | S12: 6.8965517 | T12: =N12/Y12 -> 13.30625 | U12: 7418.8 | V12: =N12 -> 26.6125 | W12: =U12-V12 -> 7392.1875 | X12: =IF(V12=0,0,(U12-V12)/V12) -> 277.77125 | Y12: 2 | Z12: =IF(Y12=0,"NA",U12/Y12) -> 3709.4 | AA12: =(Q12/100*S12/100) -> 0.0035778175
A13: K1122 | B13: Overture - US | C13: 43000000014278799 | D13: air france.com | E13: Standard | F13: Unassigned | G13: Unassigned | H13: airfrance | I13: Position 1-4 Bid Strategy | J13: Unassigned | K13: Paused | L13: 0.3125 | M13: 273 | N13: 46.349998 | O13: 0.16978021 | P13: 3171 | Q13: 8.6092715 | R13: 1.0063072 | S13: 3.6630037 | T13: =N13/Y13 -> 4.6349998 | U13: 11271.85 | V13: =N13 -> 46.349998 | W13: =U13-V13 -> 11225.5 | X13: =IF(V13=0,0,(U13-V13)/V13) -> 242.18987 | Y13: 10 | Z13: =IF(Y13=0,"NA",U13/Y13) -> 1127.185 | AA13: =(Q13/100*S13/100) -> 0.0031535793
A14: K435 | B14: Google - US | C14: 43000000017532136 | D14: air france us | E14: Broad | F14: Air France Branded | G14: Air France Website | H14: uncategorized | J14: Unassigned | K14: Live | L14: 10 | M14: 231 | N14: 99.549999 | O14: 0.43095237 | P14: 1277 | Q14: 18.089272 | R14: 1.0226077 | S14: 8.6580087 | T14: =N14/Y14 -> 4.9774999 | U14: 23076.65 | V14: =N14 -> 99.549999 | W14: =U14-V14 -> 22977.1 | X14: =IF(V14=0,0,(U14-V14)/V14) -> 230.80965 | Y14: 20 | Z14: =IF(Y14=0,"NA",U14/Y14) -> 1153.8325 | AA14: =(Q14/100*S14/100) -> 0.015661707
A15: K435 | B15: Google - US | C15: 43000000017532129 | D15: airfrance | E15: Broad | F15: Air France Branded | G15: Air France Website | H15: uncategorized | J15: Unassigned | K15: Paused | L15: 10 | M15: 907 | N15: 235.11249 | O15: 0.25921995 | P15: 4352 | Q15: 20.840993 | R15: 1.0105836 | S15: 2.8665932 | T15: =N15/Y15 -> 9.0427883 | U15: 48551.15 | V15: =N15 -> 235.11249 | W15: =U15-V15 -> 48316.038 | X15: =IF(V15=0,0,(U15-V15)/V15) -> 205.50179 | Y15: 26 | Z15: =IF(Y15=0,"NA",U15/Y15) -> 1867.3519 | AA15: =(Q15/100*S15/100) -> 0.0059742647
A16: K1122 | B16: Overture - US | C16: 43000000014278804 | D16: cdg flight | E16: Standard | F16: Unassigned | G16: Unassigned | H16: paris | I16: Position 2-5 Bid Strategy | J16: Unassigned | K16: Paused | L16: 0.125 | M16: 18 | N16: 4.75 | O16: 0.26388889 | P16: 169 | Q16: 10.650888 | R16: 1.6621302 | S16: 5.5555556 | T16: =N16/Y16 -> 4.75 | U16: 896.75 | V16: =N16 -> 4.75 | W16: =U16-V16 -> 892 | X16: =IF(V16=0,0,(U16-V16)/V16) -> 187.78947 | Y16: 1 | Z16: =IF(Y16=0,"NA",U16/Y16) -> 896.75 | AA16: =(Q16/100*S16/100) -> 0.0059171598
A17: K435 | B17: Google - US | C17: 43000000017532133 | D17: airfrance us | E17: Broad | F17: Air France Branded | G17: Air France Website | H17: uncategorized | J17: Unassigned | K17: Live | L17: 10 | M17: 207 | N17: 30.787498 | O17: 0.14873187 | P17: 730 | Q17: 28.356164 | R17: 1 | S17: 2.4154589 | T17: =N17/Y17 -> 6.1574996 | U17: 5733.25 | V17: =N17 -> 30.787498 | W17: =U17-V17 -> 5702.4625 | X17: =IF(V17=0,0,(U17-V17)/V17) -> 185.22007 | Y17: 5 | Z17: =IF(Y17=0,"NA",U17/Y17) -> 1146.65 | AA17: =(Q17/100*S17/100) -> 0.0068493151
A18: K435 | B18: Google - US | C18: 43000000014113402 | D18: france airline ticket | E18: Broad | F18: Geo Targeted New York | G18: New York to France Sale | H18: uncategorized | I18: Position 5-10 Bid Strategy | J18: Unassigned | K18: Live | L18: 6.25 | M18: 2 | N18: 2.6875 | O18: 1.34375 | P18: 24 | Q18: 8.3333333 | R18: 1.5416667 | S18: 50 | T18: =N18/Y18 -> 2.6875 | U18: 494.7 | V18: =N18 -> 2.6875 | W18: =U18-V18 -> 492.0125 | X18: =IF(V18=0,0,(U18-V18)/V18) -> 183.07442 | Y18: 1 | Z18: =IF(Y18=0,"NA",U18/Y18) -> 494.7 | AA18: =(Q18/100*S18/100) -> 0.041666667
A19: K435 | B19: Google - US | C19: 43000000013069003 | D19: airfrance website | E19: Broad | F19: Air France Branded | G19: Air France Website | H19: uncategorized | I19: Position 2-5 Bid Strategy | J19: Unassigned | K19: Live | L19: 0.7125 | M19: 10 | N19: 9.9375 | O19: 0.99375 | P19: 80 | Q19: 12.5 | R19: 1.0625 | S19: 10 | T19: =N19/Y19 -> 9.9375 | U19: 1815.6 | V19: =N19 -> 9.9375 | W19: =U19-V19 -> 1805.6625 | X19: =IF(V19=0,0,(U19-V19)/V19) -> 181.70189 | Y19: 1 | Z19: =IF(Y19=0,"NA",U19/Y19) -> 1815.6 | AA19: =(Q19/100*S19/100) -> 0.0125
A20: K1123 | B20: Overture - Global | C20: 43000000005420920 | D20: airplane france ticket | E20: Advanced | F20: Unassigned | G20: Unassigned | H20: airline | I20: Position 1-2 Target | J20: Unassigned | K20: Paused | L20: 0.4375 | M20: 16 | N20: 8.3125 | O20: 0.51953125 | P20: 6073 | Q20: 0.26346122 | R20: 2.4634283 | S20: 6.25 | T20: =N20/Y20 -> 8.3125 | U20: 1473.9 | V20: =N20 -> 8.3125 | W20: =U20-V20 -> 1465.5875 | X20: =IF(V20=0,0,(U20-V20)/V20) -> 176.31128 | Y20: 1 | Z20: =IF(Y20=0,"NA",U20/Y20) -> 1473.9 | AA20: =(Q20/100*S20/100) -> 0.00016466326
A21: K435 | B21: Google - US | C21: 43000000014115425 | D21: france airfare sale | E21: Broad | F21: Geo Targeted Miami | G21: Miami to France Sale | H21: uncategorized | I21: Position 5-10 Bid Strategy | J21: Unassigned | K21: Paused | L21: 6.25 | M21: 1 | N21: 2.7625 | O21: 2.7625 | P21: 2 | Q21: 50 | R21: 1 | S21: 100 | T21: =N21/Y21 -> 2.7625 | U21: 470.05 | V21: =N21 -> 2.7625 | W21: =U21-V21 -> 467.2875 | X21: =IF(V21=0,0,(U21-V21)/V21) -> 169.15385 | Y21: 1 | Z21: =IF(Y21=0,"NA",U21/Y21) -> 470.05 | AA21: =(Q21/100*S21/100) -> 0.5
A22: K1123 | B22: Overture - Global | C22: 43000000005421434 | D22: air france schedule | E22: Advanced | F22: Unassigned | G22: Unassigned | H22: airfrance | I22: Position 1-2 Target | J22: Unassigned | K22: Paused | L22: 0.325 | M22: 30 | N22: 10.7125 | O22: 0.35708333 | P22: 2192 | Q22: 1.3686131 | R22: 1.5193431 | S22: 3.3333333 | T22: =N22/Y22 -> 10.7125 | U22: 1785 | V22: =N22 -> 10.7125 | W22: =U22-V22 -> 1774.2875 | X22: =IF(V22=0,0,(U22-V22)/V22) -> 165.62778 | Y22: 1 | Z22: =IF(Y22=0,"NA",U22/Y22) -> 1785 | AA22: =(Q22/100*S22/100) -> 0.00045620438
A23: K1123 | B23: Overture - Global | C23: 43000000009683629 | D23: airfare to tahiti | E23: Standard | F23: Unassigned | G23: Unassigned | H23: tahiti | J23: Unassigned | K23: Paused | L23: 10 | M23: 6 | N23: 12.275 | O23: 2.0458333 | P23: 102 | Q23: 5.8823529 | R23: 4.1637255 | S23: 16.666667 | T23: =N23/Y23 -> 12.275 | U23: 1989 | V23: =N23 -> 12.275 | W23: =U23-V23 -> 1976.725 | X23: =IF(V23=0,0,(U23-V23)/V23) -> 161.03666 | Y23: 1 | Z23: =IF(Y23=0,"NA",U23/Y23) -> 1989 | AA23: =(Q23/100*S23/100) -> 0.0098039216
A24: K435 | B24: Google - US | C24: 43000000014122527 | D24: france flights | E24: Broad | F24: Geo Targeted DC | G24: DC to France Sale | H24: uncategorized | I24: Position 5-10 Bid Strategy | J24: Unassigned | K24: Unavailable | L24: 6.25 | M24: 6 | N24: 18.35 | O24: 3.0583333 | P24: 137 | Q24: 4.379562 | R24: 1.2026277 | S24: 50 | T24: =N24/Y24 -> 6.1166666 | U24: 2810.1 | V24: =N24 -> 18.35 | W24: =U24-V24 -> 2791.75 | X24: =IF(V24=0,0,(U24-V24)/V24) -> 152.13896 | Y24: 3 | Z24: =IF(Y24=0,"NA",U24/Y24) -> 936.7 | AA24: =(Q24/100*S24/100) -> 0.02189781
A25: K435 | B25: Google - US | C25: 43000000014201100 | D25: international airfares | E25: Broad | F25: Geo Targeted Detroit | G25: International Detroit | H25: uncategorized | I25: Position 5-10 Bid Strategy | J25: Unassigned | K25: Unavailable | L25: 6.25 | M25: 2 | N25: 6.6 | O25: 3.3 | P25: 79 | Q25: 2.5316456 | R25: 3.0050633 | S25: 50 | T25: =N25/Y25 -> 6.6 | U25: 923.95 | V25: =N25 -> 6.6 | W25: =U25-V25 -> 917.35 | X25: =IF(V25=0,0,(U25-V25)/V25) -> 138.99242 | Y25: 1 | Z25: =IF(Y25=0,"NA",U25/Y25) -> 923.95 | AA25: =(Q25/100*S25/100) -> 0.012658228
A26: K435 | B26: Google - US | C26: 43000000014113704 | D26: france air ticket | E26: Broad | F26: Geo Targeted New York | G26: New York to France Sale | H26: uncategorized | I26: Position 5-10 Bid Strategy | J26: Unassigned | K26: Live | L26: 6.25 | M26: 12 | N26: 19.4 | O26: 1.6166667 | P26: 116 | Q26: 10.344828 | R26: 1.0940517 | S26: 33.333333 | T26: =N26/Y26 -> 4.85 | U26: 2706.4 | V26: =N26 -> 19.4 | W26: =U26-V26 -> 2687 | X26: =IF(V26=0,0,(U26-V26)/V26) -> 138.50515 | Y26: 4 | Z26: =IF(Y26=0,"NA",U26/Y26) -> 676.6 | AA26: =(Q26/100*S26/100) -> 0.034482759
A27: K1122 | B27: Overture - US | C27: 43000000017532937 | D27: airfrance.com/us | E27: Standard | F27: Unassigned | G27: Unassigned | H27: airfrance | J27: Unassigned | K27: Paused | L27: 7.5 | M27: 17 | N27: 5.5874999 | O27: 0.32867646 | P27: 98 | Q27: 17.346939 | R27: 0.95918367 | S27: 5.8823529 | T27: =N27/Y27 -> 5.5874999 | U27: 778.6 | V27: =N27 -> 5.5874999 | W27: =U27-V27 -> 773.0125 | X27: =IF(V27=0,0,(U27-V27)/V27) -> 138.34676 | Y27: 1 | Z27: =IF(Y27=0,"NA",U27/Y27) -> 778.6 | AA27: =(Q27/100*S27/100) -> 0.010204082
A28: K435 | B28: Google - US | C28: 43000000014127450 | D28: paris cheap ticket | E28: Broad | F28: Geo Targeted Boston | G28: Boston to Paris Sale | H28: uncategorized | I28: Position 5-10 Bid Strategy | J28: Unassigned | K28: Paused | L28: 6.25 | M28: 3 | N28: 5.1375 | O28: 1.7125 | P28: 18 | Q28: 16.666667 | R28: 1.8333333 | S28: 33.333333 | T28: =N28/Y28 -> 5.1375 | U28: 676.6 | V28: =N28 -> 5.1375 | W28: =U28-V28 -> 671.4625 | X28: =IF(V28=0,0,(U28-V28)/V28) -> 130.6983 | Y28: 1 | Z28: =IF(Y28=0,"NA",U28/Y28) -> 676.6 | AA28: =(Q28/100*S28/100) -> 0.055555556
A29: K435 | B29: Google - US | C29: 43000000014118997 | D29: paris cheap flights | E29: Broad | F29: Geo Targeted Houston | G29: Houston to Paris Sale | H29: uncategorized | I29: Position 5-10 Bid Strategy | J29: Unassigned | K29: Paused | L29: 6.25 | M29: 21 | N29: 43.3875 | O29: 2.0660714 | P29: 174 | Q29: 12.068966 | R29: 1.3214368 | S29: 14.285714 | T29: =N29/Y29 -> 14.4625 | U29: 5638.05 | V29: =N29 -> 43.3875 | W29: =U29-V29 -> 5594.6625 | X29: =IF(V29=0,0,(U29-V29)/V29) -> 128.94641 | Y29: 3 | Z29: =IF(Y29=0,"NA",U29/Y29) -> 1879.35 | AA29: =(Q29/100*S29/100) -> 0.017241379
A30: K1122 | B30: Overture - US | C30: 43000000007003938 | D30: tunis | E30: Standard | F30: Unassigned | G30: Unassigned | H30: regional | I30: Position 1-4 Bid Strategy | J30: Unassigned | K30: Paused | L30: 11.25 | M30: 36 | N30: 25.375 | O30: 0.7048611 | P30: 832 | Q30: 4.3269231 | R30: 1.4074519 | S30: 8.3333333 | T30: =N30/Y30 -> 8.4583332 | U30: 3254.65 | V30: =N30 -> 25.375 | W30: =U30-V30 -> 3229.275 | X30: =IF(V30=0,0,(U30-V30)/V30) -> 127.26207 | Y30: 3 | Z30: =IF(Y30=0,"NA",U30/Y30) -> 1084.8833 | AA30: =(Q30/100*S30/100) -> 0.0036057692
A31: K2615 | B31: Yahoo - US | C31: 43000000029356928 | D31: france travel agency | E31: Standard | F31: Paris & France Terms | G31: France | H31: uncategorized | J31: Unassigned | K31: Live | L31: 6.25 | M31: 5 | N31: 15.4375 | O31: 3.0875 | P31: 167 | Q31: 2.994012 | R31: 1.2392814 | S31: 40 | T31: =N31/Y31 -> 7.71875 | U31: 1978.8 | V31: =N31 -> 15.4375 | W31: =U31-V31 -> 1963.3625 | X31: =IF(V31=0,0,(U31-V31)/V31) -> 127.18138 | Y31: 2 | Z31: =IF(Y31=0,"NA",U31/Y31) -> 989.4 | AA31: =(Q31/100*S31/100) -> 0.011976048
A32: K1175 | B32: Google - Global | C32: 43000000005663431 | D32: air france airlines | E32: Broad | F32: Air France Global Campaign | G32: Air France | H32: airfrance | I32: Position 1- 3 | J32: Unassigned | K32: Unavailable | L32: 1.25 | M32: 228 | N32: 55.312498 | O32: 0.24259868 | P32: 3747 | Q32: 6.0848679 | R32: 1.4166533 | S32: 1.754386 | T32: =N32/Y32 -> 13.828124 | U32: 6873.1 | V32: =N32 -> 55.312498 | W32: =U32-V32 -> 6817.7875 | X32: =IF(V32=0,0,(U32-V32)/V32) -> 123.25944 | Y32: 4 | Z32: =IF(Y32=0,"NA",U32/Y32) -> 1718.275 | AA32: =(Q32/100*S32/100) -> 0.0010675207
A33: K1175 | B33: Google - Global | C33: 43000000005663208 | D33: lyon airfare | E33: Broad | F33: Air France Global Campaign | G33: Lyon | H33: lyon | I33: Position 1- 3 | J33: Unassigned | K33: Unavailable | L33: 1.25 | M33: 12 | N33: 15.025 | O33: 1.2520833 | P33: 1030 | Q33: 1.1650485 | R33: 1.3096117 | S33: 16.666667 | T33: =N33/Y33 -> 7.5124999 | U33: 1836 | V33: =N33 -> 15.025 | W33: =U33-V33 -> 1820.975 | X33: =IF(V33=0,0,(U33-V33)/V33) -> 121.19634 | Y33: 2 | Z33: =IF(Y33=0,"NA",U33/Y33) -> 918 | AA33: =(Q33/100*S33/100) -> 0.0019417476
A34: K1123 | B34: Overture - Global | C34: 43000000005421430 | D34: air france web site | E34: Standard | F34: Unassigned | G34: Unassigned | H34: airfrance | I34: Position 1-2 Target | J34: Unassigned | K34: Paused | L34: 0.2875 | M34: 17 | N34: 5.3875 | O34: 0.31691176 | P34: 752 | Q34: 2.2606383 | R34: 2.2155585 | S34: 5.8823529 | T34: =N34/Y34 -> 5.3875 | U34: 637.5 | V34: =N34 -> 5.3875 | W34: =U34-V34 -> 632.1125 | X34: =IF(V34=0,0,(U34-V34)/V34) -> 117.32947 | Y34: 1 | Z34: =IF(Y34=0,"NA",U34/Y34) -> 637.5 | AA34: =(Q34/100*S34/100) -> 0.0013297872
A35: K1175 | B35: Google - Global | C35: 43000000005648300 | D35: cont:air france global campaign::france | E35: N/A | F35: Air France Global Campaign | G35: France | H35: uncategorized | J35: Unassigned | K35: Unavailable | L35: 7.5 | M35: 49 | N35: 11 | O35: 0.22448979 | P35: 4780 | Q35: 1.0251046 | R35: 4.844477 | S35: 2.0408163 | T35: =N35/Y35 -> 11 | U35: 1296.25 | V35: =N35 -> 11 | W35: =U35-V35 -> 1285.25 | X35: =IF(V35=0,0,(U35-V35)/V35) -> 116.84091 | Y35: 1 | Z35: =IF(Y35=0,"NA",U35/Y35) -> 1296.25 | AA35: =(Q35/100*S35/100) -> 0.00020920502
A36: K435 | B36: Google - US | C36: 43000000017532124 | D36: airfrance.com | E36: Broad | F36: Air France Branded | G36: Air France Website | H36: uncategorized | J36: Unassigned | K36: Live | L36: 10 | M36: 1260 | N36: 365.79999 | O36: 0.29031745 | P36: 6231 | Q36: 20.221473 | R36: 1.0051709 | S36: 2.5396825 | T36: =N36/Y36 -> 11.43125 | U36: 42538.25 | V36: =N36 -> 365.79999 | W36: =U36-V36 -> 42172.45 | X36: =IF(V36=0,0,(U36-V36)/V36) -> 115.28828 | Y36: 32 | Z36: =IF(Y36=0,"NA",U36/Y36) -> 1329.3203 | AA36: =(Q36/100*S36/100) -> 0.0051356123
A37: K2615 | B37: Yahoo - US | C37: 43000000027382609 | D37: airfrance.us | E37: Advanced | F37: Air France Branded | G37: Air France Website | H37: uncategorized | J37: Unassigned | K37: Live | L37: 7.5 | M37: 242 | N37: 87.574999 | O37: 0.36188016 | P37: 1371 | Q37: 17.651349 | R37: 1.0201313 | S37: 5.785124 | T37: =N37/Y37 -> 6.2553571 | U37: 10140.5 | V37: =N37 -> 87.574999 | W37: =U37-V37 -> 10052.925 | X37: =IF(V37=0,0,(U37-V37)/V37) -> 114.79218 | Y37: 14 | Z37: =IF(Y37=0,"NA",U37/Y37) -> 724.32143 | AA37: =(Q37/100*S37/100) -> 0.010211524
A38: K435 | B38: Google - US | C38: 43000000013136095 | D38: book airfrance | E38: Broad | F38: Air France Branded | G38: Air France Brand | H38: uncategorized | I38: Position 1 -2 Target | J38: Unassigned | K38: Live | L38: 10 | M38: 4 | N38: 6 | O38: 1.5 | P38: 43 | Q38: 9.3023256 | R38: 1.0930233 | S38: 25 | T38: =N38/Y38 -> 6 | U38: 671.5 | V38: =N38 -> 6 | W38: =U38-V38 -> 665.5 | X38: =IF(V38=0,0,(U38-V38)/V38) -> 110.91667 | Y38: 1 | Z38: =IF(Y38=0,"NA",U38/Y38) -> 671.5 | AA38: =(Q38/100*S38/100) -> 0.023255814
A39: K1175 | B39: Google - Global | C39: 43000000005663350 | D39: nice flight | E39: Broad | F39: Air France Global Campaign | G39: Nice | H39: nice | I39: Position 1- 3 | J39: Unassigned | K39: Unavailable | L39: 1.25 | M39: 28 | N39: 36.425 | O39: 1.3008928 | P39: 2356 | Q39: 1.188455 | R39: 1.5467317 | S39: 10.714286 | T39: =N39/Y39 -> 12.141667 | U39: 3944 | V39: =N39 -> 36.425 | W39: =U39-V39 -> 3907.575 | X39: =IF(V39=0,0,(U39-V39)/V39) -> 107.27728 | Y39: 3 | Z39: =IF(Y39=0,"NA",U39/Y39) -> 1314.6667 | AA39: =(Q39/100*S39/100) -> 0.0012733447
A40: K435 | B40: Google - US | C40: 43000000017532142 | D40: airfrance.us | E40: Broad | F40: Air France Branded | G40: Air France Website | H40: uncategorized | J40: Unassigned | K40: Live | L40: 10 | M40: 25 | N40: 6.95 | O40: 0.278 | P40: 132 | Q40: 18.939394 | R40: 1 | S40: 4 | T40: =N40/Y40 -> 6.95 | U40: 751.4 | V40: =N40 -> 6.95 | W40: =U40-V40 -> 744.45 | X40: =IF(V40=0,0,(U40-V40)/V40) -> 107.11511 | Y40: 1 | Z40: =IF(Y40=0,"NA",U40/Y40) -> 751.4 | AA40: =(Q40/100*S40/100) -> 0.0075757576
A41: K2615 | B41: Yahoo - US | C41: 43000000039658517 | D41: rome travel | E41: Advanced | F41: Western Europe Destinations | G41: Rome | H41: uncategorized | J41: Unassigned | K41: Live | L41: 2.7 | M41: 27 | N41: 56.4125 | O41: 2.0893518 | P41: 1051 | Q41: 2.5689819 | R41: 2.8635585 | S41: 14.814815 | T41: =N41/Y41 -> 14.103125 | U41: 5729 | V41: =N41 -> 56.4125 | W41: =U41-V41 -> 5672.5875 | X41: =IF(V41=0,0,(U41-V41)/V41) -> 100.55551 | Y41: 4 | Z41: =IF(Y41=0,"NA",U41/Y41) -> 1432.25 | AA41: =(Q41/100*S41/100) -> 0.0038058991
A42: K435 | B42: Google - US | C42: 43000000007147583 | D42: rabat flights | E42: Broad | F42: Google_Yearlong 2006 | G42: Google|rabat | H42: uncategorized | I42: Postiion 1-4 Bid Strategy | J42: Unassigned | K42: Paused | L42: 6.25 | M42: 11 | N42: 14.075 | O42: 1.2795455 | P42: 361 | Q42: 3.0470914 | R42: 1.1379501 | S42: 9.0909091 | T42: =N42/Y42 -> 14.075 | U42: 1402.5 | V42: =N42 -> 14.075 | W42: =U42-V42 -> 1388.425 | X42: =IF(V42=0,0,(U42-V42)/V42) -> 98.644761 | Y42: 1 | Z42: =IF(Y42=0,"NA",U42/Y42) -> 1402.5 | AA42: =(Q42/100*S42/100) -> 0.0027700831
A43: K2615 | B43: Yahoo - US | C43: 43000000027382580 | D43: airfrance,com | E43: Advanced | F43: Air France Branded | G43: Air France Website | H43: uncategorized | J43: Unassigned | K43: Live | L43: 7.5 | M43: 48 | N43: 7.3125 | O43: 0.15234375 | P43: 298 | Q43: 16.107383 | R43: 1 | S43: 2.0833333 | T43: =N43/Y43 -> 7.3125 | U43: 718.25 | V43: =N43 -> 7.3125 | W43: =U43-V43 -> 710.9375 | X43: =IF(V43=0,0,(U43-V43)/V43) -> 97.222222 | Y43: 1 | Z43: =IF(Y43=0,"NA",U43/Y43) -> 718.25 | AA43: =(Q43/100*S43/100) -> 0.0033557047
A44: K1123 | B44: Overture - Global | C44: 43000000005420948 | D44: air france phone number | E44: Standard | F44: Unassigned | G44: Unassigned | H44: airfrance | I44: Position 1-2 Target | J44: Unassigned | K44: Paused | L44: 0.125 | M44: 65 | N44: 9.7124999 | O44: 0.14942307 | P44: 1831 | Q44: 3.5499727 | R44: 2.4816494 | S44: 1.5384615 | T44: =N44/Y44 -> 9.7124999 | U44: 947.75 | V44: =N44 -> 9.7124999 | W44: =U44-V44 -> 938.0375 | X44: =IF(V44=0,0,(U44-V44)/V44) -> 96.580439 | Y44: 1 | Z44: =IF(Y44=0,"NA",U44/Y44) -> 947.75 | AA44: =(Q44/100*S44/100) -> 0.00054614965
A45: K1122 | B45: Overture - US | C45: 43000000014278767 | D45: airline ticket to france | E45: Standard | F45: Unassigned | G45: Unassigned | H45: france | I45: Position 1-4 Bid Strategy | J45: Unassigned | K45: Paused | L45: 1.2625 | M45: 14 | N45: 10.2625 | O45: 0.73303571 | P45: 225 | Q45: 6.2222222 | R45: 2.1017778 | S45: 7.1428571 | T45: =N45/Y45 -> 10.2625 | U45: 991.1 | V45: =N45 -> 10.2625 | W45: =U45-V45 -> 980.8375 | X45: =IF(V45=0,0,(U45-V45)/V45) -> 95.574909 | Y45: 1 | Z45: =IF(Y45=0,"NA",U45/Y45) -> 991.1 | AA45: =(Q45/100*S45/100) -> 0.0044444444
A46: K1175 | B46: Google - Global | C46: 43000000005663191 | D46: airfrance com | E46: Broad | F46: Air France Global Campaign | G46: Air France Website | H46: airfrancewebsite | I46: Position 1- 3 | J46: Unassigned | K46: Unavailable | L46: 2.5 | M46: 548 | N46: 247.9375 | O46: 0.45244069 | P46: 2919 | Q46: 18.773553 | R46: 1.4655361 | S46: 2.189781 | T46: =N46/Y46 -> 20.661458 | U46: 23041.8 | V46: =N46 -> 247.9375 | W46: =U46-V46 -> 22793.863 | X46: =IF(V46=0,0,(U46-V46)/V46) -> 91.933906 | Y46: 12 | Z46: =IF(Y46=0,"NA",U46/Y46) -> 1920.15 | AA46: =(Q46/100*S46/100) -> 0.0041109969
A47: K1123 | B47: Overture - Global | C47: 43000000005421358 | D47: new york to paris | E47: Advanced | F47: Unassigned | G47: Unassigned | H47: paris | I47: Position 1-2 Target | J47: Unassigned | K47: Sent | L47: 0.725 | M47: 39 | N47: 24.4375 | O47: 0.62660256 | P47: 2364 | Q47: 1.6497462 | R47: 3.6335448 | S47: 2.5641026 | T47: =N47/Y47 -> 24.4375 | U47: 2226.15 | V47: =N47 -> 24.4375 | W47: =U47-V47 -> 2201.7125 | X47: =IF(V47=0,0,(U47-V47)/V47) -> 90.095652 | Y47: 1 | Z47: =IF(Y47=0,"NA",U47/Y47) -> 2226.15 | AA47: =(Q47/100*S47/100) -> 0.00042301184
A48: K435 | B48: Google - US | C48: 43000000005277892 | D48: cont:google_yearlong 2006::google|europe | E48: N/A | F48: Google_Yearlong 2006 | G48: Google|Europe | H48: uncategorized | J48: Unassigned | K48: Unavailable | L48: 7.5 | M48: 112 | N48: 31.649999 | O48: 0.28258927 | P48: 157285 | Q48: 0.071208316 | R48: 2.3088775 | S48: 0.89285714 | T48: =N48/Y48 -> 31.649999 | U48: 2882.35 | V48: =N48 -> 31.649999 | W48: =U48-V48 -> 2850.7 | X48: =IF(V48=0,0,(U48-V48)/V48) -> 90.069514 | Y48: 1 | Z48: =IF(Y48=0,"NA",U48/Y48) -> 2882.35 | AA48: =(Q48/100*S48/100) -> 6.3578854e-06
A49: K435 | B49: Google - US | C49: 43000000013069225 | D49: airfrance | E49: Broad | F49: Air France Branded | G49: Air France Brand | H49: uncategorized | J49: Unassigned | K49: Live | L49: 27.5 | M49: 11789 | N49: 2412.5125 | O49: 0.20464098 | P49: 78814 | Q49: 14.958002 | R49: 1.1294811 | S49: 1.8491814 | T49: =N49/Y49 -> 11.066571 | U49: 216915.75 | V49: =N49 -> 2412.5125 | W49: =U49-V49 -> 214503.24 | X49: =IF(V49=0,0,(U49-V49)/V49) -> 88.9128 | Y49: 218 | Z49: =IF(Y49=0,"NA",U49/Y49) -> 995.02638 | AA49: =(Q49/100*S49/100) -> 0.002766006
A50: K1123 | B50: Overture - Global | C50: 43000000005421406 | D50: cheap travel france | E50: Advanced | F50: Unassigned | G50: Unassigned | H50: france | I50: Position 1-2 Target | J50: Unassigned | K50: Sent | L50: 0.475 | M50: 20 | N50: 10.4 | O50: 0.52 | P50: 501 | Q50: 3.992016 | R50: 2.1215569 | S50: 5 | T50: =N50/Y50 -> 10.4 | U50: 935 | V50: =N50 -> 10.4 | W50: =U50-V50 -> 924.6 | X50: =IF(V50=0,0,(U50-V50)/V50) -> 88.903846 | Y50: 1 | Z50: =IF(Y50=0,"NA",U50/Y50) -> 935 | AA50: =(Q50/100*S50/100) -> 0.001996008
A51: K435 | B51: Google - US | C51: 43000000014113121 | D51: paris flight | E51: Broad | F51: Geo Targeted Philadelphia | G51: Philadelphia to Paris Sale | H51: uncategorized | I51: Position 5-10 Bid Strategy | J51: Unassigned | K51: Paused | L51: 6.25 | M51: 2 | N51: 4.8875 | O51: 2.44375 | P51: 38 | Q51: 5.2631579 | R51: 1.7089474 | S51: 50 | T51: =N51/Y51 -> 4.8875 | U51: 434.35 | V51: =N51 -> 4.8875 | W51: =U51-V51 -> 429.4625 | X51: =IF(V51=0,0,(U51-V51)/V51) -> 87.869565 | Y51: 1 | Z51: =IF(Y51=0,"NA",U51/Y51) -> 434.35 | AA51: =(Q51/100*S51/100) -> 0.026315789
A52: K1123 | B52: Overture - Global | C52: 43000000005421034 | D52: airfrance.us | E52: Advanced | F52: Unassigned | G52: Unassigned | H52: airfrancewebsite | I52: Position 1-2 Target | J52: Unassigned | K52: Paused | L52: 0.1375 | M52: 207 | N52: 34.874998 | O52: 0.16847825 | P52: 1100 | Q52: 18.818182 | R52: 1.1695455 | S52: 1.9323671 | T52: =N52/Y52 -> 8.7187494 | U52: 3035.35 | V52: =N52 -> 34.874998 | W52: =U52-V52 -> 3000.475 | X52: =IF(V52=0,0,(U52-V52)/V52) -> 86.035131 | Y52: 4 | Z52: =IF(Y52=0,"NA",U52/Y52) -> 758.8375 | AA52: =(Q52/100*S52/100) -> 0.0036363636
A53: K435 | B53: Google - US | C53: 43000000013068975 | D53: airfrance airlines | E53: Broad | F53: Air France Branded | G53: Air France Brand | H53: uncategorized | I53: Position 1 -2 Target | J53: Unassigned | K53: Live | L53: 0.35 | M53: 116 | N53: 59.349999 | O53: 0.51163793 | P53: 776 | Q53: 14.948454 | R53: 1.3006959 | S53: 4.3103448 | T53: =N53/Y53 -> 11.87 | U53: 5146.75 | V53: =N53 -> 59.349999 | W53: =U53-V53 -> 5087.4 | X53: =IF(V53=0,0,(U53-V53)/V53) -> 85.718619 | Y53: 5 | Z53: =IF(Y53=0,"NA",U53/Y53) -> 1029.35 | AA53: =(Q53/100*S53/100) -> 0.006443299
A54: K435 | B54: Google - US | C54: 43000000014113546 | D54: florence cheap tickets | E54: Broad | F54: Geo Targeted New York | G54: New York to Florence Sale | H54: uncategorized | I54: Position 5-10 Bid Strategy | J54: Unassigned | K54: Unavailable | L54: 6.25 | M54: 3 | N54: 5.975 | O54: 1.9916667 | P54: 6 | Q54: 50 | R54: 2 | S54: 33.333333 | T54: =N54/Y54 -> 5.975 | U54: 490.45 | V54: =N54 -> 5.975 | W54: =U54-V54 -> 484.475 | X54: =IF(V54=0,0,(U54-V54)/V54) -> 81.083682 | Y54: 1 | Z54: =IF(Y54=0,"NA",U54/Y54) -> 490.45 | AA54: =(Q54/100*S54/100) -> 0.16666667
A55: K2615 | B55: Yahoo - US | C55: 43000000027413323 | D55: air france travel | E55: Advanced | F55: Air France Branded | G55: Air France Brand | H55: uncategorized | J55: Unassigned | K55: Live | L55: 6.25 | M55: 24 | N55: 33.7875 | O55: 1.4078125 | P55: 1171 | Q55: 2.0495303 | R55: 3.0695218 | S55: 4.1666667 | T55: =N55/Y55 -> 33.7875 | U55: 2772.7 | V55: =N55 -> 33.7875 | W55: =U55-V55 -> 2738.9125 | X55: =IF(V55=0,0,(U55-V55)/V55) -> 81.062893 | Y55: 1 | Z55: =IF(Y55=0,"NA",U55/Y55) -> 2772.7 | AA55: =(Q55/100*S55/100) -> 0.00085397096
A56: K435 | B56: Google - US | C56: 43000000005278156 | D56: rome fare | E56: Broad | F56: Google_Yearlong 2006 | G56: Google|Rome | H56: uncategorized | I56: Postiion 1-4 Bid Strategy | J56: Unassigned | K56: Paused | L56: 6.25 | M56: 14 | N56: 20.1125 | O56: 1.4366071 | P56: 310 | Q56: 4.516129 | R56: 1.4922581 | S56: 7.1428571 | T56: =N56/Y56 -> 20.1125 | U56: 1489.2 | V56: =N56 -> 20.1125 | W56: =U56-V56 -> 1469.0875 | X56: =IF(V56=0,0,(U56-V56)/V56) -> 73.043506 | Y56: 1 | Z56: =IF(Y56=0,"NA",U56/Y56) -> 1489.2 | AA56: =(Q56/100*S56/100) -> 0.0032258065
A57: K435 | B57: Google - US | C57: 43000000013069140 | D57: air france com | E57: Broad | F57: Air France Branded | G57: Air France Website | H57: uncategorized | I57: Postiion 1-4 Bid Strategy | J57: Unassigned | K57: Live | L57: 15 | M57: 6119 | N57: 1905.8624 | O57: 0.31146632 | P57: 15166 | Q57: 40.346828 | R57: 1.0388712 | S57: 1.9120771 | T57: =N57/Y57 -> 16.289423 | U57: 132065.35 | V57: =N57 -> 1905.8624 | W57: =U57-V57 -> 130159.49 | X57: =IF(V57=0,0,(U57-V57)/V57) -> 68.294272 | Y57: 117 | Z57: =IF(Y57=0,"NA",U57/Y57) -> 1128.7637 | AA57: =(Q57/100*S57/100) -> 0.0077146248
A58: K2966 | B58: MSN - US | C58: 43000000031840336 | D58: air travel in france | E58: Broad | F58: Air France Brand & French Destinations | G58: France | H58: uncategorized | J58: Unassigned | K58: Live | L58: 0 | M58: 2 | N58: 7.5625 | O58: 3.78125 | P58: 35 | Q58: 5.7142857 | R58: 6.0845714 | S58: 50 | T58: =N58/Y58 -> 7.5625 | U58: 512.55 | V58: =N58 -> 7.5625 | W58: =U58-V58 -> 504.9875 | X58: =IF(V58=0,0,(U58-V58)/V58) -> 66.775207 | Y58: 1 | Z58: =IF(Y58=0,"NA",U58/Y58) -> 512.55 | AA58: =(Q58/100*S58/100) -> 0.028571429
A59: K435 | B59: Google - US | C59: 43000000017532123 | D59: airfrance usa | E59: Broad | F59: Air France Branded | G59: Air France Website | H59: uncategorized | J59: Unassigned | K59: Live | L59: 10 | M59: 57 | N59: 15 | O59: 0.26315789 | P59: 200 | Q59: 28.5 | R59: 1.005 | S59: 1.754386 | T59: =N59/Y59 -> 15 | U59: 1008.95 | V59: =N59 -> 15 | W59: =U59-V59 -> 993.95 | X59: =IF(V59=0,0,(U59-V59)/V59) -> 66.263335 | Y59: 1 | Z59: =IF(Y59=0,"NA",U59/Y59) -> 1008.95 | AA59: =(Q59/100*S59/100) -> 0.005
A60: K435 | B60: Google - US | C60: 43000000014122844 | D60: france cheap tickets | E60: Broad | F60: Geo Targeted DC | G60: DC to France Sale | H60: uncategorized | I60: Position 5-10 Bid Strategy | J60: Unassigned | K60: Unavailable | L60: 6.25 | M60: 3 | N60: 7.3875 | O60: 2.4625 | P60: 22 | Q60: 13.636364 | R60: 1.09 | S60: 33.333333 | T60: =N60/Y60 -> 7.3875 | U60: 490.45 | V60: =N60 -> 7.3875 | W60: =U60-V60 -> 483.0625 | X60: =IF(V60=0,0,(U60-V60)/V60) -> 65.389171 | Y60: 1 | Z60: =IF(Y60=0,"NA",U60/Y60) -> 490.45 | AA60: =(Q60/100*S60/100) -> 0.045454545
A61: K1123 | B61: Overture - Global | C61: 43000000005421121 | D61: boston to paris | E61: Advanced | F61: Unassigned | G61: Unassigned | H61: paris | I61: Position 1-2 Target | J61: Unassigned | K61: Sent | L61: 0.725 | M61: 23 | N61: 12.5875 | O61: 0.5472826 | P61: 699 | Q61: 3.2904149 | R61: 2.4997139 | S61: 4.3478261 | T61: =N61/Y61 -> 12.5875 | U61: 806.65 | V61: =N61 -> 12.5875 | W61: =U61-V61 -> 794.0625 | X61: =IF(V61=0,0,(U61-V61)/V61) -> 63.083417 | Y61: 1 | Z61: =IF(Y61=0,"NA",U61/Y61) -> 806.65 | AA61: =(Q61/100*S61/100) -> 0.0014306152
A62: K435 | B62: Google - US | C62: 43000000014126195 | D62: paris ticket | E62: Broad | F62: Geo Targeted Chicago | G62: Chicago to Paris Sale | H62: uncategorized | I62: Position 5-10 Bid Strategy | J62: Unassigned | K62: Unavailable | L62: 6.25 | M62: 6 | N62: 14.725 | O62: 2.4541667 | P62: 97 | Q62: 6.185567 | R62: 1.2561856 | S62: 16.666667 | T62: =N62/Y62 -> 14.725 | U62: 940.95 | V62: =N62 -> 14.725 | W62: =U62-V62 -> 926.225 | X62: =IF(V62=0,0,(U62-V62)/V62) -> 62.901528 | Y62: 1 | Z62: =IF(Y62=0,"NA",U62/Y62) -> 940.95 | AA62: =(Q62/100*S62/100) -> 0.010309278
A63: K1175 | B63: Google - Global | C63: 43000000005663215 | D63: air france com | E63: Broad | F63: Air France Global Campaign | G63: Air France Website | H63: airfrancewebsite | I63: Position 1- 3 | J63: Unassigned | K63: Unavailable | L63: 0 | M63: 661 | N63: 202.8 | O63: 0.30680786 | P63: 2703 | Q63: 24.45431 | R63: 1.4758417 | S63: 1.5128593 | T63: =N63/Y63 -> 20.28 | U63: 11950.15 | V63: =N63 -> 202.8 | W63: =U63-V63 -> 11747.35 | X63: =IF(V63=0,0,(U63-V63)/V63) -> 57.92579 | Y63: 10 | Z63: =IF(Y63=0,"NA",U63/Y63) -> 1195.015 | AA63: =(Q63/100*S63/100) -> 0.003699593
A64: K1123 | B64: Overture - Global | C64: 43000000005420972 | D64: cheap airline ticket to france | E64: Advanced | F64: Unassigned | G64: Unassigned | H64: france | I64: Position 1-2 Target | J64: Unassigned | K64: Sent | L64: 0.3125 | M64: 26 | N64: 16.0625 | O64: 0.61778845 | P64: 9279 | Q64: 0.28020261 | R64: 2.3996767 | S64: 3.8461538 | T64: =N64/Y64 -> 16.0625 | U64: 935 | V64: =N64 -> 16.0625 | W64: =U64-V64 -> 918.9375 | X64: =IF(V64=0,0,(U64-V64)/V64) -> 57.210118 | Y64: 1 | Z64: =IF(Y64=0,"NA",U64/Y64) -> 935 | AA64: =(Q64/100*S64/100) -> 0.00010777023
A65: K1175 | B65: Google - Global | C65: 43000000019449245 | D65: air france com | E65: Broad | F65: Air France Brand & French Destinations | G65: Air France Website | H65: uncategorized | J65: Unassigned | K65: Unavailable | L65: 5 | M65: 568 | N65: 263.125 | O65: 0.46324824 | P65: 1710 | Q65: 33.216374 | R65: 1.1094152 | S65: 2.2887324 | T65: =N65/Y65 -> 20.240385 | U65: 15011 | V65: =N65 -> 263.125 | W65: =U65-V65 -> 14747.875 | X65: =IF(V65=0,0,(U65-V65)/V65) -> 56.048931 | Y65: 13 | Z65: =IF(Y65=0,"NA",U65/Y65) -> 1154.6923 | AA65: =(Q65/100*S65/100) -> 0.0076023392
A66: K1123 | B66: Overture - Global | C66: 43000000008202838 | D66: airfrance.com | E66: Standard | F66: Unassigned | G66: Unassigned | H66: airfrancewebsite | J66: Unassigned | K66: Paused | L66: 8.75 | M66: 2010 | N66: 574.24999 | O66: 0.28569651 | P66: 37801 | Q66: 5.3173196 | R66: 1.1638951 | S66: 1.7910448 | T66: =N66/Y66 -> 15.951389 | U66: 32613.65 | V66: =N66 -> 574.24999 | W66: =U66-V66 -> 32039.4 | X66: =IF(V66=0,0,(U66-V66)/V66) -> 55.793471 | Y66: 36 | Z66: =IF(Y66=0,"NA",U66/Y66) -> 905.93472 | AA66: =(Q66/100*S66/100) -> 0.00095235576
A67: K435 | B67: Google - US | C67: 43000000013069207 | D67: air france website | E67: Broad | F67: Air France Branded | G67: Air France Website | H67: uncategorized | I67: Position 2-5 Bid Strategy | J67: Unassigned | K67: Live | L67: 0.3 | M67: 187 | N67: 66.562498 | O67: 0.35594919 | P67: 899 | Q67: 20.80089 | R67: 1.1424472 | S67: 2.1390374 | T67: =N67/Y67 -> 16.640625 | U67: 3621 | V67: =N67 -> 66.562498 | W67: =U67-V67 -> 3554.4375 | X67: =IF(V67=0,0,(U67-V67)/V67) -> 53.400002 | Y67: 4 | Z67: =IF(Y67=0,"NA",U67/Y67) -> 905.25 | AA67: =(Q67/100*S67/100) -> 0.0044493882
A68: K435 | B68: Google - US | C68: 43000000014113639 | D68: paris air fares | E68: Broad | F68: Geo Targeted New York | G68: New York to Paris Sale | H68: uncategorized | I68: Position 5-10 Bid Strategy | J68: Unassigned | K68: Live | L68: 6.25 | M68: 10 | N68: 25.0125 | O68: 2.50125 | P68: 41 | Q68: 24.390244 | R68: 1.194878 | S68: 10 | T68: =N68/Y68 -> 25.0125 | U68: 1360 | V68: =N68 -> 25.0125 | W68: =U68-V68 -> 1334.9875 | X68: =IF(V68=0,0,(U68-V68)/V68) -> 53.372814 | Y68: 1 | Z68: =IF(Y68=0,"NA",U68/Y68) -> 1360 | AA68: =(Q68/100*S68/100) -> 0.024390244
A69: K1122 | B69: Overture - US | C69: 43000000006981635 | D69: europe ticket | E69: Standard | F69: Unassigned | G69: Unassigned | H69: europe2 | I69: Position 1-4 Bid Strategy | J69: Unassigned | K69: Paused | L69: 0.8625 | M69: 123 | N69: 81.312499 | O69: 0.66107722 | P69: 3325 | Q69: 3.6992481 | R69: 2.1720902 | S69: 1.6260163 | T69: =N69/Y69 -> 40.656249 | U69: 4187.1 | V69: =N69 -> 81.312499 | W69: =U69-V69 -> 4105.7875 | X69: =IF(V69=0,0,(U69-V69)/V69) -> 50.493929 | Y69: 2 | Z69: =IF(Y69=0,"NA",U69/Y69) -> 2093.55 | AA69: =(Q69/100*S69/100) -> 0.00060150376
A70: K435 | B70: Google - US | C70: 43000000014118692 | D70: paris air flight | E70: Broad | F70: Geo Targeted Houston | G70: Houston to Paris Sale | H70: uncategorized | I70: Position 5-10 Bid Strategy | J70: Unassigned | K70: Paused | L70: 6.25 | M70: 4 | N70: 8.4875 | O70: 2.121875 | P70: 20 | Q70: 20 | R70: 1.35 | S70: 25 | T70: =N70/Y70 -> 8.4875 | U70: 426.7 | V70: =N70 -> 8.4875 | W70: =U70-V70 -> 418.2125 | X70: =IF(V70=0,0,(U70-V70)/V70) -> 49.273932 | Y70: 1 | Z70: =IF(Y70=0,"NA",U70/Y70) -> 426.7 | AA70: =(Q70/100*S70/100) -> 0.05
A71: K435 | B71: Google - US | C71: 43000000014113425 | D71: paris airfares | E71: Broad | F71: Geo Targeted New York | G71: New York to Paris Sale | H71: uncategorized | I71: Position 5-10 Bid Strategy | J71: Unassigned | K71: Live | L71: 6.25 | M71: 21 | N71: 50.2 | O71: 2.3904762 | P71: 195 | Q71: 10.769231 | R71: 1.8745641 | S71: 9.5238095 | T71: =N71/Y71 -> 25.1 | U71: 2450.55 | V71: =N71 -> 50.2 | W71: =U71-V71 -> 2400.35 | X71: =IF(V71=0,0,(U71-V71)/V71) -> 47.815737 | Y71: 2 | Z71: =IF(Y71=0,"NA",U71/Y71) -> 1225.275 | AA71: =(Q71/100*S71/100) -> 0.01025641
A72: K1175 | B72: Google - Global | C72: 43000000005663439 | D72: [air france] | E72: Exact | F72: Air France Global Campaign | G72: Air France | H72: airfrance | I72: Position 1- 3 | J72: Unassigned | K72: Unavailable | L72: 1.25 | M72: 11150 | N72: 4886.0999 | O72: 0.43821524 | P72: 107222 | Q72: 10.398985 | R72: 1.8312035 | S72: 1.5964126 | T72: =N72/Y72 -> 27.449999 | U72: 235965.95 | V72: =N72 -> 4886.0999 | W72: =U72-V72 -> 231079.85 | X72: =IF(V72=0,0,(U72-V72)/V72) -> 47.293313 | Y72: 178 | Z72: =IF(Y72=0,"NA",U72/Y72) -> 1325.6514 | AA72: =(Q72/100*S72/100) -> 0.0016601071
A73: K1123 | B73: Overture - Global | C73: 43000000008202787 | D73: air france fr | E73: Advanced | F73: Unassigned | G73: Unassigned | H73: airfrancewebsite | J73: Unassigned | K73: Paused | L73: 7.5 | M73: 60 | N73: 16.75 | O73: 0.27916666 | P73: 3370 | Q73: 1.7804154 | R73: 1.0401484 | S73: 1.6666667 | T73: =N73/Y73 -> 16.75 | U73: 769.25 | V73: =N73 -> 16.75 | W73: =U73-V73 -> 752.5 | X73: =IF(V73=0,0,(U73-V73)/V73) -> 44.925374 | Y73: 1 | Z73: =IF(Y73=0,"NA",U73/Y73) -> 769.25 | AA73: =(Q73/100*S73/100) -> 0.00029673591
A74: K435 | B74: Google - US | C74: 43000000013068288 | D74: airfrance com | E74: Broad | F74: Air France Branded | G74: Air France Website | H74: uncategorized | I74: Postiion 1-4 Bid Strategy | J74: Unassigned | K74: Live | L74: 11.5 | M74: 3853 | N74: 1670.7375 | O74: 0.4336199 | P74: 22668 | Q74: 16.99753 | R74: 1.0531719 | S74: 1.6610433 | T74: =N74/Y74 -> 26.105273 | U74: 76245.85 | V74: =N74 -> 1670.7375 | W74: =U74-V74 -> 74575.113 | X74: =IF(V74=0,0,(U74-V74)/V74) -> 44.636045 | Y74: 64 | Z74: =IF(Y74=0,"NA",U74/Y74) -> 1191.3414 | AA74: =(Q74/100*S74/100) -> 0.0028233633
A75: K435 | B75: Google - US | C75: 43000000017532138 | D75: air france usa | E75: Broad | F75: Air France Branded | G75: Air France Website | H75: uncategorized | J75: Unassigned | K75: Live | L75: 10 | M75: 558 | N75: 241.1875 | O75: 0.43223566 | P75: 1602 | Q75: 34.831461 | R75: 1.0323533 | S75: 1.9713262 | T75: =N75/Y75 -> 21.926136 | U75: 10767.8 | V75: =N75 -> 241.1875 | W75: =U75-V75 -> 10526.613 | X75: =IF(V75=0,0,(U75-V75)/V75) -> 43.644934 | Y75: 11 | Z75: =IF(Y75=0,"NA",U75/Y75) -> 978.89091 | AA75: =(Q75/100*S75/100) -> 0.006866417
A76: K1123 | B76: Overture - Global | C76: 43000000008202780 | D76: air france.com | E76: Advanced | F76: Unassigned | G76: Unassigned | H76: airfrancewebsite | J76: Unassigned | K76: Paused | L76: 8.75 | M76: 681 | N76: 130.27499 | O76: 0.19129955 | P76: 7996 | Q76: 8.5167584 | R76: 1.1776138 | S76: 1.0279001 | T76: =N76/Y76 -> 18.610713 | U76: 5767.25 | V76: =N76 -> 130.27499 | W76: =U76-V76 -> 5636.975 | X76: =IF(V76=0,0,(U76-V76)/V76) -> 43.269816 | Y76: 7 | Z76: =IF(Y76=0,"NA",U76/Y76) -> 823.89286 | AA76: =(Q76/100*S76/100) -> 0.00087543772
A77: K435 | B77: Google - US | C77: 43000000034321251 | D77: paris tickets | E77: Broad | F77: Geo Targeted Seattle | G77: Seattle to Paris Sale | H77: uncategorized | I77: Position 2-5 Bid Strategy | J77: Unassigned | K77: Paused | L77: 5 | M77: 12 | N77: 34.0875 | O77: 2.840625 | P77: 538 | Q77: 2.2304833 | R77: 1.6939405 | S77: 8.3333333 | T77: =N77/Y77 -> 34.0875 | U77: 1439.9 | V77: =N77 -> 34.0875 | W77: =U77-V77 -> 1405.8125 | X77: =IF(V77=0,0,(U77-V77)/V77) -> 41.241291 | Y77: 1 | Z77: =IF(Y77=0,"NA",U77/Y77) -> 1439.9 | AA77: =(Q77/100*S77/100) -> 0.0018587361
A78: K435 | B78: Google - US | C78: 43000000014113834 | D78: paris cheap air tickets | E78: Broad | F78: Geo Targeted New York | G78: New York to Paris Sale | H78: uncategorized | I78: Position 5-10 Bid Strategy | J78: Unassigned | K78: Live | L78: 6.25 | M78: 5 | N78: 12.1125 | O78: 2.4225 | P78: 7 | Q78: 71.428571 | R78: 1 | S78: 20 | T78: =N78/Y78 -> 12.1125 | U78: 494.7 | V78: =N78 -> 12.1125 | W78: =U78-V78 -> 482.5875 | X78: =IF(V78=0,0,(U78-V78)/V78) -> 39.842105 | Y78: 1 | Z78: =IF(Y78=0,"NA",U78/Y78) -> 494.7 | AA78: =(Q78/100*S78/100) -> 0.14285714
A79: K1175 | B79: Google - Global | C79: 43000000009028069 | D79: paris airline | E79: Broad | F79: Air France Global Campaign | G79: Tour de France | H79: uncategorized | J79: Unassigned | K79: Unavailable | L79: 6.25 | M79: 16 | N79: 27.425 | O79: 1.7140625 | P79: 1602 | Q79: 0.99875156 | R79: 1.240824 | S79: 6.25 | T79: =N79/Y79 -> 27.425 | U79: 1098.2 | V79: =N79 -> 27.425 | W79: =U79-V79 -> 1070.775 | X79: =IF(V79=0,0,(U79-V79)/V79) -> 39.043756 | Y79: 1 | Z79: =IF(Y79=0,"NA",U79/Y79) -> 1098.2 | AA79: =(Q79/100*S79/100) -> 0.00062421973
A80: K435 | B80: Google - US | C80: 43000000014113617 | D80: france airlines | E80: Broad | F80: Geo Targeted New York | G80: New York to France Sale | H80: uncategorized | I80: Postiion 1-4 Bid Strategy | J80: Unassigned | K80: Live | L80: 6.25 | M80: 119 | N80: 286.3 | O80: 2.4058824 | P80: 4403 | Q80: 2.7027027 | R80: 1.6807745 | S80: 7.5630252 | T80: =N80/Y80 -> 31.811111 | U80: 11301.6 | V80: =N80 -> 286.3 | W80: =U80-V80 -> 11015.3 | X80: =IF(V80=0,0,(U80-V80)/V80) -> 38.474677 | Y80: 9 | Z80: =IF(Y80=0,"NA",U80/Y80) -> 1255.7333 | AA80: =(Q80/100*S80/100) -> 0.0020440609
A81: K435 | B81: Google - US | C81: 43000000014113896 | D81: france air flight | E81: Broad | F81: Geo Targeted New York | G81: New York to France Sale | H81: uncategorized | I81: Position 5-10 Bid Strategy | J81: Unassigned | K81: Live | L81: 6.25 | M81: 55 | N81: 41.399999 | O81: 0.75272726 | P81: 776 | Q81: 7.0876289 | R81: 1.0417397 | S81: 3.6363636 | T81: =N81/Y81 -> 20.7 | U81: 1616.7 | V81: =N81 -> 41.399999 | W81: =U81-V81 -> 1575.3 | X81: =IF(V81=0,0,(U81-V81)/V81) -> 38.050725 | Y81: 2 | Z81: =IF(Y81=0,"NA",U81/Y81) -> 808.35 | AA81: =(Q81/100*S81/100) -> 0.0025773196
A82: K435 | B82: Google - US | C82: 43000000014116465 | D82: france air flight | E82: Broad | F82: Geo Targeted Los Angeles | G82: Los Angeles to France Sale | H82: uncategorized | I82: Position 5-10 Bid Strategy | J82: Unassigned | K82: Unavailable | L82: 6.25 | M82: 9 | N82: 12.425 | O82: 1.3805555 | P82: 67 | Q82: 13.432836 | R82: 1.1358209 | S82: 11.111111 | T82: =N82/Y82 -> 12.425 | U82: 483.65 | V82: =N82 -> 12.425 | W82: =U82-V82 -> 471.225 | X82: =IF(V82=0,0,(U82-V82)/V82) -> 37.925553 | Y82: 1 | Z82: =IF(Y82=0,"NA",U82/Y82) -> 483.65 | AA82: =(Q82/100*S82/100) -> 0.014925373
A83: K435 | B83: Google - US | C83: 43000000013068726 | D83: [air france] | E83: Exact | F83: Air France Branded | G83: Air France Brand | H83: uncategorized | J83: Unassigned | K83: Live | L83: 27.5 | M83: 30418 | N83: 13336.812 | O83: 0.43845133 | P83: 188409 | Q83: 16.144664 | R83: 1.265507 | S83: 1.4432244 | T83: =N83/Y83 -> 30.379983 | U83: 515791.9 | V83: =N83 -> 13336.812 | W83: =U83-V83 -> 502455.09 | X83: =IF(V83=0,0,(U83-V83)/V83) -> 37.674301 | Y83: 439 | Z83: =IF(Y83=0,"NA",U83/Y83) -> 1174.9246 | AA83: =(Q83/100*S83/100) -> 0.0023300373
A84: K435 | B84: Google - US | C84: 43000000013136087 | D84: airfrance tickets | E84: Broad | F84: Air France Branded | G84: Air France Brand | H84: uncategorized | I84: Position 1 -2 Target | J84: Unassigned | K84: Live | L84: 0.925 | M84: 33 | N84: 29.2625 | O84: 0.88674241 | P84: 241 | Q84: 13.692946 | R84: 1.193361 | S84: 3.030303 | T84: =N84/Y84 -> 29.2625 | U84: 1123.7 | V84: =N84 -> 29.2625 | W84: =U84-V84 -> 1094.4375 | X84: =IF(V84=0,0,(U84-V84)/V84) -> 37.400684 | Y84: 1 | Z84: =IF(Y84=0,"NA",U84/Y84) -> 1123.7 | AA84: =(Q84/100*S84/100) -> 0.0041493776
A85: K435 | B85: Google - US | C85: 43000000013068860 | D85: airfrance airline | E85: Broad | F85: Air France Branded | G85: Air France Brand | H85: uncategorized | I85: Position 1 -2 Target | J85: Unassigned | K85: Live | L85: 0.2875 | M85: 95 | N85: 50.387499 | O85: 0.53039472 | P85: 712 | Q85: 13.342697 | R85: 1.3119522 | S85: 1.0526316 | T85: =N85/Y85 -> 50.387499 | U85: 1887 | V85: =N85 -> 50.387499 | W85: =U85-V85 -> 1836.6125 | X85: =IF(V85=0,0,(U85-V85)/V85) -> 36.449765 | Y85: 1 | Z85: =IF(Y85=0,"NA",U85/Y85) -> 1887 | AA85: =(Q85/100*S85/100) -> 0.0014044944
A86: K2615 | B86: Yahoo - US | C86: 43000000039649216 | D86: international flight | E86: Advanced | F86: Geo Targeted Chicago | G86: International Chicago | H86: uncategorized | J86: Unassigned | K86: Live | L86: 6.25 | M86: 86 | N86: 118.8875 | O86: 1.3824128 | P86: 1215 | Q86: 7.0781893 | R86: 1.3184444 | S86: 1.1627907 | T86: =N86/Y86 -> 118.8875 | U86: 4403.85 | V86: =N86 -> 118.8875 | W86: =U86-V86 -> 4284.9625 | X86: =IF(V86=0,0,(U86-V86)/V86) -> 36.042162 | Y86: 1 | Z86: =IF(Y86=0,"NA",U86/Y86) -> 4403.85 | AA86: =(Q86/100*S86/100) -> 0.00082304527
A87: K1175 | B87: Google - Global | C87: 43000000005663445 | D87: airfrance | E87: Broad | F87: Air France Global Campaign | G87: Air France | H87: airfrance | I87: Position 1- 3 | J87: Unassigned | K87: Unavailable | L87: 2.5 | M87: 1383 | N87: 998.38749 | O87: 0.72189985 | P87: 23310 | Q87: 5.9330759 | R87: 1.6499571 | S87: 2.6753435 | T87: =N87/Y87 -> 26.983446 | U87: 35357.45 | V87: =N87 -> 998.38749 | W87: =U87-V87 -> 34359.063 | X87: =IF(V87=0,0,(U87-V87)/V87) -> 34.414556 | Y87: 37 | Z87: =IF(Y87=0,"NA",U87/Y87) -> 955.60676 | AA87: =(Q87/100*S87/100) -> 0.0015873016
A88: K2615 | B88: Yahoo - US | C88: 43000000027382601 | D88: airfrance.com | E88: Advanced | F88: Air France Branded | G88: Air France Website | H88: uncategorized | J88: Unassigned | K88: Live | L88: 7.5 | M88: 4023 | N88: 3491.7875 | O88: 0.86795612 | P88: 24934 | Q88: 16.134595 | R88: 1.2702358 | S88: 2.1128511 | T88: =N88/Y88 -> 41.079853 | U88: 121372.35 | V88: =N88 -> 3491.7875 | W88: =U88-V88 -> 117880.56 | X88: =IF(V88=0,0,(U88-V88)/V88) -> 33.759375 | Y88: 85 | Z88: =IF(Y88=0,"NA",U88/Y88) -> 1427.91 | AA88: =(Q88/100*S88/100) -> 0.0034089998
A89: K1123 | B89: Overture - Global | C89: 43000000005420856 | D89: airline ticket to france | E89: Advanced | F89: Unassigned | G89: Unassigned | H89: france | I89: Position 1-2 Target | J89: Unassigned | K89: Unavailable | L89: 7.5 | M89: 43 | N89: 36.7625 | O89: 0.85494185 | P89: 825 | Q89: 5.2121212 | R89: 1.7916364 | S89: 2.3255814 | T89: =N89/Y89 -> 36.7625 | U89: 1274.15 | V89: =N89 -> 36.7625 | W89: =U89-V89 -> 1237.3875 | X89: =IF(V89=0,0,(U89-V89)/V89) -> 33.65896 | Y89: 1 | Z89: =IF(Y89=0,"NA",U89/Y89) -> 1274.15 | AA89: =(Q89/100*S89/100) -> 0.0012121212
A90: K435 | B90: Google - US | C90: 43000000014126154 | D90: paris airfare | E90: Broad | F90: Geo Targeted Chicago | G90: Chicago to Paris Sale | H90: uncategorized | I90: Position 5-10 Bid Strategy | J90: Unassigned | K90: Unavailable | L90: 6.25 | M90: 24 | N90: 44.5125 | O90: 1.8546875 | P90: 194 | Q90: 12.371134 | R90: 1.7108763 | S90: 4.1666667 | T90: =N90/Y90 -> 44.5125 | U90: 1530 | V90: =N90 -> 44.5125 | W90: =U90-V90 -> 1485.4875 | X90: =IF(V90=0,0,(U90-V90)/V90) -> 33.372367 | Y90: 1 | Z90: =IF(Y90=0,"NA",U90/Y90) -> 1530 | AA90: =(Q90/100*S90/100) -> 0.0051546392
A91: K1123 | B91: Overture - Global | C91: 43000000005421316 | D91: air france reservation | E91: Advanced | F91: Unassigned | G91: Unassigned | H91: airfrance | I91: Position 1-2 Target | J91: Unassigned | K91: Paused | L91: 0.45 | M91: 302 | N91: 176.775 | O91: 0.58534767 | P91: 22484 | Q91: 1.3431774 | R91: 1.3111902 | S91: 1.986755 | T91: =N91/Y91 -> 29.4625 | U91: 5888.8 | V91: =N91 -> 176.775 | W91: =U91-V91 -> 5712.025 | X91: =IF(V91=0,0,(U91-V91)/V91) -> 32.312403 | Y91: 6 | Z91: =IF(Y91=0,"NA",U91/Y91) -> 981.46667 | AA91: =(Q91/100*S91/100) -> 0.00026685643
A92: K1123 | B92: Overture - Global | C92: 43000000005421182 | D92: air france usa | E92: Advanced | F92: Unassigned | G92: Unassigned | H92: airfrance | I92: Position 1-2 Target | J92: Unassigned | K92: Paused | L92: 7.5 | M92: 116 | N92: 41.949999 | O92: 0.36163793 | P92: 4815 | Q92: 2.4091381 | R92: 1.9894081 | S92: 0.86206897 | T92: =N92/Y92 -> 41.949999 | U92: 1394.85 | V92: =N92 -> 41.949999 | W92: =U92-V92 -> 1352.9 | X92: =IF(V92=0,0,(U92-V92)/V92) -> 32.250299 | Y92: 1 | Z92: =IF(Y92=0,"NA",U92/Y92) -> 1394.85 | AA92: =(Q92/100*S92/100) -> 0.00020768432
A93: K435 | B93: Google - US | C93: 43000000014110167 | D93: italy airline | E93: Broad | F93: Geo Targeted San Francisco | G93: San Francisco to Italy Sale | H93: uncategorized | I93: Position 5-10 Bid Strategy | J93: Unassigned | K93: Unavailable | L93: 6.25 | M93: 16 | N93: 25.75 | O93: 1.609375 | P93: 163 | Q93: 9.8159509 | R93: 1.5705521 | S93: 6.25 | T93: =N93/Y93 -> 25.75 | U93: 850 | V93: =N93 -> 25.75 | W93: =U93-V93 -> 824.25 | X93: =IF(V93=0,0,(U93-V93)/V93) -> 32.009709 | Y93: 1 | Z93: =IF(Y93=0,"NA",U93/Y93) -> 850 | AA93: =(Q93/100*S93/100) -> 0.0061349693
A94: K2615 | B94: Yahoo - US | C94: 43000000039655020 | D94: international air fare | E94: Advanced | F94: Geo Targeted New York | G94: International New York | H94: uncategorized | J94: Unassigned | K94: Paused | L94: 6.25 | M94: 10 | N94: 25.7875 | O94: 2.57875 | P94: 830 | Q94: 1.2048193 | R94: 3.4382169 | S94: 10 | T94: =N94/Y94 -> 25.7875 | U94: 816 | V94: =N94 -> 25.7875 | W94: =U94-V94 -> 790.2125 | X94: =IF(V94=0,0,(U94-V94)/V94) -> 30.643238 | Y94: 1 | Z94: =IF(Y94=0,"NA",U94/Y94) -> 816 | AA94: =(Q94/100*S94/100) -> 0.0012048193
A95: K2615 | B95: Yahoo - US | C95: 43000000027382592 | D95: airfrance | E95: Advanced | F95: Air France Branded | G95: Air France Website | H95: uncategorized | J95: Unassigned | K95: Live | L95: 7.5 | M95: 23893 | N95: 17939.35 | O95: 0.75082031 | P95: 162070 | Q95: 14.742395 | R95: 1.6010922 | S95: 1.7620223 | T95: =N95/Y95 -> 42.611282 | U95: 567463.4 | V95: =N95 -> 17939.35 | W95: =U95-V95 -> 549524.05 | X95: =IF(V95=0,0,(U95-V95)/V95) -> 30.632328 | Y95: 421 | Z95: =IF(Y95=0,"NA",U95/Y95) -> 1347.8941 | AA95: =(Q95/100*S95/100) -> 0.002597643
A96: K2966 | B96: MSN - US | C96: 43000000031840290 | D96: airfrance com | E96: Broad | F96: Air France Brand & French Destinations | G96: Air France Website | H96: uncategorized | J96: Unassigned | K96: Live | L96: 0 | M96: 1498 | N96: 951.31248 | O96: 0.63505506 | P96: 5490 | Q96: 27.285974 | R96: 1.1497505 | S96: 1.6021362 | T96: =N96/Y96 -> 39.63802 | U96: 30053.45 | V96: =N96 -> 951.31248 | W96: =U96-V96 -> 29102.138 | X96: =IF(V96=0,0,(U96-V96)/V96) -> 30.591565 | Y96: 24 | Z96: =IF(Y96=0,"NA",U96/Y96) -> 1252.2271 | AA96: =(Q96/100*S96/100) -> 0.0043715847
A97: K1123 | B97: Overture - Global | C97: 43000000005421364 | D97: air france us | E97: Advanced | F97: Unassigned | G97: Unassigned | H97: airfrance | I97: Position 1-2 Target | J97: Unassigned | K97: Paused | L97: 7.5 | M97: 87 | N97: 38.687499 | O97: 0.4446839 | P97: 2505 | Q97: 3.4730539 | R97: 1.1856687 | S97: 1.1494253 | T97: =N97/Y97 -> 38.687499 | U97: 1202.75 | V97: =N97 -> 38.687499 | W97: =U97-V97 -> 1164.0625 | X97: =IF(V97=0,0,(U97-V97)/V97) -> 30.088854 | Y97: 1 | Z97: =IF(Y97=0,"NA",U97/Y97) -> 1202.75 | AA97: =(Q97/100*S97/100) -> 0.0003992016
A98: K2615 | B98: Yahoo - US | C98: 43000000029356952 | D98: france flight | E98: Standard | F98: Paris & France Terms | G98: France | H98: uncategorized | J98: Unassigned | K98: Live | L98: 6.25 | M98: 107 | N98: 136.3 | O98: 1.2738318 | P98: 3137 | Q98: 3.4109021 | R98: 1 | S98: 0.93457944 | T98: =N98/Y98 -> 136.3 | U98: 4148 | V98: =N98 -> 136.3 | W98: =U98-V98 -> 4011.7 | X98: =IF(V98=0,0,(U98-V98)/V98) -> 29.432869 | Y98: 1 | Z98: =IF(Y98=0,"NA",U98/Y98) -> 4148 | AA98: =(Q98/100*S98/100) -> 0.0003187759
A99: K1122 | B99: Overture - US | C99: 43000000014278672 | D99: air france | E99: Standard | F99: Unassigned | G99: Unassigned | H99: airfrance | I99: Position 1-4 Bid Strategy | J99: Unassigned | K99: Unavailable | L99: 7.5 | M99: 2235 | N99: 1441.325 | O99: 0.64488814 | P99: 38432 | Q99: 5.8154663 | R99: 1.373993 | S99: 1.7002237 | T99: =N99/Y99 -> 37.929605 | U99: 43020.2 | V99: =N99 -> 1441.325 | W99: =U99-V99 -> 41578.875 | X99: =IF(V99=0,0,(U99-V99)/V99) -> 28.847675 | Y99: 38 | Z99: =IF(Y99=0,"NA",U99/Y99) -> 1132.1105 | AA99: =(Q99/100*S99/100) -> 0.00098875937
A100: K435 | B100: Google - US | C100: 43000000013069215 | D100: air france airlines | E100: Broad | F100: Air France Branded | G100: Air France Brand | H100: uncategorized | I100: Position 1 -2 Target | J100: Unassigned | K100: Live | L100: 18.75 | M100: 2454 | N100: 1050.7875 | O100: 0.42819376 | P100: 11128 | Q100: 22.05248 | R100: 1.1778774 | S100: 1.1409943 | T100: =N100/Y100 -> 37.528125 | U100: 31200.1 | V100: =N100 -> 1050.7875 | W100: =U100-V100 -> 30149.313 | X100: =IF(V100=0,0,(U100-V100)/V100) -> 28.692112 | Y100: 28 | Z100: =IF(Y100=0,"NA",U100/Y100) -> 1114.2893 | AA100: =(Q100/100*S100/100) -> 0.0025161754
...

Sheet data_cleaned
A1: Publisher Name | B1: Keyword | C1: Match Type | D1: Campaign | E1: Keyword Group | F1: Bid Strategy | G1: Search Engine Bid | H1: Clicks | I1: Click Charges | J1: Avg. Cost per Click | K1: Impressions | L1: Engine Click Thru % | M1: Avg. Pos. | N1: Trans. Conv. % | O1: Total Cost/ Trans. | P1: Total Revenue | Q1: Total Cost | R1: Net Revenue (Profit) | S1: Return on Ad Dollar Spent | T1: Total Volume of Bookings | U1: Avg. Revenue per Booking | V1: Probability of Booking | W1: Margin % | X1: Cost per Booking | Y1: Budgeted Cost | Z1: Budgeted Revenue | AA1: Cost Variance | AB1: Revenue Variance
A2: Yahoo - US | B2: fly to florence | C2: Advanced | D2: Western Europe Destinations | E2: Florence | G2: 6.25 | H2: 1 | I2: 2.3125 | J2: 2.3125 | K2: 11 | L2: 0.090909091 | M2: 1.2727273 | N2: 9 | O2: =I2/T2 -> 0.25694444 | P2: 8777.95 | Q2: =I2 -> 2.3125 | R2: =P2-Q2 -> 8775.6375 | S2: =IF(Q2=0,0,(P2-Q2)/Q2) -> 3794.8703 | T2: 9 | U2: =IF(T2=0,"NA",P2/T2) -> 975.32778 | V2: =(L2*N2) -> 0.81818182 | W2: =IF(P2=0,0,R2/P2) -> 0.99973656 | X2: =IF(T2=0,0,Q2/T2) -> 0.25694444 | Y2: =Q2*0.9 -> 2.08125 | Z2: =R2*1.05 -> 9214.4194 | AA2: =Q2-Y2 -> 0.23125 | AB2: =R2-Z2 -> -438.78188
A3: Yahoo - US | B3: low international airfare | C3: Advanced | D3: Geo Targeted DC | E3: Low International DC | G3: 6.25 | H3: 1 | I3: 0.625 | J3: 0.625 | K3: 6 | L3: 0.16666667 | M3: 1 | N3: 1 | O3: =I3/T3 -> 0.625 | P3: 1574.2 | Q3: =I3 -> 0.625 | R3: =P3-Q3 -> 1573.575 | S3: =IF(Q3=0,0,(P3-Q3)/Q3) -> 2517.72 | T3: 1 | U3: =IF(T3=0,"NA",P3/T3) -> 1574.2 | V3: =(L3*N3) -> 0.16666667 | W3: =IF(P3=0,0,R3/P3) -> 0.99960297 | X3: =IF(T3=0,0,Q3/T3) -> 0.625 | Y3: =Q3*0.9 -> 0.5625 | Z3: =R3*1.05 -> 1652.2538 | AA3: =Q3-Y3 -> 0.0625 | AB3: =R3-Z3 -> -78.67875
A4: MSN - Global | B4: air discount france ticket | C4: Broad | D4: Air France Brand & French Destinations | E4: France | F4: Position 2-5 Bid Strategy | G4: 0 | H4: 1 | I4: 0.3875 | J4: 0.3875 | K4: 9 | L4: 0.11111111 | M4: 1.1111111 | N4: 1 | O4: =I4/T4 -> 0.3875 | P4: 390.15 | Q4: =I4 -> 0.3875 | R4: =P4-Q4 -> 389.7625 | S4: =IF(Q4=0,0,(P4-Q4)/Q4) -> 1005.8387 | T4: 1 | U4: =IF(T4=0,"NA",P4/T4) -> 390.15 | V4: =(L4*N4) -> 0.11111111 | W4: =IF(P4=0,0,R4/P4) -> 0.99900679 | X4: =IF(T4=0,0,Q4/T4) -> 0.3875 | Y4: =Q4*0.9 -> 0.34875 | Z4: =R4*1.05 -> 409.25063 | AA4: =Q4-Y4 -> 0.03875 | AB4: =R4-Z4 -> -19.488125
A5: Google - Global | B5: [airfrance] | C5: Exact | D5: Air France Global Campaign | E5: Air France | F5: Position 1- 3 | G5: 7.5 | H5: 59 | I5: 2.3124998 | J5: 0.039194912 | K5: 401 | L5: 0.14713217 | M5: 2 | N5: 0.033898305 | O5: =I5/T5 -> 1.1562499 | P5: 1665.15 | Q5: =I5 -> 2.3124998 | R5: =P5-Q5 -> 1662.8375 | S5: =IF(Q5=0,0,(P5-Q5)/Q5) -> 719.06492 | T5: 2 | U5: =IF(T5=0,"NA",P5/T5) -> 832.575 | V5: =(L5*N5) -> 0.0049875312 | W5: =IF(P5=0,0,R5/P5) -> 0.99861124 | X5: =IF(T5=0,0,Q5/T5) -> 1.1562499 | Y5: =Q5*0.9 -> 2.0812499 | Z5: =R5*1.05 -> 1745.9794 | AA5: =Q5-Y5 -> 0.23124998 | AB5: =R5-Z5 -> -83.141875
A6: Overture - Global | B6: air france online booking | C6: Standard | D6: Unassigned | E6: Unassigned | F6: Position 1-2 Target | G6: 0.25 | H6: 8 | I6: 2.2 | J6: 0.275 | K6: 318 | L6: 0.025157233 | M6: 2.9757862 | N6: 0.125 | O6: =I6/T6 -> 2.2 | P6: 935 | Q6: =I6 -> 2.2 | R6: =P6-Q6 -> 932.8 | S6: =IF(Q6=0,0,(P6-Q6)/Q6) -> 424 | T6: 1 | U6: =IF(T6=0,"NA",P6/T6) -> 935 | V6: =(L6*N6) -> 0.0031446541 | W6: =IF(P6=0,0,R6/P6) -> 0.99764706 | X6: =IF(T6=0,0,Q6/T6) -> 2.2 | Y6: =Q6*0.9 -> 1.98 | Z6: =R6*1.05 -> 979.44 | AA6: =Q6-Y6 -> 0.22 | AB6: =R6-Z6 -> -46.64
A7: Overture - Global | B7: airfrance,com | C7: Standard | D7: Unassigned | E7: Unassigned | F7: Position 1-2 Target | G7: 0.125 | H7: 42 | I7: 5.25 | J7: 0.125 | K7: 722 | L7: 0.058171745 | M7: 1.1290859 | N7: 0.047619048 | O7: =I7/T7 -> 2.625 | P7: 1817.3 | Q7: =I7 -> 5.25 | R7: =P7-Q7 -> 1812.05 | S7: =IF(Q7=0,0,(P7-Q7)/Q7) -> 345.15238 | T7: 2 | U7: =IF(T7=0,"NA",P7/T7) -> 908.65 | V7: =(L7*N7) -> 0.0027700831 | W7: =IF(P7=0,0,R7/P7) -> 0.9971111 | X7: =IF(T7=0,0,Q7/T7) -> 2.625 | Y7: =Q7*0.9 -> 4.725 | Z7: =R7*1.05 -> 1902.6525 | AA7: =Q7-Y7 -> 0.525 | AB7: =R7-Z7 -> -90.6025
A8: Google - US | B8: paris cheap airline | C8: Broad | D8: Geo Targeted San Francisco | E8: San Francisco to Paris Sale | F8: Position 5-10 Bid Strategy | G8: 6.25 | H8: 3 | I8: 5.2125 | J8: 1.7375 | K8: 13 | L8: 0.23076923 | M8: 1 | N8: 0.33333333 | O8: =I8/T8 -> 5.2125 | P8: 1685.55 | Q8: =I8 -> 5.2125 | R8: =P8-Q8 -> 1680.3375 | S8: =IF(Q8=0,0,(P8-Q8)/Q8) -> 322.36691 | T8: 1 | U8: =IF(T8=0,"NA",P8/T8) -> 1685.55 | V8: =(L8*N8) -> 0.076923077 | W8: =IF(P8=0,0,R8/P8) -> 0.99690754 | X8: =IF(T8=0,0,Q8/T8) -> 5.2125 | Y8: =Q8*0.9 -> 4.69125 | Z8: =R8*1.05 -> 1764.3544 | AA8: =Q8-Y8 -> 0.52125 | AB8: =R8-Z8 -> -84.016875
A9: Overture - US | B9: airfrance.us | C9: Standard | D9: Unassigned | E9: Unassigned | F9: Position 1-4 Bid Strategy | G9: 0.325 | H9: 47 | I9: 11.8 | J9: 0.25106383 | K9: 547 | L9: 0.085923218 | M9: 1.1819013 | N9: 0.042553191 | O9: =I9/T9 -> 5.8999999 | P9: 3796.1 | Q9: =I9 -> 11.8 | R9: =P9-Q9 -> 3784.3 | S9: =IF(Q9=0,0,(P9-Q9)/Q9) -> 320.7034 | T9: 2 | U9: =IF(T9=0,"NA",P9/T9) -> 1898.05 | V9: =(L9*N9) -> 0.0036563071 | W9: =IF(P9=0,0,R9/P9) -> 0.99689155 | X9: =IF(T9=0,0,Q9/T9) -> 5.8999999 | Y9: =Q9*0.9 -> 10.62 | Z9: =R9*1.05 -> 3973.515 | AA9: =Q9-Y9 -> 1.18 | AB9: =R9-Z9 -> -189.215
A10: Overture - Global | B10: air travel to paris | C10: Standard | D10: Unassigned | E10: Unassigned | F10: Position 1-2 Target | G10: 7.5 | H10: 13 | I10: 5.2125 | J10: 0.40096154 | K10: 448 | L10: 0.029017857 | M10: 1.8564732 | N10: 0.076923077 | O10: =I10/T10 -> 5.2125 | P10: 1513 | Q10: =I10 -> 5.2125 | R10: =P10-Q10 -> 1507.7875 | S10: =IF(Q10=0,0,(P10-Q10)/Q10) -> 289.26379 | T10: 1 | U10: =IF(T10=0,"NA",P10/T10) -> 1513 | V10: =(L10*N10) -> 0.0022321429 | W10: =IF(P10=0,0,R10/P10) -> 0.99655486 | X10: =IF(T10=0,0,Q10/T10) -> 5.2125 | Y10: =Q10*0.9 -> 4.69125 | Z10: =R10*1.05 -> 1583.1769 | AA10: =Q10-Y10 -> 0.52125 | AB10: =R10-Z10 -> -75.389375
A11: Google - Global | B11: air france site | C11: Broad | D11: Air France Brand & French Destinations | E11: Air France Website | G11: 5 | H11: 19 | I11: 8.2374999 | J11: 0.43355262 | K11: 129 | L11: 0.14728682 | M11: 1.0302326 | N11: 0.052631579 | O11: =I11/T11 -> 8.2374999 | P11: 2348.55 | Q11: =I11 -> 8.2374999 | R11: =P11-Q11 -> 2340.3125 | S11: =IF(Q11=0,0,(P11-Q11)/Q11) -> 284.10471 | T11: 1 | U11: =IF(T11=0,"NA",P11/T11) -> 2348.55 | V11: =(L11*N11) -> 0.007751938 | W11: =IF(P11=0,0,R11/P11) -> 0.99649252 | X11: =IF(T11=0,0,Q11/T11) -> 8.2374999 | Y11: =Q11*0.9 -> 7.4137499 | Z11: =R11*1.05 -> 2457.3281 | AA11: =Q11-Y11 -> 0.82374999 | AB11: =R11-Z11 -> -117.01563
A12: Overture - Global | B12: cheap fare to paris | C12: Advanced | D12: Unassigned | E12: Unassigned | F12: Position 1-2 Target | G12: 0.6875 | H12: 29 | I12: 26.6125 | J12: 0.91767241 | K12: 559 | L12: 0.051878354 | M12: 2.3334526 | N12: 0.068965517 | O12: =I12/T12 -> 13.30625 | P12: 7418.8 | Q12: =I12 -> 26.6125 | R12: =P12-Q12 -> 7392.1875 | S12: =IF(Q12=0,0,(P12-Q12)/Q12) -> 277.77125 | T12: 2 | U12: =IF(T12=0,"NA",P12/T12) -> 3709.4 | V12: =(L12*N12) -> 0.0035778175 | W12: =IF(P12=0,0,R12/P12) -> 0.99641283 | X12: =IF(T12=0,0,Q12/T12) -> 13.30625 | Y12: =Q12*0.9 -> 23.95125 | Z12: =R12*1.05 -> 7761.7969 | AA12: =Q12-Y12 -> 2.66125 | AB12: =R12-Z12 -> -369.60938
A13: Overture - US | B13: air france.com | C13: Standard | D13: Unassigned | E13: Unassigned | F13: Position 1-4 Bid Strategy | G13: 0.3125 | H13: 273 | I13: 46.349998 | J13: 0.16978021 | K13: 3171 | L13: 0.086092715 | M13: 1.0063072 | N13: 0.036630037 | O13: =I13/T13 -> 4.6349998 | P13: 11271.85 | Q13: =I13 -> 46.349998 | R13: =P13-Q13 -> 11225.5 | S13: =IF(Q13=0,0,(P13-Q13)/Q13) -> 242.18987 | T13: 10 | U13: =IF(T13=0,"NA",P13/T13) -> 1127.185 | V13: =(L13*N13) -> 0.0031535793 | W13: =IF(P13=0,0,R13/P13) -> 0.99588799 | X13: =IF(T13=0,0,Q13/T13) -> 4.6349998 | Y13: =Q13*0.9 -> 41.714998 | Z13: =R13*1.05 -> 11786.775 | AA13: =Q13-Y13 -> 4.6349998 | AB13: =R13-Z13 -> -561.275
A14: Google - US | B14: air france us | C14: Broad | D14: Air France Branded | E14: Air France Website | G14: 10 | H14: 231 | I14: 99.549999 | J14: 0.43095237 | K14: 1277 | L14: 0.18089272 | M14: 1.0226077 | N14: 0.086580087 | O14: =I14/T14 -> 4.9774999 | P14: 23076.65 | Q14: =I14 -> 99.549999 | R14: =P14-Q14 -> 22977.1 | S14: =IF(Q14=0,0,(P14-Q14)/Q14) -> 230.80965 | T14: 20 | U14: =IF(T14=0,"NA",P14/T14) -> 1153.8325 | V14: =(L14*N14) -> 0.015661707 | W14: =IF(P14=0,0,R14/P14) -> 0.99568612 | X14: =IF(T14=0,0,Q14/T14) -> 4.9774999 | Y14: =Q14*0.9 -> 89.594999 | Z14: =R14*1.05 -> 24125.955 | AA14: =Q14-Y14 -> 9.9549999 | AB14: =R14-Z14 -> -1148.855
A15: Google - US | B15: airfrance | C15: Broad | D15: Air France Branded | E15: Air France Website | G15: 10 | H15: 907 | I15: 235.11249 | J15: 0.25921995 | K15: 4352 | L15: 0.20840993 | M15: 1.0105836 | N15: 0.028665932 | O15: =I15/T15 -> 9.0427883 | P15: 48551.15 | Q15: =I15 -> 235.11249 | R15: =P15-Q15 -> 48316.038 | S15: =IF(Q15=0,0,(P15-Q15)/Q15) -> 205.50179 | T15: 26 | U15: =IF(T15=0,"NA",P15/T15) -> 1867.3519 | V15: =(L15*N15) -> 0.0059742647 | W15: =IF(P15=0,0,R15/P15) -> 0.99515743 | X15: =IF(T15=0,0,Q15/T15) -> 9.0427883 | Y15: =Q15*0.9 -> 211.60125 | Z15: =R15*1.05 -> 50731.839 | AA15: =Q15-Y15 -> 23.511249 | AB15: =R15-Z15 -> -2415.8019
A16: Overture - US | B16: cdg flight | C16: Standard | D16: Unassigned | E16: Unassigned | F16: Position 2-5 Bid Strategy | G16: 0.125 | H16: 18 | I16: 4.75 | J16: 0.26388889 | K16: 169 | L16: 0.10650888 | M16: 1.6621302 | N16: 0.055555556 | O16: =I16/T16 -> 4.75 | P16: 896.75 | Q16: =I16 -> 4.75 | R16: =P16-Q16 -> 892 | S16: =IF(Q16=0,0,(P16-Q16)/Q16) -> 187.78947 | T16: 1 | U16: =IF(T16=0,"NA",P16/T16) -> 896.75 | V16: =(L16*N16) -> 0.0059171598 | W16: =IF(P16=0,0,R16/P16) -> 0.99470309 | X16: =IF(T16=0,0,Q16/T16) -> 4.75 | Y16: =Q16*0.9 -> 4.275 | Z16: =R16*1.05 -> 936.6 | AA16: =Q16-Y16 -> 0.475 | AB16: =R16-Z16 -> -44.6
A17: Google - US | B17: airfrance us | C17: Broad | D17: Air France Branded | E17: Air France Website | G17: 10 | H17: 207 | I17: 30.787498 | J17: 0.14873187 | K17: 730 | L17: 0.28356164 | M17: 1 | N17: 0.024154589 | O17: =I17/T17 -> 6.1574996 | P17: 5733.25 | Q17: =I17 -> 30.787498 | R17: =P17-Q17 -> 5702.4625 | S17: =IF(Q17=0,0,(P17-Q17)/Q17) -> 185.22007 | T17: 5 | U17: =IF(T17=0,"NA",P17/T17) -> 1146.65 | V17: =(L17*N17) -> 0.0068493151 | W17: =IF(P17=0,0,R17/P17) -> 0.99463001 | X17: =IF(T17=0,0,Q17/T17) -> 6.1574996 | Y17: =Q17*0.9 -> 27.708748 | Z17: =R17*1.05 -> 5987.5856 | AA17: =Q17-Y17 -> 3.0787498 | AB17: =R17-Z17 -> -285.12313
A18: Google - US | B18: france airline ticket | C18: Broad | D18: Geo Targeted New York | E18: New York to France Sale | F18: Position 5-10 Bid Strategy | G18: 6.25 | H18: 2 | I18: 2.6875 | J18: 1.34375 | K18: 24 | L18: 0.083333333 | M18: 1.5416667 | N18: 0.5 | O18: =I18/T18 -> 2.6875 | P18: 494.7 | Q18: =I18 -> 2.6875 | R18: =P18-Q18 -> 492.0125 | S18: =IF(Q18=0,0,(P18-Q18)/Q18) -> 183.07442 | T18: 1 | U18: =IF(T18=0,"NA",P18/T18) -> 494.7 | V18: =(L18*N18) -> 0.041666667 | W18: =IF(P18=0,0,R18/P18) -> 0.99456741 | X18: =IF(T18=0,0,Q18/T18) -> 2.6875 | Y18: =Q18*0.9 -> 2.41875 | Z18: =R18*1.05 -> 516.61312 | AA18: =Q18-Y18 -> 0.26875 | AB18: =R18-Z18 -> -24.600625
A19: Google - US | B19: airfrance website | C19: Broad | D19: Air France Branded | E19: Air France Website | F19: Position 2-5 Bid Strategy | G19: 0.7125 | H19: 10 | I19: 9.9375 | J19: 0.99375 | K19: 80 | L19: 0.125 | M19: 1.0625 | N19: 0.1 | O19: =I19/T19 -> 9.9375 | P19: 1815.6 | Q19: =I19 -> 9.9375 | R19: =P19-Q19 -> 1805.6625 | S19: =IF(Q19=0,0,(P19-Q19)/Q19) -> 181.70189 | T19: 1 | U19: =IF(T19=0,"NA",P19/T19) -> 1815.6 | V19: =(L19*N19) -> 0.0125 | W19: =IF(P19=0,0,R19/P19) -> 0.9945266 | X19: =IF(T19=0,0,Q19/T19) -> 9.9375 | Y19: =Q19*0.9 -> 8.94375 | Z19: =R19*1.05 -> 1895.9456 | AA19: =Q19-Y19 -> 0.99375 | AB19: =R19-Z19 -> -90.283125
A20: Overture - Global | B20: airplane france ticket | C20: Advanced | D20: Unassigned | E20: Unassigned | F20: Position 1-2 Target | G20: 0.4375 | H20: 16 | I20: 8.3125 | J20: 0.51953125 | K20: 6073 | L20: 0.0026346122 | M20: 2.4634283 | N20: 0.0625 | O20: =I20/T20 -> 8.3125 | P20: 1473.9 | Q20: =I20 -> 8.3125 | R20: =P20-Q20 -> 1465.5875 | S20: =IF(Q20=0,0,(P20-Q20)/Q20) -> 176.31128 | T20: 1 | U20: =IF(T20=0,"NA",P20/T20) -> 1473.9 | V20: =(L20*N20) -> 0.00016466326 | W20: =IF(P20=0,0,R20/P20) -> 0.9943602 | X20: =IF(T20=0,0,Q20/T20) -> 8.3125 | Y20: =Q20*0.9 -> 7.48125 | Z20: =R20*1.05 -> 1538.8669 | AA20: =Q20-Y20 -> 0.83125 | AB20: =R20-Z20 -> -73.279375
A21: Google - US | B21: france airfare sale | C21: Broad | D21: Geo Targeted Miami | E21: Miami to France Sale | F21: Position 5-10 Bid Strategy | G21: 6.25 | H21: 1 | I21: 2.7625 | J21: 2.7625 | K21: 2 | L21: 0.5 | M21: 1 | N21: 1 | O21: =I21/T21 -> 2.7625 | P21: 470.05 | Q21: =I21 -> 2.7625 | R21: =P21-Q21 -> 467.2875 | S21: =IF(Q21=0,0,(P21-Q21)/Q21) -> 169.15385 | T21: 1 | U21: =IF(T21=0,"NA",P21/T21) -> 470.05 | V21: =(L21*N21) -> 0.5 | W21: =IF(P21=0,0,R21/P21) -> 0.99412297 | X21: =IF(T21=0,0,Q21/T21) -> 2.7625 | Y21: =Q21*0.9 -> 2.48625 | Z21: =R21*1.05 -> 490.65188 | AA21: =Q21-Y21 -> 0.27625 | AB21: =R21-Z21 -> -23.364375
A22: Overture - Global | B22: air france schedule | C22: Advanced | D22: Unassigned | E22: Unassigned | F22: Position 1-2 Target | G22: 0.325 | H22: 30 | I22: 10.7125 | J22: 0.35708333 | K22: 2192 | L22: 0.013686131 | M22: 1.5193431 | N22: 0.033333333 | O22: =I22/T22 -> 10.7125 | P22: 1785 | Q22: =I22 -> 10.7125 | R22: =P22-Q22 -> 1774.2875 | S22: =IF(Q22=0,0,(P22-Q22)/Q22) -> 165.62778 | T22: 1 | U22: =IF(T22=0,"NA",P22/T22) -> 1785 | V22: =(L22*N22) -> 0.00045620438 | W22: =IF(P22=0,0,R22/P22) -> 0.9939986 | X22: =IF(T22=0,0,Q22/T22) -> 10.7125 | Y22: =Q22*0.9 -> 9.6412498 | Z22: =R22*1.05 -> 1863.0019 | AA22: =Q22-Y22 -> 1.07125 | AB22: =R22-Z22 -> -88.714375
A23: Overture - Global | B23: airfare to tahiti | C23: Standard | D23: Unassigned | E23: Unassigned | G23: 10 | H23: 6 | I23: 12.275 | J23: 2.0458333 | K23: 102 | L23: 0.058823529 | M23: 4.1637255 | N23: 0.16666667 | O23: =I23/T23 -> 12.275 | P23: 1989 | Q23: =I23 -> 12.275 | R23: =P23-Q23 -> 1976.725 | S23: =IF(Q23=0,0,(P23-Q23)/Q23) -> 161.03666 | T23: 1 | U23: =IF(T23=0,"NA",P23/T23) -> 1989 | V23: =(L23*N23) -> 0.0098039216 | W23: =IF(P23=0,0,R23/P23) -> 0.99382856 | X23: =IF(T23=0,0,Q23/T23) -> 12.275 | Y23: =Q23*0.9 -> 11.0475 | Z23: =R23*1.05 -> 2075.5613 | AA23: =Q23-Y23 -> 1.2275 | AB23: =R23-Z23 -> -98.83625
A24: Google - US | B24: france flights | C24: Broad | D24: Geo Targeted DC | E24: DC to France Sale | F24: Position 5-10 Bid Strategy | G24: 6.25 | H24: 6 | I24: 18.35 | J24: 3.0583333 | K24: 137 | L24: 0.04379562 | M24: 1.2026277 | N24: 0.5 | O24: =I24/T24 -> 6.1166666 | P24: 2810.1 | Q24: =I24 -> 18.35 | R24: =P24-Q24 -> 2791.75 | S24: =IF(Q24=0,0,(P24-Q24)/Q24) -> 152.13896 | T24: 3 | U24: =IF(T24=0,"NA",P24/T24) -> 936.7 | V24: =(L24*N24) -> 0.02189781 | W24: =IF(P24=0,0,R24/P24) -> 0.99346998 | X24: =IF(T24=0,0,Q24/T24) -> 6.1166666 | Y24: =Q24*0.9 -> 16.515 | Z24: =R24*1.05 -> 2931.3375 | AA24: =Q24-Y24 -> 1.835 | AB24: =R24-Z24 -> -139.5875
A25: Google - US | B25: international airfares | C25: Broad | D25: Geo Targeted Detroit | E25: International Detroit | F25: Position 5-10 Bid Strategy | G25: 6.25 | H25: 2 | I25: 6.6 | J25: 3.3 | K25: 79 | L25: 0.025316456 | M25: 3.0050633 | N25: 0.5 | O25: =I25/T25 -> 6.6 | P25: 923.95 | Q25: =I25 -> 6.6 | R25: =P25-Q25 -> 917.35 | S25: =IF(Q25=0,0,(P25-Q25)/Q25) -> 138.99242 | T25: 1 | U25: =IF(T25=0,"NA",P25/T25) -> 923.95 | V25: =(L25*N25) -> 0.012658228 | W25: =IF(P25=0,0,R25/P25) -> 0.99285676 | X25: =IF(T25=0,0,Q25/T25) -> 6.6 | Y25: =Q25*0.9 -> 5.94 | Z25: =R25*1.05 -> 963.2175 | AA25: =Q25-Y25 -> 0.66 | AB25: =R25-Z25 -> -45.8675
A26: Google - US | B26: france air ticket | C26: Broad | D26: Geo Targeted New York | E26: New York to France Sale | F26: Position 5-10 Bid Strategy | G26: 6.25 | H26: 12 | I26: 19.4 | J26: 1.6166667 | K26: 116 | L26: 0.10344828 | M26: 1.0940517 | N26: 0.33333333 | O26: =I26/T26 -> 4.85 | P26: 2706.4 | Q26: =I26 -> 19.4 | R26: =P26-Q26 -> 2687 | S26: =IF(Q26=0,0,(P26-Q26)/Q26) -> 138.50515 | T26: 4 | U26: =IF(T26=0,"NA",P26/T26) -> 676.6 | V26: =(L26*N26) -> 0.034482759 | W26: =IF(P26=0,0,R26/P26) -> 0.99283181 | X26: =IF(T26=0,0,Q26/T26) -> 4.85 | Y26: =Q26*0.9 -> 17.46 | Z26: =R26*1.05 -> 2821.35 | AA26: =Q26-Y26 -> 1.94 | AB26: =R26-Z26 -> -134.35
A27: Overture - US | B27: airfrance.com/us | C27: Standard | D27: Unassigned | E27: Unassigned | G27: 7.5 | H27: 17 | I27: 5.5874999 | J27: 0.32867646 | K27: 98 | L27: 0.17346939 | M27: 0.95918367 | N27: 0.058823529 | O27: =I27/T27 -> 5.5874999 | P27: 778.6 | Q27: =I27 -> 5.5874999 | R27: =P27-Q27 -> 773.0125 | S27: =IF(Q27=0,0,(P27-Q27)/Q27) -> 138.34676 | T27: 1 | U27: =IF(T27=0,"NA",P27/T27) -> 778.6 | V27: =(L27*N27) -> 0.010204082 | W27: =IF(P27=0,0,R27/P27) -> 0.99282366 | X27: =IF(T27=0,0,Q27/T27) -> 5.5874999 | Y27: =Q27*0.9 -> 5.0287499 | Z27: =R27*1.05 -> 811.66313 | AA27: =Q27-Y27 -> 0.55874999 | AB27: =R27-Z27 -> -38.650625
A28: Google - US | B28: paris cheap ticket | C28: Broad | D28: Geo Targeted Boston | E28: Boston to Paris Sale | F28: Position 5-10 Bid Strategy | G28: 6.25 | H28: 3 | I28: 5.1375 | J28: 1.7125 | K28: 18 | L28: 0.16666667 | M28: 1.8333333 | N28: 0.33333333 | O28: =I28/T28 -> 5.1375 | P28: 676.6 | Q28: =I28 -> 5.1375 | R28: =P28-Q28 -> 671.4625 | S28: =IF(Q28=0,0,(P28-Q28)/Q28) -> 130.6983 | T28: 1 | U28: =IF(T28=0,"NA",P28/T28) -> 676.6 | V28: =(L28*N28) -> 0.055555556 | W28: =IF(P28=0,0,R28/P28) -> 0.99240689 | X28: =IF(T28=0,0,Q28/T28) -> 5.1375 | Y28: =Q28*0.9 -> 4.62375 | Z28: =R28*1.05 -> 705.03562 | AA28: =Q28-Y28 -> 0.51375 | AB28: =R28-Z28 -> -33.573125
A29: Google - US | B29: paris cheap flights | C29: Broad | D29: Geo Targeted Houston | E29: Houston to Paris Sale | F29: Position 5-10 Bid Strategy | G29: 6.25 | H29: 21 | I29: 43.3875 | J29: 2.0660714 | K29: 174 | L29: 0.12068966 | M29: 1.3214368 | N29: 0.14285714 | O29: =I29/T29 -> 14.4625 | P29: 5638.05 | Q29: =I29 -> 43.3875 | R29: =P29-Q29 -> 5594.6625 | S29: =IF(Q29=0,0,(P29-Q29)/Q29) -> 128.94641 | T29: 3 | U29: =IF(T29=0,"NA",P29/T29) -> 1879.35 | V29: =(L29*N29) -> 0.017241379 | W29: =IF(P29=0,0,R29/P29) -> 0.99230452 | X29: =IF(T29=0,0,Q29/T29) -> 14.4625 | Y29: =Q29*0.9 -> 39.04875 | Z29: =R29*1.05 -> 5874.3956 | AA29: =Q29-Y29 -> 4.33875 | AB29: =R29-Z29 -> -279.73313
A30: Overture - US | B30: tunis | C30: Standard | D30: Unassigned | E30: Unassigned | F30: Position 1-4 Bid Strategy | G30: 11.25 | H30: 36 | I30: 25.375 | J30: 0.7048611 | K30: 832 | L30: 0.043269231 | M30: 1.4074519 | N30: 0.083333333 | O30: =I30/T30 -> 8.4583332 | P30: 3254.65 | Q30: =I30 -> 25.375 | R30: =P30-Q30 -> 3229.275 | S30: =IF(Q30=0,0,(P30-Q30)/Q30) -> 127.26207 | T30: 3 | U30: =IF(T30=0,"NA",P30/T30) -> 1084.8833 | V30: =(L30*N30) -> 0.0036057692 | W30: =IF(P30=0,0,R30/P30) -> 0.99220346 | X30: =IF(T30=0,0,Q30/T30) -> 8.4583332 | Y30: =Q30*0.9 -> 22.8375 | Z30: =R30*1.05 -> 3390.7388 | AA30: =Q30-Y30 -> 2.5375 | AB30: =R30-Z30 -> -161.46375
A31: Yahoo - US | B31: france travel agency | C31: Standard | D31: Paris & France Terms | E31: France | G31: 6.25 | H31: 5 | I31: 15.4375 | J31: 3.0875 | K31: 167 | L31: 0.02994012 | M31: 1.2392814 | N31: 0.4 | O31: =I31/T31 -> 7.71875 | P31: 1978.8 | Q31: =I31 -> 15.4375 | R31: =P31-Q31 -> 1963.3625 | S31: =IF(Q31=0,0,(P31-Q31)/Q31) -> 127.18138 | T31: 2 | U31: =IF(T31=0,"NA",P31/T31) -> 989.4 | V31: =(L31*N31) -> 0.011976048 | W31: =IF(P31=0,0,R31/P31) -> 0.99219855 | X31: =IF(T31=0,0,Q31/T31) -> 7.71875 | Y31: =Q31*0.9 -> 13.89375 | Z31: =R31*1.05 -> 2061.5306 | AA31: =Q31-Y31 -> 1.54375 | AB31: =R31-Z31 -> -98.168125
A32: Google - Global | B32: air france airlines | C32: Broad | D32: Air France Global Campaign | E32: Air France | F32: Position 1- 3 | G32: 1.25 | H32: 228 | I32: 55.312498 | J32: 0.24259868 | K32: 3747 | L32: 0.060848679 | M32: 1.4166533 | N32: 0.01754386 | O32: =I32/T32 -> 13.828124 | P32: 6873.1 | Q32: =I32 -> 55.312498 | R32: =P32-Q32 -> 6817.7875 | S32: =IF(Q32=0,0,(P32-Q32)/Q32) -> 123.25944 | T32: 4 | U32: =IF(T32=0,"NA",P32/T32) -> 1718.275 | V32: =(L32*N32) -> 0.0010675207 | W32: =IF(P32=0,0,R32/P32) -> 0.99195232 | X32: =IF(T32=0,0,Q32/T32) -> 13.828124 | Y32: =Q32*0.9 -> 49.781248 | Z32: =R32*1.05 -> 7158.6769 | AA32: =Q32-Y32 -> 5.5312498 | AB32: =R32-Z32 -> -340.88938
A33: Google - Global | B33: lyon airfare | C33: Broad | D33: Air France Global Campaign | E33: Lyon | F33: Position 1- 3 | G33: 1.25 | H33: 12 | I33: 15.025 | J33: 1.2520833 | K33: 1030 | L33: 0.011650485 | M33: 1.3096117 | N33: 0.16666667 | O33: =I33/T33 -> 7.5124999 | P33: 1836 | Q33: =I33 -> 15.025 | R33: =P33-Q33 -> 1820.975 | S33: =IF(Q33=0,0,(P33-Q33)/Q33) -> 121.19634 | T33: 2 | U33: =IF(T33=0,"NA",P33/T33) -> 918 | V33: =(L33*N33) -> 0.0019417476 | W33: =IF(P33=0,0,R33/P33) -> 0.99181645 | X33: =IF(T33=0,0,Q33/T33) -> 7.5124999 | Y33: =Q33*0.9 -> 13.5225 | Z33: =R33*1.05 -> 1912.0238 | AA33: =Q33-Y33 -> 1.5025 | AB33: =R33-Z33 -> -91.04875
A34: Overture - Global | B34: air france web site | C34: Standard | D34: Unassigned | E34: Unassigned | F34: Position 1-2 Target | G34: 0.2875 | H34: 17 | I34: 5.3875 | J34: 0.31691176 | K34: 752 | L34: 0.022606383 | M34: 2.2155585 | N34: 0.058823529 | O34: =I34/T34 -> 5.3875 | P34: 637.5 | Q34: =I34 -> 5.3875 | R34: =P34-Q34 -> 632.1125 | S34: =IF(Q34=0,0,(P34-Q34)/Q34) -> 117.32947 | T34: 1 | U34: =IF(T34=0,"NA",P34/T34) -> 637.5 | V34: =(L34*N34) -> 0.0013297872 | W34: =IF(P34=0,0,R34/P34) -> 0.99154902 | X34: =IF(T34=0,0,Q34/T34) -> 5.3875 | Y34: =Q34*0.9 -> 4.84875 | Z34: =R34*1.05 -> 663.71813 | AA34: =Q34-Y34 -> 0.53875 | AB34: =R34-Z34 -> -31.605625
A35: Google - Global | B35: cont:air france global campaign::france | C35: N/A | D35: Air France Global Campaign | E35: France | G35: 7.5 | H35: 49 | I35: 11 | J35: 0.22448979 | K35: 4780 | L35: 0.010251046 | M35: 4.844477 | N35: 0.020408163 | O35: =I35/T35 -> 11 | P35: 1296.25 | Q35: =I35 -> 11 | R35: =P35-Q35 -> 1285.25 | S35: =IF(Q35=0,0,(P35-Q35)/Q35) -> 116.84091 | T35: 1 | U35: =IF(T35=0,"NA",P35/T35) -> 1296.25 | V35: =(L35*N35) -> 0.00020920502 | W35: =IF(P35=0,0,R35/P35) -> 0.99151398 | X35: =IF(T35=0,0,Q35/T35) -> 11 | Y35: =Q35*0.9 -> 9.8999996 | Z35: =R35*1.05 -> 1349.5125 | AA35: =Q35-Y35 -> 1.1 | AB35: =R35-Z35 -> -64.2625
A36: Google - US | B36: airfrance.com | C36: Broad | D36: Air France Branded | E36: Air France Website | G36: 10 | H36: 1260 | I36: 365.79999 | J36: 0.29031745 | K36: 6231 | L36: 0.20221473 | M36: 1.0051709 | N36: 0.025396825 | O36: =I36/T36 -> 11.43125 | P36: 42538.25 | Q36: =I36 -> 365.79999 | R36: =P36-Q36 -> 42172.45 | S36: =IF(Q36=0,0,(P36-Q36)/Q36) -> 115.28828 | T36: 32 | U36: =IF(T36=0,"NA",P36/T36) -> 1329.3203 | V36: =(L36*N36) -> 0.0051356123 | W36: =IF(P36=0,0,R36/P36) -> 0.99140068 | X36: =IF(T36=0,0,Q36/T36) -> 11.43125 | Y36: =Q36*0.9 -> 329.21999 | Z36: =R36*1.05 -> 44281.073 | AA36: =Q36-Y36 -> 36.579999 | AB36: =R36-Z36 -> -2108.6225
A37: Yahoo - US | B37: airfrance.us | C37: Advanced | D37: Air France Branded | E37: Air France Website | G37: 7.5 | H37: 242 | I37: 87.574999 | J37: 0.36188016 | K37: 1371 | L37: 0.17651349 | M37: 1.0201313 | N37: 0.05785124 | O37: =I37/T37 -> 6.2553571 | P37: 10140.5 | Q37: =I37 -> 87.574999 | R37: =P37-Q37 -> 10052.925 | S37: =IF(Q37=0,0,(P37-Q37)/Q37) -> 114.79218 | T37: 14 | U37: =IF(T37=0,"NA",P37/T37) -> 724.32143 | V37: =(L37*N37) -> 0.010211524 | W37: =IF(P37=0,0,R37/P37) -> 0.99136384 | X37: =IF(T37=0,0,Q37/T37) -> 6.2553571 | Y37: =Q37*0.9 -> 78.817499 | Z37: =R37*1.05 -> 10555.571 | AA37: =Q37-Y37 -> 8.7574999 | AB37: =R37-Z37 -> -502.64625
A38: Google - US | B38: book airfrance | C38: Broad | D38: Air France Branded | E38: Air France Brand | F38: Position 1 -2 Target | G38: 10 | H38: 4 | I38: 6 | J38: 1.5 | K38: 43 | L38: 0.093023256 | M38: 1.0930233 | N38: 0.25 | O38: =I38/T38 -> 6 | P38: 671.5 | Q38: =I38 -> 6 | R38: =P38-Q38 -> 665.5 | S38: =IF(Q38=0,0,(P38-Q38)/Q38) -> 110.91667 | T38: 1 | U38: =IF(T38=0,"NA",P38/T38) -> 671.5 | V38: =(L38*N38) -> 0.023255814 | W38: =IF(P38=0,0,R38/P38) -> 0.99106478 | X38: =IF(T38=0,0,Q38/T38) -> 6 | Y38: =Q38*0.9 -> 5.4 | Z38: =R38*1.05 -> 698.775 | AA38: =Q38-Y38 -> 0.6 | AB38: =R38-Z38 -> -33.275
A39: Google - Global | B39: nice flight | C39: Broad | D39: Air France Global Campaign | E39: Nice | F39: Position 1- 3 | G39: 1.25 | H39: 28 | I39: 36.425 | J39: 1.3008928 | K39: 2356 | L39: 0.01188455 | M39: 1.5467317 | N39: 0.10714286 | O39: =I39/T39 -> 12.141667 | P39: 3944 | Q39: =I39 -> 36.425 | R39: =P39-Q39 -> 3907.575 | S39: =IF(Q39=0,0,(P39-Q39)/Q39) -> 107.27728 | T39: 3 | U39: =IF(T39=0,"NA",P39/T39) -> 1314.6667 | V39: =(L39*N39) -> 0.0012733447 | W39: =IF(P39=0,0,R39/P39) -> 0.99076445 | X39: =IF(T39=0,0,Q39/T39) -> 12.141667 | Y39: =Q39*0.9 -> 32.7825 | Z39: =R39*1.05 -> 4102.9538 | AA39: =Q39-Y39 -> 3.6425 | AB39: =R39-Z39 -> -195.37875
A40: Google - US | B40: airfrance.us | C40: Broad | D40: Air France Branded | E40: Air France Website | G40: 10 | H40: 25 | I40: 6.95 | J40: 0.278 | K40: 132 | L40: 0.18939394 | M40: 1 | N40: 0.04 | O40: =I40/T40 -> 6.95 | P40: 751.4 | Q40: =I40 -> 6.95 | R40: =P40-Q40 -> 744.45 | S40: =IF(Q40=0,0,(P40-Q40)/Q40) -> 107.11511 | T40: 1 | U40: =IF(T40=0,"NA",P40/T40) -> 751.4 | V40: =(L40*N40) -> 0.0075757576 | W40: =IF(P40=0,0,R40/P40) -> 0.9907506 | X40: =IF(T40=0,0,Q40/T40) -> 6.95 | Y40: =Q40*0.9 -> 6.255 | Z40: =R40*1.05 -> 781.6725 | AA40: =Q40-Y40 -> 0.695 | AB40: =R40-Z40 -> -37.2225
A41: Yahoo - US | B41: rome travel | C41: Advanced | D41: Western Europe Destinations | E41: Rome | G41: 2.7 | H41: 27 | I41: 56.4125 | J41: 2.0893518 | K41: 1051 | L41: 0.025689819 | M41: 2.8635585 | N41: 0.14814815 | O41: =I41/T41 -> 14.103125 | P41: 5729 | Q41: =I41 -> 56.4125 | R41: =P41-Q41 -> 5672.5875 | S41: =IF(Q41=0,0,(P41-Q41)/Q41) -> 100.55551 | T41: 4 | U41: =IF(T41=0,"NA",P41/T41) -> 1432.25 | V41: =(L41*N41) -> 0.0038058991 | W41: =IF(P41=0,0,R41/P41) -> 0.99015317 | X41: =IF(T41=0,0,Q41/T41) -> 14.103125 | Y41: =Q41*0.9 -> 50.77125 | Z41: =R41*1.05 -> 5956.2169 | AA41: =Q41-Y41 -> 5.64125 | AB41: =R41-Z41 -> -283.62938
A42: Google - US | B42: rabat flights | C42: Broad | D42: Google_Yearlong 2006 | E42: Google|rabat | F42: Postiion 1-4 Bid Strategy | G42: 6.25 | H42: 11 | I42: 14.075 | J42: 1.2795455 | K42: 361 | L42: 0.030470914 | M42: 1.1379501 | N42: 0.090909091 | O42: =I42/T42 -> 14.075 | P42: 1402.5 | Q42: =I42 -> 14.075 | R42: =P42-Q42 -> 1388.425 | S42: =IF(Q42=0,0,(P42-Q42)/Q42) -> 98.644761 | T42: 1 | U42: =IF(T42=0,"NA",P42/T42) -> 1402.5 | V42: =(L42*N42) -> 0.0027700831 | W42: =IF(P42=0,0,R42/P42) -> 0.98996435 | X42: =IF(T42=0,0,Q42/T42) -> 14.075 | Y42: =Q42*0.9 -> 12.6675 | Z42: =R42*1.05 -> 1457.8463 | AA42: =Q42-Y42 -> 1.4075 | AB42: =R42-Z42 -> -69.42125
A43: Yahoo - US | B43: airfrance,com | C43: Advanced | D43: Air France Branded | E43: Air France Website | G43: 7.5 | H43: 48 | I43: 7.3125 | J43: 0.15234375 | K43: 298 | L43: 0.16107383 | M43: 1 | N43: 0.020833333 | O43: =I43/T43 -> 7.3125 | P43: 718.25 | Q43: =I43 -> 7.3125 | R43: =P43-Q43 -> 710.9375 | S43: =IF(Q43=0,0,(P43-Q43)/Q43) -> 97.222222 | T43: 1 | U43: =IF(T43=0,"NA",P43/T43) -> 718.25 | V43: =(L43*N43) -> 0.0033557047 | W43: =IF(P43=0,0,R43/P43) -> 0.989819 | X43: =IF(T43=0,0,Q43/T43) -> 7.3125 | Y43: =Q43*0.9 -> 6.58125 | Z43: =R43*1.05 -> 746.48438 | AA43: =Q43-Y43 -> 0.73125 | AB43: =R43-Z43 -> -35.546875
A44: Overture - Global | B44: air france phone number | C44: Standard | D44: Unassigned | E44: Unassigned | F44: Position 1-2 Target | G44: 0.125 | H44: 65 | I44: 9.7124999 | J44: 0.14942307 | K44: 1831 | L44: 0.035499727 | M44: 2.4816494 | N44: 0.015384615 | O44: =I44/T44 -> 9.7124999 | P44: 947.75 | Q44: =I44 -> 9.7124999 | R44: =P44-Q44 -> 938.0375 | S44: =IF(Q44=0,0,(P44-Q44)/Q44) -> 96.580439 | T44: 1 | U44: =IF(T44=0,"NA",P44/T44) -> 947.75 | V44: =(L44*N44) -> 0.00054614965 | W44: =IF(P44=0,0,R44/P44) -> 0.98975204 | X44: =IF(T44=0,0,Q44/T44) -> 9.7124999 | Y44: =Q44*0.9 -> 8.7412499 | Z44: =R44*1.05 -> 984.93938 | AA44: =Q44-Y44 -> 0.97124999 | AB44: =R44-Z44 -> -46.901875
A45: Overture - US | B45: airline ticket to france | C45: Standard | D45: Unassigned | E45: Unassigned | F45: Position 1-4 Bid Strategy | G45: 1.2625 | H45: 14 | I45: 10.2625 | J45: 0.73303571 | K45: 225 | L45: 0.062222222 | M45: 2.1017778 | N45: 0.071428571 | O45: =I45/T45 -> 10.2625 | P45: 991.1 | Q45: =I45 -> 10.2625 | R45: =P45-Q45 -> 980.8375 | S45: =IF(Q45=0,0,(P45-Q45)/Q45) -> 95.574909 | T45: 1 | U45: =IF(T45=0,"NA",P45/T45) -> 991.1 | V45: =(L45*N45) -> 0.0044444444 | W45: =IF(P45=0,0,R45/P45) -> 0.98964534 | X45: =IF(T45=0,0,Q45/T45) -> 10.2625 | Y45: =Q45*0.9 -> 9.23625 | Z45: =R45*1.05 -> 1029.8794 | AA45: =Q45-Y45 -> 1.02625 | AB45: =R45-Z45 -> -49.041875
A46: Google - Global | B46: airfrance com | C46: Broad | D46: Air France Global Campaign | E46: Air France Website | F46: Position 1- 3 | G46: 2.5 | H46: 548 | I46: 247.9375 | J46: 0.45244069 | K46: 2919 | L46: 0.18773553 | M46: 1.4655361 | N46: 0.02189781 | O46: =I46/T46 -> 20.661458 | P46: 23041.8 | Q46: =I46 -> 247.9375 | R46: =P46-Q46 -> 22793.863 | S46: =IF(Q46=0,0,(P46-Q46)/Q46) -> 91.933906 | T46: 12 | U46: =IF(T46=0,"NA",P46/T46) -> 1920.15 | V46: =(L46*N46) -> 0.0041109969 | W46: =IF(P46=0,0,R46/P46) -> 0.98923966 | X46: =IF(T46=0,0,Q46/T46) -> 20.661458 | Y46: =Q46*0.9 -> 223.14375 | Z46: =R46*1.05 -> 23933.556 | AA46: =Q46-Y46 -> 24.79375 | AB46: =R46-Z46 -> -1139.6931
A47: Overture - Global | B47: new york to paris | C47: Advanced | D47: Unassigned | E47: Unassigned | F47: Position 1-2 Target | G47: 0.725 | H47: 39 | I47: 24.4375 | J47: 0.62660256 | K47: 2364 | L47: 0.016497462 | M47: 3.6335448 | N47: 0.025641026 | O47: =I47/T47 -> 24.4375 | P47: 2226.15 | Q47: =I47 -> 24.4375 | R47: =P47-Q47 -> 2201.7125 | S47: =IF(Q47=0,0,(P47-Q47)/Q47) -> 90.095652 | T47: 1 | U47: =IF(T47=0,"NA",P47/T47) -> 2226.15 | V47: =(L47*N47) -> 0.00042301184 | W47: =IF(P47=0,0,R47/P47) -> 0.98902253 | X47: =IF(T47=0,0,Q47/T47) -> 24.4375 | Y47: =Q47*0.9 -> 21.99375 | Z47: =R47*1.05 -> 2311.7981 | AA47: =Q47-Y47 -> 2.44375 | AB47: =R47-Z47 -> -110.08563
A48: Google - US | B48: cont:google_yearlong 2006::google|europe | C48: N/A | D48: Google_Yearlong 2006 | E48: Google|Europe | G48: 7.5 | H48: 112 | I48: 31.649999 | J48: 0.28258927 | K48: 157285 | L48: 0.00071208316 | M48: 2.3088775 | N48: 0.0089285714 | O48: =I48/T48 -> 31.649999 | P48: 2882.35 | Q48: =I48 -> 31.649999 | R48: =P48-Q48 -> 2850.7 | S48: =IF(Q48=0,0,(P48-Q48)/Q48) -> 90.069514 | T48: 1 | U48: =IF(T48=0,"NA",P48/T48) -> 2882.35 | V48: =(L48*N48) -> 6.3578854e-06 | W48: =IF(P48=0,0,R48/P48) -> 0.98901938 | X48: =IF(T48=0,0,Q48/T48) -> 31.649999 | Y48: =Q48*0.9 -> 28.484999 | Z48: =R48*1.05 -> 2993.235 | AA48: =Q48-Y48 -> 3.1649999 | AB48: =R48-Z48 -> -142.535
A49: Google - US | B49: airfrance | C49: Broad | D49: Air France Branded | E49: Air France Brand | G49: 27.5 | H49: 11789 | I49: 2412.5125 | J49: 0.20464098 | K49: 78814 | L49: 0.14958002 | M49: 1.1294811 | N49: 0.018491814 | O49: =I49/T49 -> 11.066571 | P49: 216915.75 | Q49: =I49 -> 2412.5125 | R49: =P49-Q49 -> 214503.24 | S49: =IF(Q49=0,0,(P49-Q49)/Q49) -> 88.9128 | T49: 218 | U49: =IF(T49=0,"NA",P49/T49) -> 995.02638 | V49: =(L49*N49) -> 0.002766006 | W49: =IF(P49=0,0,R49/P49) -> 0.98887811 | X49: =IF(T49=0,0,Q49/T49) -> 11.066571 | Y49: =Q49*0.9 -> 2171.2612 | Z49: =R49*1.05 -> 225228.4 | AA49: =Q49-Y49 -> 241.25125 | AB49: =R49-Z49 -> -10725.162
A50: Overture - Global | B50: cheap travel france | C50: Advanced | D50: Unassigned | E50: Unassigned | F50: Position 1-2 Target | G50: 0.475 | H50: 20 | I50: 10.4 | J50: 0.52 | K50: 501 | L50: 0.03992016 | M50: 2.1215569 | N50: 0.05 | O50: =I50/T50 -> 10.4 | P50: 935 | Q50: =I50 -> 10.4 | R50: =P50-Q50 -> 924.6 | S50: =IF(Q50=0,0,(P50-Q50)/Q50) -> 88.903846 | T50: 1 | U50: =IF(T50=0,"NA",P50/T50) -> 935 | V50: =(L50*N50) -> 0.001996008 | W50: =IF(P50=0,0,R50/P50) -> 0.98887701 | X50: =IF(T50=0,0,Q50/T50) -> 10.4 | Y50: =Q50*0.9 -> 9.36 | Z50: =R50*1.05 -> 970.83 | AA50: =Q50-Y50 -> 1.04 | AB50: =R50-Z50 -> -46.23
A51: Google - US | B51: paris flight | C51: Broad | D51: Geo Targeted Philadelphia | E51: Philadelphia to Paris Sale | F51: Position 5-10 Bid Strategy | G51: 6.25 | H51: 2 | I51: 4.8875 | J51: 2.44375 | K51: 38 | L51: 0.052631579 | M51: 1.7089474 | N51: 0.5 | O51: =I51/T51 -> 4.8875 | P51: 434.35 | Q51: =I51 -> 4.8875 | R51: =P51-Q51 -> 429.4625 | S51: =IF(Q51=0,0,(P51-Q51)/Q51) -> 87.869565 | T51: 1 | U51: =IF(T51=0,"NA",P51/T51) -> 434.35 | V51: =(L51*N51) -> 0.026315789 | W51: =IF(P51=0,0,R51/P51) -> 0.98874755 | X51: =IF(T51=0,0,Q51/T51) -> 4.8875 | Y51: =Q51*0.9 -> 4.39875 | Z51: =R51*1.05 -> 450.93563 | AA51: =Q51-Y51 -> 0.48875 | AB51: =R51-Z51 -> -21.473125
A52: Overture - Global | B52: airfrance.us | C52: Advanced | D52: Unassigned | E52: Unassigned | F52: Position 1-2 Target | G52: 0.1375 | H52: 207 | I52: 34.874998 | J52: 0.16847825 | K52: 1100 | L52: 0.18818182 | M52: 1.1695455 | N52: 0.019323671 | O52: =I52/T52 -> 8.7187494 | P52: 3035.35 | Q52: =I52 -> 34.874998 | R52: =P52-Q52 -> 3000.475 | S52: =IF(Q52=0,0,(P52-Q52)/Q52) -> 86.035131 | T52: 4 | U52: =IF(T52=0,"NA",P52/T52) -> 758.8375 | V52: =(L52*N52) -> 0.0036363636 | W52: =IF(P52=0,0,R52/P52) -> 0.98851039 | X52: =IF(T52=0,0,Q52/T52) -> 8.7187494 | Y52: =Q52*0.9 -> 31.387498 | Z52: =R52*1.05 -> 3150.4988 | AA52: =Q52-Y52 -> 3.4874998 | AB52: =R52-Z52 -> -150.02375
A53: Google - US | B53: airfrance airlines | C53: Broad | D53: Air France Branded | E53: Air France Brand | F53: Position 1 -2 Target | G53: 0.35 | H53: 116 | I53: 59.349999 | J53: 0.51163793 | K53: 776 | L53: 0.14948454 | M53: 1.3006959 | N53: 0.043103448 | O53: =I53/T53 -> 11.87 | P53: 5146.75 | Q53: =I53 -> 59.349999 | R53: =P53-Q53 -> 5087.4 | S53: =IF(Q53=0,0,(P53-Q53)/Q53) -> 85.718619 | T53: 5 | U53: =IF(T53=0,"NA",P53/T53) -> 1029.35 | V53: =(L53*N53) -> 0.006443299 | W53: =IF(P53=0,0,R53/P53) -> 0.98846845 | X53: =IF(T53=0,0,Q53/T53) -> 11.87 | Y53: =Q53*0.9 -> 53.414999 | Z53: =R53*1.05 -> 5341.77 | AA53: =Q53-Y53 -> 5.9349999 | AB53: =R53-Z53 -> -254.37
A54: Google - US | B54: florence cheap tickets | C54: Broad | D54: Geo Targeted New York | E54: New York to Florence Sale | F54: Position 5-10 Bid Strategy | G54: 6.25 | H54: 3 | I54: 5.975 | J54: 1.9916667 | K54: 6 | L54: 0.5 | M54: 2 | N54: 0.33333333 | O54: =I54/T54 -> 5.975 | P54: 490.45 | Q54: =I54 -> 5.975 | R54: =P54-Q54 -> 484.475 | S54: =IF(Q54=0,0,(P54-Q54)/Q54) -> 81.083682 | T54: 1 | U54: =IF(T54=0,"NA",P54/T54) -> 490.45 | V54: =(L54*N54) -> 0.16666667 | W54: =IF(P54=0,0,R54/P54) -> 0.98781731 | X54: =IF(T54=0,0,Q54/T54) -> 5.975 | Y54: =Q54*0.9 -> 5.3775 | Z54: =R54*1.05 -> 508.69875 | AA54: =Q54-Y54 -> 0.5975 | AB54: =R54-Z54 -> -24.22375
A55: Yahoo - US | B55: air france travel | C55: Advanced | D55: Air France Branded | E55: Air France Brand | G55: 6.25 | H55: 24 | I55: 33.7875 | J55: 1.4078125 | K55: 1171 | L55: 0.020495303 | M55: 3.0695218 | N55: 0.041666667 | O55: =I55/T55 -> 33.7875 | P55: 2772.7 | Q55: =I55 -> 33.7875 | R55: =P55-Q55 -> 2738.9125 | S55: =IF(Q55=0,0,(P55-Q55)/Q55) -> 81.062893 | T55: 1 | U55: =IF(T55=0,"NA",P55/T55) -> 2772.7 | V55: =(L55*N55) -> 0.00085397096 | W55: =IF(P55=0,0,R55/P55) -> 0.98781422 | X55: =IF(T55=0,0,Q55/T55) -> 33.7875 | Y55: =Q55*0.9 -> 30.40875 | Z55: =R55*1.05 -> 2875.8581 | AA55: =Q55-Y55 -> 3.37875 | AB55: =R55-Z55 -> -136.94563
A56: Google - US | B56: rome fare | C56: Broad | D56: Google_Yearlong 2006 | E56: Google|Rome | F56: Postiion 1-4 Bid Strategy | G56: 6.25 | H56: 14 | I56: 20.1125 | J56: 1.4366071 | K56: 310 | L56: 0.04516129 | M56: 1.4922581 | N56: 0.071428571 | O56: =I56/T56 -> 20.1125 | P56: 1489.2 | Q56: =I56 -> 20.1125 | R56: =P56-Q56 -> 1469.0875 | S56: =IF(Q56=0,0,(P56-Q56)/Q56) -> 73.043506 | T56: 1 | U56: =IF(T56=0,"NA",P56/T56) -> 1489.2 | V56: =(L56*N56) -> 0.0032258065 | W56: =IF(P56=0,0,R56/P56) -> 0.98649443 | X56: =IF(T56=0,0,Q56/T56) -> 20.1125 | Y56: =Q56*0.9 -> 18.10125 | Z56: =R56*1.05 -> 1542.5419 | AA56: =Q56-Y56 -> 2.01125 | AB56: =R56-Z56 -> -73.454375
A57: Google - US | B57: air france com | C57: Broad | D57: Air France Branded | E57: Air France Website | F57: Postiion 1-4 Bid Strategy | G57: 15 | H57: 6119 | I57: 1905.8624 | J57: 0.31146632 | K57: 15166 | L57: 0.40346828 | M57: 1.0388712 | N57: 0.019120771 | O57: =I57/T57 -> 16.289423 | P57: 132065.35 | Q57: =I57 -> 1905.8624 | R57: =P57-Q57 -> 130159.49 | S57: =IF(Q57=0,0,(P57-Q57)/Q57) -> 68.294272 | T57: 117 | U57: =IF(T57=0,"NA",P57/T57) -> 1128.7637 | V57: =(L57*N57) -> 0.0077146248 | W57: =IF(P57=0,0,R57/P57) -> 0.98556879 | X57: =IF(T57=0,0,Q57/T57) -> 16.289423 | Y57: =Q57*0.9 -> 1715.2762 | Z57: =R57*1.05 -> 136667.46 | AA57: =Q57-Y57 -> 190.58624 | AB57: =R57-Z57 -> -6507.9744
A58: MSN - US | B58: air travel in france | C58: Broad | D58: Air France Brand & French Destinations | E58: France | G58: 0 | H58: 2 | I58: 7.5625 | J58: 3.78125 | K58: 35 | L58: 0.057142857 | M58: 6.0845714 | N58: 0.5 | O58: =I58/T58 -> 7.5625 | P58: 512.55 | Q58: =I58 -> 7.5625 | R58: =P58-Q58 -> 504.9875 | S58: =IF(Q58=0,0,(P58-Q58)/Q58) -> 66.775207 | T58: 1 | U58: =IF(T58=0,"NA",P58/T58) -> 512.55 | V58: =(L58*N58) -> 0.028571429 | W58: =IF(P58=0,0,R58/P58) -> 0.98524534 | X58: =IF(T58=0,0,Q58/T58) -> 7.5625 | Y58: =Q58*0.9 -> 6.80625 | Z58: =R58*1.05 -> 530.23687 | AA58: =Q58-Y58 -> 0.75625 | AB58: =R58-Z58 -> -25.249375
A59: Google - US | B59: airfrance usa | C59: Broad | D59: Air France Branded | E59: Air France Website | G59: 10 | H59: 57 | I59: 15 | J59: 0.26315789 | K59: 200 | L59: 0.285 | M59: 1.005 | N59: 0.01754386 | O59: =I59/T59 -> 15 | P59: 1008.95 | Q59: =I59 -> 15 | R59: =P59-Q59 -> 993.95 | S59: =IF(Q59=0,0,(P59-Q59)/Q59) -> 66.263335 | T59: 1 | U59: =IF(T59=0,"NA",P59/T59) -> 1008.95 | V59: =(L59*N59) -> 0.005 | W59: =IF(P59=0,0,R59/P59) -> 0.98513306 | X59: =IF(T59=0,0,Q59/T59) -> 15 | Y59: =Q59*0.9 -> 13.5 | Z59: =R59*1.05 -> 1043.6475 | AA59: =Q59-Y59 -> 1.5 | AB59: =R59-Z59 -> -49.6975
A60: Google - US | B60: france cheap tickets | C60: Broad | D60: Geo Targeted DC | E60: DC to France Sale | F60: Position 5-10 Bid Strategy | G60: 6.25 | H60: 3 | I60: 7.3875 | J60: 2.4625 | K60: 22 | L60: 0.13636364 | M60: 1.09 | N60: 0.33333333 | O60: =I60/T60 -> 7.3875 | P60: 490.45 | Q60: =I60 -> 7.3875 | R60: =P60-Q60 -> 483.0625 | S60: =IF(Q60=0,0,(P60-Q60)/Q60) -> 65.389171 | T60: 1 | U60: =IF(T60=0,"NA",P60/T60) -> 490.45 | V60: =(L60*N60) -> 0.045454545 | W60: =IF(P60=0,0,R60/P60) -> 0.9849373 | X60: =IF(T60=0,0,Q60/T60) -> 7.3875 | Y60: =Q60*0.9 -> 6.64875 | Z60: =R60*1.05 -> 507.21563 | AA60: =Q60-Y60 -> 0.73875 | AB60: =R60-Z60 -> -24.153125
A61: Overture - Global | B61: boston to paris | C61: Advanced | D61: Unassigned | E61: Unassigned | F61: Position 1-2 Target | G61: 0.725 | H61: 23 | I61: 12.5875 | J61: 0.5472826 | K61: 699 | L61: 0.032904149 | M61: 2.4997139 | N61: 0.043478261 | O61: =I61/T61 -> 12.5875 | P61: 806.65 | Q61: =I61 -> 12.5875 | R61: =P61-Q61 -> 794.0625 | S61: =IF(Q61=0,0,(P61-Q61)/Q61) -> 63.083417 | T61: 1 | U61: =IF(T61=0,"NA",P61/T61) -> 806.65 | V61: =(L61*N61) -> 0.0014306152 | W61: =IF(P61=0,0,R61/P61) -> 0.98439534 | X61: =IF(T61=0,0,Q61/T61) -> 12.5875 | Y61: =Q61*0.9 -> 11.32875 | Z61: =R61*1.05 -> 833.76563 | AA61: =Q61-Y61 -> 1.25875 | AB61: =R61-Z61 -> -39.703125
A62: Google - US | B62: paris ticket | C62: Broad | D62: Geo Targeted Chicago | E62: Chicago to Paris Sale | F62: Position 5-10 Bid Strategy | G62: 6.25 | H62: 6 | I62: 14.725 | J62: 2.4541667 | K62: 97 | L62: 0.06185567 | M62: 1.2561856 | N62: 0.16666667 | O62: =I62/T62 -> 14.725 | P62: 940.95 | Q62: =I62 -> 14.725 | R62: =P62-Q62 -> 926.225 | S62: =IF(Q62=0,0,(P62-Q62)/Q62) -> 62.901528 | T62: 1 | U62: =IF(T62=0,"NA",P62/T62) -> 940.95 | V62: =(L62*N62) -> 0.010309278 | W62: =IF(P62=0,0,R62/P62) -> 0.98435092 | X62: =IF(T62=0,0,Q62/T62) -> 14.725 | Y62: =Q62*0.9 -> 13.2525 | Z62: =R62*1.05 -> 972.53625 | AA62: =Q62-Y62 -> 1.4725 | AB62: =R62-Z62 -> -46.31125
A63: Google - Global | B63: air france com | C63: Broad | D63: Air France Global Campaign | E63: Air France Website | F63: Position 1- 3 | G63: 0 | H63: 661 | I63: 202.8 | J63: 0.30680786 | K63: 2703 | L63: 0.2445431 | M63: 1.4758417 | N63: 0.015128593 | O63: =I63/T63 -> 20.28 | P63: 11950.15 | Q63: =I63 -> 202.8 | R63: =P63-Q63 -> 11747.35 | S63: =IF(Q63=0,0,(P63-Q63)/Q63) -> 57.92579 | T63: 10 | U63: =IF(T63=0,"NA",P63/T63) -> 1195.015 | V63: =(L63*N63) -> 0.003699593 | W63: =IF(P63=0,0,R63/P63) -> 0.9830295 | X63: =IF(T63=0,0,Q63/T63) -> 20.28 | Y63: =Q63*0.9 -> 182.52 | Z63: =R63*1.05 -> 12334.718 | AA63: =Q63-Y63 -> 20.28 | AB63: =R63-Z63 -> -587.3675
A64: Overture - Global | B64: cheap airline ticket to france | C64: Advanced | D64: Unassigned | E64: Unassigned | F64: Position 1-2 Target | G64: 0.3125 | H64: 26 | I64: 16.0625 | J64: 0.61778845 | K64: 9279 | L64: 0.0028020261 | M64: 2.3996767 | N64: 0.038461538 | O64: =I64/T64 -> 16.0625 | P64: 935 | Q64: =I64 -> 16.0625 | R64: =P64-Q64 -> 918.9375 | S64: =IF(Q64=0,0,(P64-Q64)/Q64) -> 57.210118 | T64: 1 | U64: =IF(T64=0,"NA",P64/T64) -> 935 | V64: =(L64*N64) -> 0.00010777023 | W64: =IF(P64=0,0,R64/P64) -> 0.98282086 | X64: =IF(T64=0,0,Q64/T64) -> 16.0625 | Y64: =Q64*0.9 -> 14.45625 | Z64: =R64*1.05 -> 964.88438 | AA64: =Q64-Y64 -> 1.60625 | AB64: =R64-Z64 -> -45.946875
A65: Google - Global | B65: air france com | C65: Broad | D65: Air France Brand & French Destinations | E65: Air France Website | G65: 5 | H65: 568 | I65: 263.125 | J65: 0.46324824 | K65: 1710 | L65: 0.33216374 | M65: 1.1094152 | N65: 0.022887324 | O65: =I65/T65 -> 20.240385 | P65: 15011 | Q65: =I65 -> 263.125 | R65: =P65-Q65 -> 14747.875 | S65: =IF(Q65=0,0,(P65-Q65)/Q65) -> 56.048931 | T65: 13 | U65: =IF(T65=0,"NA",P65/T65) -> 1154.6923 | V65: =(L65*N65) -> 0.0076023392 | W65: =IF(P65=0,0,R65/P65) -> 0.98247119 | X65: =IF(T65=0,0,Q65/T65) -> 20.240385 | Y65: =Q65*0.9 -> 236.8125 | Z65: =R65*1.05 -> 15485.269 | AA65: =Q65-Y65 -> 26.3125 | AB65: =R65-Z65 -> -737.39375
A66: Overture - Global | B66: airfrance.com | C66: Standard | D66: Unassigned | E66: Unassigned | G66: 8.75 | H66: 2010 | I66: 574.24999 | J66: 0.28569651 | K66: 37801 | L66: 0.053173196 | M66: 1.1638951 | N66: 0.017910448 | O66: =I66/T66 -> 15.951389 | P66: 32613.65 | Q66: =I66 -> 574.24999 | R66: =P66-Q66 -> 32039.4 | S66: =IF(Q66=0,0,(P66-Q66)/Q66) -> 55.793471 | T66: 36 | U66: =IF(T66=0,"NA",P66/T66) -> 905.93472 | V66: =(L66*N66) -> 0.00095235576 | W66: =IF(P66=0,0,R66/P66) -> 0.98239234 | X66: =IF(T66=0,0,Q66/T66) -> 15.951389 | Y66: =Q66*0.9 -> 516.82499 | Z66: =R66*1.05 -> 33641.37 | AA66: =Q66-Y66 -> 57.424999 | AB66: =R66-Z66 -> -1601.97
A67: Google - US | B67: air france website | C67: Broad | D67: Air France Branded | E67: Air France Website | F67: Position 2-5 Bid Strategy | G67: 0.3 | H67: 187 | I67: 66.562498 | J67: 0.35594919 | K67: 899 | L67: 0.2080089 | M67: 1.1424472 | N67: 0.021390374 | O67: =I67/T67 -> 16.640625 | P67: 3621 | Q67: =I67 -> 66.562498 | R67: =P67-Q67 -> 3554.4375 | S67: =IF(Q67=0,0,(P67-Q67)/Q67) -> 53.400002 | T67: 4 | U67: =IF(T67=0,"NA",P67/T67) -> 905.25 | V67: =(L67*N67) -> 0.0044493882 | W67: =IF(P67=0,0,R67/P67) -> 0.98161765 | X67: =IF(T67=0,0,Q67/T67) -> 16.640625 | Y67: =Q67*0.9 -> 59.906248 | Z67: =R67*1.05 -> 3732.1594 | AA67: =Q67-Y67 -> 6.6562498 | AB67: =R67-Z67 -> -177.72188
A68: Google - US | B68: paris air fares | C68: Broad | D68: Geo Targeted New York | E68: New York to Paris Sale | F68: Position 5-10 Bid Strategy | G68: 6.25 | H68: 10 | I68: 25.0125 | J68: 2.50125 | K68: 41 | L68: 0.24390244 | M68: 1.194878 | N68: 0.1 | O68: =I68/T68 -> 25.0125 | P68: 1360 | Q68: =I68 -> 25.0125 | R68: =P68-Q68 -> 1334.9875 | S68: =IF(Q68=0,0,(P68-Q68)/Q68) -> 53.372814 | T68: 1 | U68: =IF(T68=0,"NA",P68/T68) -> 1360 | V68: =(L68*N68) -> 0.024390244 | W68: =IF(P68=0,0,R68/P68) -> 0.98160846 | X68: =IF(T68=0,0,Q68/T68) -> 25.0125 | Y68: =Q68*0.9 -> 22.51125 | Z68: =R68*1.05 -> 1401.7369 | AA68: =Q68-Y68 -> 2.50125 | AB68: =R68-Z68 -> -66.749375
A69: Overture - US | B69: europe ticket | C69: Standard | D69: Unassigned | E69: Unassigned | F69: Position 1-4 Bid Strategy | G69: 0.8625 | H69: 123 | I69: 81.312499 | J69: 0.66107722 | K69: 3325 | L69: 0.036992481 | M69: 2.1720902 | N69: 0.016260163 | O69: =I69/T69 -> 40.656249 | P69: 4187.1 | Q69: =I69 -> 81.312499 | R69: =P69-Q69 -> 4105.7875 | S69: =IF(Q69=0,0,(P69-Q69)/Q69) -> 50.493929 | T69: 2 | U69: =IF(T69=0,"NA",P69/T69) -> 2093.55 | V69: =(L69*N69) -> 0.00060150376 | W69: =IF(P69=0,0,R69/P69) -> 0.98058023 | X69: =IF(T69=0,0,Q69/T69) -> 40.656249 | Y69: =Q69*0.9 -> 73.181249 | Z69: =R69*1.05 -> 4311.0769 | AA69: =Q69-Y69 -> 8.1312499 | AB69: =R69-Z69 -> -205.28938
A70: Google - US | B70: paris air flight | C70: Broad | D70: Geo Targeted Houston | E70: Houston to Paris Sale | F70: Position 5-10 Bid Strategy | G70: 6.25 | H70: 4 | I70: 8.4875 | J70: 2.121875 | K70: 20 | L70: 0.2 | M70: 1.35 | N70: 0.25 | O70: =I70/T70 -> 8.4875 | P70: 426.7 | Q70: =I70 -> 8.4875 | R70: =P70-Q70 -> 418.2125 | S70: =IF(Q70=0,0,(P70-Q70)/Q70) -> 49.273932 | T70: 1 | U70: =IF(T70=0,"NA",P70/T70) -> 426.7 | V70: =(L70*N70) -> 0.05 | W70: =IF(P70=0,0,R70/P70) -> 0.98010898 | X70: =IF(T70=0,0,Q70/T70) -> 8.4875 | Y70: =Q70*0.9 -> 7.63875 | Z70: =R70*1.05 -> 439.12313 | AA70: =Q70-Y70 -> 0.84875 | AB70: =R70-Z70 -> -20.910625
A71: Google - US | B71: paris airfares | C71: Broad | D71: Geo Targeted New York | E71: New York to Paris Sale | F71: Position 5-10 Bid Strategy | G71: 6.25 | H71: 21 | I71: 50.2 | J71: 2.3904762 | K71: 195 | L71: 0.10769231 | M71: 1.8745641 | N71: 0.095238095 | O71: =I71/T71 -> 25.1 | P71: 2450.55 | Q71: =I71 -> 50.2 | R71: =P71-Q71 -> 2400.35 | S71: =IF(Q71=0,0,(P71-Q71)/Q71) -> 47.815737 | T71: 2 | U71: =IF(T71=0,"NA",P71/T71) -> 1225.275 | V71: =(L71*N71) -> 0.01025641 | W71: =IF(P71=0,0,R71/P71) -> 0.9795148 | X71: =IF(T71=0,0,Q71/T71) -> 25.1 | Y71: =Q71*0.9 -> 45.18 | Z71: =R71*1.05 -> 2520.3675 | AA71: =Q71-Y71 -> 5.02 | AB71: =R71-Z71 -> -120.0175
A72: Google - Global | B72: [air france] | C72: Exact | D72: Air France Global Campaign | E72: Air France | F72: Position 1- 3 | G72: 1.25 | H72: 11150 | I72: 4886.0999 | J72: 0.43821524 | K72: 107222 | L72: 0.10398985 | M72: 1.8312035 | N72: 0.015964126 | O72: =I72/T72 -> 27.449999 | P72: 235965.95 | Q72: =I72 -> 4886.0999 | R72: =P72-Q72 -> 231079.85 | S72: =IF(Q72=0,0,(P72-Q72)/Q72) -> 47.293313 | T72: 178 | U72: =IF(T72=0,"NA",P72/T72) -> 1325.6514 | V72: =(L72*N72) -> 0.0016601071 | W72: =IF(P72=0,0,R72/P72) -> 0.9792932 | X72: =IF(T72=0,0,Q72/T72) -> 27.449999 | Y72: =Q72*0.9 -> 4397.4899 | Z72: =R72*1.05 -> 242633.84 | AA72: =Q72-Y72 -> 488.60999 | AB72: =R72-Z72 -> -11553.993
A73: Overture - Global | B73: air france fr | C73: Advanced | D73: Unassigned | E73: Unassigned | G73: 7.5 | H73: 60 | I73: 16.75 | J73: 0.27916666 | K73: 3370 | L73: 0.017804154 | M73: 1.0401484 | N73: 0.016666667 | O73: =I73/T73 -> 16.75 | P73: 769.25 | Q73: =I73 -> 16.75 | R73: =P73-Q73 -> 752.5 | S73: =IF(Q73=0,0,(P73-Q73)/Q73) -> 44.925374 | T73: 1 | U73: =IF(T73=0,"NA",P73/T73) -> 769.25 | V73: =(L73*N73) -> 0.00029673591 | W73: =IF(P73=0,0,R73/P73) -> 0.97822554 | X73: =IF(T73=0,0,Q73/T73) -> 16.75 | Y73: =Q73*0.9 -> 15.075 | Z73: =R73*1.05 -> 790.125 | AA73: =Q73-Y73 -> 1.675 | AB73: =R73-Z73 -> -37.625
A74: Google - US | B74: airfrance com | C74: Broad | D74: Air France Branded | E74: Air France Website | F74: Postiion 1-4 Bid Strategy | G74: 11.5 | H74: 3853 | I74: 1670.7375 | J74: 0.4336199 | K74: 22668 | L74: 0.1699753 | M74: 1.0531719 | N74: 0.016610433 | O74: =I74/T74 -> 26.105273 | P74: 76245.85 | Q74: =I74 -> 1670.7375 | R74: =P74-Q74 -> 74575.113 | S74: =IF(Q74=0,0,(P74-Q74)/Q74) -> 44.636045 | T74: 64 | U74: =IF(T74=0,"NA",P74/T74) -> 1191.3414 | V74: =(L74*N74) -> 0.0028233633 | W74: =IF(P74=0,0,R74/P74) -> 0.9780875 | X74: =IF(T74=0,0,Q74/T74) -> 26.105273 | Y74: =Q74*0.9 -> 1503.6637 | Z74: =R74*1.05 -> 78303.868 | AA74: =Q74-Y74 -> 167.07375 | AB74: =R74-Z74 -> -3728.7556
A75: Google - US | B75: air france usa | C75: Broad | D75: Air France Branded | E75: Air France Website | G75: 10 | H75: 558 | I75: 241.1875 | J75: 0.43223566 | K75: 1602 | L75: 0.34831461 | M75: 1.0323533 | N75: 0.019713262 | O75: =I75/T75 -> 21.926136 | P75: 10767.8 | Q75: =I75 -> 241.1875 | R75: =P75-Q75 -> 10526.613 | S75: =IF(Q75=0,0,(P75-Q75)/Q75) -> 43.644934 | T75: 11 | U75: =IF(T75=0,"NA",P75/T75) -> 978.89091 | V75: =(L75*N75) -> 0.006866417 | W75: =IF(P75=0,0,R75/P75) -> 0.97760104 | X75: =IF(T75=0,0,Q75/T75) -> 21.926136 | Y75: =Q75*0.9 -> 217.06875 | Z75: =R75*1.05 -> 11052.943 | AA75: =Q75-Y75 -> 24.11875 | AB75: =R75-Z75 -> -526.33063
A76: Overture - Global | B76: air france.com | C76: Advanced | D76: Unassigned | E76: Unassigned | G76: 8.75 | H76: 681 | I76: 130.27499 | J76: 0.19129955 | K76: 7996 | L76: 0.085167584 | M76: 1.1776138 | N76: 0.010279001 | O76: =I76/T76 -> 18.610713 | P76: 5767.25 | Q76: =I76 -> 130.27499 | R76: =P76-Q76 -> 5636.975 | S76: =IF(Q76=0,0,(P76-Q76)/Q76) -> 43.269816 | T76: 7 | U76: =IF(T76=0,"NA",P76/T76) -> 823.89286 | V76: =(L76*N76) -> 0.00087543772 | W76: =IF(P76=0,0,R76/P76) -> 0.97741125 | X76: =IF(T76=0,0,Q76/T76) -> 18.610713 | Y76: =Q76*0.9 -> 117.24749 | Z76: =R76*1.05 -> 5918.8238 | AA76: =Q76-Y76 -> 13.027499 | AB76: =R76-Z76 -> -281.84875
A77: Google - US | B77: paris tickets | C77: Broad | D77: Geo Targeted Seattle | E77: Seattle to Paris Sale | F77: Position 2-5 Bid Strategy | G77: 5 | H77: 12 | I77: 34.0875 | J77: 2.840625 | K77: 538 | L77: 0.022304833 | M77: 1.6939405 | N77: 0.083333333 | O77: =I77/T77 -> 34.0875 | P77: 1439.9 | Q77: =I77 -> 34.0875 | R77: =P77-Q77 -> 1405.8125 | S77: =IF(Q77=0,0,(P77-Q77)/Q77) -> 41.241291 | T77: 1 | U77: =IF(T77=0,"NA",P77/T77) -> 1439.9 | V77: =(L77*N77) -> 0.0018587361 | W77: =IF(P77=0,0,R77/P77) -> 0.97632648 | X77: =IF(T77=0,0,Q77/T77) -> 34.0875 | Y77: =Q77*0.9 -> 30.67875 | Z77: =R77*1.05 -> 1476.1031 | AA77: =Q77-Y77 -> 3.40875 | AB77: =R77-Z77 -> -70.290625
A78: Google - US | B78: paris cheap air tickets | C78: Broad | D78: Geo Targeted New York | E78: New York to Paris Sale | F78: Position 5-10 Bid Strategy | G78: 6.25 | H78: 5 | I78: 12.1125 | J78: 2.4225 | K78: 7 | L78: 0.71428571 | M78: 1 | N78: 0.2 | O78: =I78/T78 -> 12.1125 | P78: 494.7 | Q78: =I78 -> 12.1125 | R78: =P78-Q78 -> 482.5875 | S78: =IF(Q78=0,0,(P78-Q78)/Q78) -> 39.842105 | T78: 1 | U78: =IF(T78=0,"NA",P78/T78) -> 494.7 | V78: =(L78*N78) -> 0.14285714 | W78: =IF(P78=0,0,R78/P78) -> 0.97551546 | X78: =IF(T78=0,0,Q78/T78) -> 12.1125 | Y78: =Q78*0.9 -> 10.90125 | Z78: =R78*1.05 -> 506.71688 | AA78: =Q78-Y78 -> 1.21125 | AB78: =R78-Z78 -> -24.129375
A79: Google - Global | B79: paris airline | C79: Broad | D79: Air France Global Campaign | E79: Tour de France | G79: 6.25 | H79: 16 | I79: 27.425 | J79: 1.7140625 | K79: 1602 | L79: 0.0099875156 | M79: 1.240824 | N79: 0.0625 | O79: =I79/T79 -> 27.425 | P79: 1098.2 | Q79: =I79 -> 27.425 | R79: =P79-Q79 -> 1070.775 | S79: =IF(Q79=0,0,(P79-Q79)/Q79) -> 39.043756 | T79: 1 | U79: =IF(T79=0,"NA",P79/T79) -> 1098.2 | V79: =(L79*N79) -> 0.00062421973 | W79: =IF(P79=0,0,R79/P79) -> 0.97502732 | X79: =IF(T79=0,0,Q79/T79) -> 27.425 | Y79: =Q79*0.9 -> 24.6825 | Z79: =R79*1.05 -> 1124.3138 | AA79: =Q79-Y79 -> 2.7425 | AB79: =R79-Z79 -> -53.53875
A80: Google - US | B80: france airlines | C80: Broad | D80: Geo Targeted New York | E80: New York to France Sale | F80: Postiion 1-4 Bid Strategy | G80: 6.25 | H80: 119 | I80: 286.3 | J80: 2.4058824 | K80: 4403 | L80: 0.027027027 | M80: 1.6807745 | N80: 0.075630252 | O80: =I80/T80 -> 31.811111 | P80: 11301.6 | Q80: =I80 -> 286.3 | R80: =P80-Q80 -> 11015.3 | S80: =IF(Q80=0,0,(P80-Q80)/Q80) -> 38.474677 | T80: 9 | U80: =IF(T80=0,"NA",P80/T80) -> 1255.7333 | V80: =(L80*N80) -> 0.0020440609 | W80: =IF(P80=0,0,R80/P80) -> 0.9746673 | X80: =IF(T80=0,0,Q80/T80) -> 31.811111 | Y80: =Q80*0.9 -> 257.67 | Z80: =R80*1.05 -> 11566.065 | AA80: =Q80-Y80 -> 28.63 | AB80: =R80-Z80 -> -550.765
A81: Google - US | B81: france air flight | C81: Broad | D81: Geo Targeted New York | E81: New York to France Sale | F81: Position 5-10 Bid Strategy | G81: 6.25 | H81: 55 | I81: 41.399999 | J81: 0.75272726 | K81: 776 | L81: 0.070876289 | M81: 1.0417397 | N81: 0.036363636 | O81: =I81/T81 -> 20.7 | P81: 1616.7 | Q81: =I81 -> 41.399999 | R81: =P81-Q81 -> 1575.3 | S81: =IF(Q81=0,0,(P81-Q81)/Q81) -> 38.050725 | T81: 2 | U81: =IF(T81=0,"NA",P81/T81) -> 808.35 | V81: =(L81*N81) -> 0.0025773196 | W81: =IF(P81=0,0,R81/P81) -> 0.97439228 | X81: =IF(T81=0,0,Q81/T81) -> 20.7 | Y81: =Q81*0.9 -> 37.259999 | Z81: =R81*1.05 -> 1654.065 | AA81: =Q81-Y81 -> 4.1399999 | AB81: =R81-Z81 -> -78.765
A82: Google - US | B82: france air flight | C82: Broad | D82: Geo Targeted Los Angeles | E82: Los Angeles to France Sale | F82: Position 5-10 Bid Strategy | G82: 6.25 | H82: 9 | I82: 12.425 | J82: 1.3805555 | K82: 67 | L82: 0.13432836 | M82: 1.1358209 | N82: 0.11111111 | O82: =I82/T82 -> 12.425 | P82: 483.65 | Q82: =I82 -> 12.425 | R82: =P82-Q82 -> 471.225 | S82: =IF(Q82=0,0,(P82-Q82)/Q82) -> 37.925553 | T82: 1 | U82: =IF(T82=0,"NA",P82/T82) -> 483.65 | V82: =(L82*N82) -> 0.014925373 | W82: =IF(P82=0,0,R82/P82) -> 0.97430993 | X82: =IF(T82=0,0,Q82/T82) -> 12.425 | Y82: =Q82*0.9 -> 11.1825 | Z82: =R82*1.05 -> 494.78625 | AA82: =Q82-Y82 -> 1.2425 | AB82: =R82-Z82 -> -23.56125
A83: Google - US | B83: [air france] | C83: Exact | D83: Air France Branded | E83: Air France Brand | G83: 27.5 | H83: 30418 | I83: 13336.812 | J83: 0.43845133 | K83: 188409 | L83: 0.16144664 | M83: 1.265507 | N83: 0.014432244 | O83: =I83/T83 -> 30.379983 | P83: 515791.9 | Q83: =I83 -> 13336.812 | R83: =P83-Q83 -> 502455.09 | S83: =IF(Q83=0,0,(P83-Q83)/Q83) -> 37.674301 | T83: 439 | U83: =IF(T83=0,"NA",P83/T83) -> 1174.9246 | V83: =(L83*N83) -> 0.0023300373 | W83: =IF(P83=0,0,R83/P83) -> 0.97414304 | X83: =IF(T83=0,0,Q83/T83) -> 30.379983 | Y83: =Q83*0.9 -> 12003.131 | Z83: =R83*1.05 -> 527577.84 | AA83: =Q83-Y83 -> 1333.6812 | AB83: =R83-Z83 -> -25122.754
A84: Google - US | B84: airfrance tickets | C84: Broad | D84: Air France Branded | E84: Air France Brand | F84: Position 1 -2 Target | G84: 0.925 | H84: 33 | I84: 29.2625 | J84: 0.88674241 | K84: 241 | L84: 0.13692946 | M84: 1.193361 | N84: 0.03030303 | O84: =I84/T84 -> 29.2625 | P84: 1123.7 | Q84: =I84 -> 29.2625 | R84: =P84-Q84 -> 1094.4375 | S84: =IF(Q84=0,0,(P84-Q84)/Q84) -> 37.400684 | T84: 1 | U84: =IF(T84=0,"NA",P84/T84) -> 1123.7 | V84: =(L84*N84) -> 0.0041493776 | W84: =IF(P84=0,0,R84/P84) -> 0.9739588 | X84: =IF(T84=0,0,Q84/T84) -> 29.2625 | Y84: =Q84*0.9 -> 26.33625 | Z84: =R84*1.05 -> 1149.1594 | AA84: =Q84-Y84 -> 2.92625 | AB84: =R84-Z84 -> -54.721875
A85: Google - US | B85: airfrance airline | C85: Broad | D85: Air France Branded | E85: Air France Brand | F85: Position 1 -2 Target | G85: 0.2875 | H85: 95 | I85: 50.387499 | J85: 0.53039472 | K85: 712 | L85: 0.13342697 | M85: 1.3119522 | N85: 0.010526316 | O85: =I85/T85 -> 50.387499 | P85: 1887 | Q85: =I85 -> 50.387499 | R85: =P85-Q85 -> 1836.6125 | S85: =IF(Q85=0,0,(P85-Q85)/Q85) -> 36.449765 | T85: 1 | U85: =IF(T85=0,"NA",P85/T85) -> 1887 | V85: =(L85*N85) -> 0.0014044944 | W85: =IF(P85=0,0,R85/P85) -> 0.97329756 | X85: =IF(T85=0,0,Q85/T85) -> 50.387499 | Y85: =Q85*0.9 -> 45.348749 | Z85: =R85*1.05 -> 1928.4431 | AA85: =Q85-Y85 -> 5.0387499 | AB85: =R85-Z85 -> -91.830625
A86: Yahoo - US | B86: international flight | C86: Advanced | D86: Geo Targeted Chicago | E86: International Chicago | G86: 6.25 | H86: 86 | I86: 118.8875 | J86: 1.3824128 | K86: 1215 | L86: 0.070781893 | M86: 1.3184444 | N86: 0.011627907 | O86: =I86/T86 -> 118.8875 | P86: 4403.85 | Q86: =I86 -> 118.8875 | R86: =P86-Q86 -> 4284.9625 | S86: =IF(Q86=0,0,(P86-Q86)/Q86) -> 36.042162 | T86: 1 | U86: =IF(T86=0,"NA",P86/T86) -> 4403.85 | V86: =(L86*N86) -> 0.00082304527 | W86: =IF(P86=0,0,R86/P86) -> 0.97300374 | X86: =IF(T86=0,0,Q86/T86) -> 118.8875 | Y86: =Q86*0.9 -> 106.99875 | Z86: =R86*1.05 -> 4499.2106 | AA86: =Q86-Y86 -> 11.88875 | AB86: =R86-Z86 -> -214.24813
A87: Google - Global | B87: airfrance | C87: Broad | D87: Air France Global Campaign | E87: Air France | F87: Position 1- 3 | G87: 2.5 | H87: 1383 | I87: 998.38749 | J87: 0.72189985 | K87: 23310 | L87: 0.059330759 | M87: 1.6499571 | N87: 0.026753435 | O87: =I87/T87 -> 26.983446 | P87: 35357.45 | Q87: =I87 -> 998.38749 | R87: =P87-Q87 -> 34359.063 | S87: =IF(Q87=0,0,(P87-Q87)/Q87) -> 34.414556 | T87: 37 | U87: =IF(T87=0,"NA",P87/T87) -> 955.60676 | V87: =(L87*N87) -> 0.0015873016 | W87: =IF(P87=0,0,R87/P87) -> 0.97176302 | X87: =IF(T87=0,0,Q87/T87) -> 26.983446 | Y87: =Q87*0.9 -> 898.54874 | Z87: =R87*1.05 -> 36077.016 | AA87: =Q87-Y87 -> 99.838749 | AB87: =R87-Z87 -> -1717.9531
A88: Yahoo - US | B88: airfrance.com | C88: Advanced | D88: Air France Branded | E88: Air France Website | G88: 7.5 | H88: 4023 | I88: 3491.7875 | J88: 0.86795612 | K88: 24934 | L88: 0.16134595 | M88: 1.2702358 | N88: 0.021128511 | O88: =I88/T88 -> 41.079853 | P88: 121372.35 | Q88: =I88 -> 3491.7875 | R88: =P88-Q88 -> 117880.56 | S88: =IF(Q88=0,0,(P88-Q88)/Q88) -> 33.759375 | T88: 85 | U88: =IF(T88=0,"NA",P88/T88) -> 1427.91 | V88: =(L88*N88) -> 0.0034089998 | W88: =IF(P88=0,0,R88/P88) -> 0.97123078 | X88: =IF(T88=0,0,Q88/T88) -> 41.079853 | Y88: =Q88*0.9 -> 3142.6087 | Z88: =R88*1.05 -> 123774.59 | AA88: =Q88-Y88 -> 349.17875 | AB88: =R88-Z88 -> -5894.0281
A89: Overture - Global | B89: airline ticket to france | C89: Advanced | D89: Unassigned | E89: Unassigned | F89: Position 1-2 Target | G89: 7.5 | H89: 43 | I89: 36.7625 | J89: 0.85494185 | K89: 825 | L89: 0.052121212 | M89: 1.7916364 | N89: 0.023255814 | O89: =I89/T89 -> 36.7625 | P89: 1274.15 | Q89: =I89 -> 36.7625 | R89: =P89-Q89 -> 1237.3875 | S89: =IF(Q89=0,0,(P89-Q89)/Q89) -> 33.65896 | T89: 1 | U89: =IF(T89=0,"NA",P89/T89) -> 1274.15 | V89: =(L89*N89) -> 0.0012121212 | W89: =IF(P89=0,0,R89/P89) -> 0.97114743 | X89: =IF(T89=0,0,Q89/T89) -> 36.7625 | Y89: =Q89*0.9 -> 33.08625 | Z89: =R89*1.05 -> 1299.2569 | AA89: =Q89-Y89 -> 3.67625 | AB89: =R89-Z89 -> -61.869375
A90: Google - US | B90: paris airfare | C90: Broad | D90: Geo Targeted Chicago | E90: Chicago to Paris Sale | F90: Position 5-10 Bid Strategy | G90: 6.25 | H90: 24 | I90: 44.5125 | J90: 1.8546875 | K90: 194 | L90: 0.12371134 | M90: 1.7108763 | N90: 0.041666667 | O90: =I90/T90 -> 44.5125 | P90: 1530 | Q90: =I90 -> 44.5125 | R90: =P90-Q90 -> 1485.4875 | S90: =IF(Q90=0,0,(P90-Q90)/Q90) -> 33.372367 | T90: 1 | U90: =IF(T90=0,"NA",P90/T90) -> 1530 | V90: =(L90*N90) -> 0.0051546392 | W90: =IF(P90=0,0,R90/P90) -> 0.97090686 | X90: =IF(T90=0,0,Q90/T90) -> 44.5125 | Y90: =Q90*0.9 -> 40.06125 | Z90: =R90*1.05 -> 1559.7619 | AA90: =Q90-Y90 -> 4.45125 | AB90: =R90-Z90 -> -74.274375
A91: Overture - Global | B91: air france reservation | C91: Advanced | D91: Unassigned | E91: Unassigned | F91: Position 1-2 Target | G91: 0.45 | H91: 302 | I91: 176.775 | J91: 0.58534767 | K91: 22484 | L91: 0.013431774 | M91: 1.3111902 | N91: 0.01986755 | O91: =I91/T91 -> 29.4625 | P91: 5888.8 | Q91: =I91 -> 176.775 | R91: =P91-Q91 -> 5712.025 | S91: =IF(Q91=0,0,(P91-Q91)/Q91) -> 32.312403 | T91: 6 | U91: =IF(T91=0,"NA",P91/T91) -> 981.46667 | V91: =(L91*N91) -> 0.00026685643 | W91: =IF(P91=0,0,R91/P91) -> 0.96998115 | X91: =IF(T91=0,0,Q91/T91) -> 29.4625 | Y91: =Q91*0.9 -> 159.0975 | Z91: =R91*1.05 -> 5997.6263 | AA91: =Q91-Y91 -> 17.6775 | AB91: =R91-Z91 -> -285.60125
A92: Overture - Global | B92: air france usa | C92: Advanced | D92: Unassigned | E92: Unassigned | F92: Position 1-2 Target | G92: 7.5 | H92: 116 | I92: 41.949999 | J92: 0.36163793 | K92: 4815 | L92: 0.024091381 | M92: 1.9894081 | N92: 0.0086206897 | O92: =I92/T92 -> 41.949999 | P92: 1394.85 | Q92: =I92 -> 41.949999 | R92: =P92-Q92 -> 1352.9 | S92: =IF(Q92=0,0,(P92-Q92)/Q92) -> 32.250299 | T92: 1 | U92: =IF(T92=0,"NA",P92/T92) -> 1394.85 | V92: =(L92*N92) -> 0.00020768432 | W92: =IF(P92=0,0,R92/P92) -> 0.96992508 | X92: =IF(T92=0,0,Q92/T92) -> 41.949999 | Y92: =Q92*0.9 -> 37.754999 | Z92: =R92*1.05 -> 1420.545 | AA92: =Q92-Y92 -> 4.1949999 | AB92: =R92-Z92 -> -67.645
A93: Google - US | B93: italy airline | C93: Broad | D93: Geo Targeted San Francisco | E93: San Francisco to Italy Sale | F93: Position 5-10 Bid Strategy | G93: 6.25 | H93: 16 | I93: 25.75 | J93: 1.609375 | K93: 163 | L93: 0.098159509 | M93: 1.5705521 | N93: 0.0625 | O93: =I93/T93 -> 25.75 | P93: 850 | Q93: =I93 -> 25.75 | R93: =P93-Q93 -> 824.25 | S93: =IF(Q93=0,0,(P93-Q93)/Q93) -> 32.009709 | T93: 1 | U93: =IF(T93=0,"NA",P93/T93) -> 850 | V93: =(L93*N93) -> 0.0061349693 | W93: =IF(P93=0,0,R93/P93) -> 0.96970588 | X93: =IF(T93=0,0,Q93/T93) -> 25.75 | Y93: =Q93*0.9 -> 23.175 | Z93: =R93*1.05 -> 865.4625 | AA93: =Q93-Y93 -> 2.575 | AB93: =R93-Z93 -> -41.2125
A94: Yahoo - US | B94: international air fare | C94: Advanced | D94: Geo Targeted New York | E94: International New York | G94: 6.25 | H94: 10 | I94: 25.7875 | J94: 2.57875 | K94: 830 | L94: 0.012048193 | M94: 3.4382169 | N94: 0.1 | O94: =I94/T94 -> 25.7875 | P94: 816 | Q94: =I94 -> 25.7875 | R94: =P94-Q94 -> 790.2125 | S94: =IF(Q94=0,0,(P94-Q94)/Q94) -> 30.643238 | T94: 1 | U94: =IF(T94=0,"NA",P94/T94) -> 816 | V94: =(L94*N94) -> 0.0012048193 | W94: =IF(P94=0,0,R94/P94) -> 0.96839767 | X94: =IF(T94=0,0,Q94/T94) -> 25.7875 | Y94: =Q94*0.9 -> 23.20875 | Z94: =R94*1.05 -> 829.72312 | AA94: =Q94-Y94 -> 2.57875 | AB94: =R94-Z94 -> -39.510625
A95: Yahoo - US | B95: airfrance | C95: Advanced | D95: Air France Branded | E95: Air France Website | G95: 7.5 | H95: 23893 | I95: 17939.35 | J95: 0.75082031 | K95: 162070 | L95: 0.14742395 | M95: 1.6010922 | N95: 0.017620223 | O95: =I95/T95 -> 42.611282 | P95: 567463.4 | Q95: =I95 -> 17939.35 | R95: =P95-Q95 -> 549524.05 | S95: =IF(Q95=0,0,(P95-Q95)/Q95) -> 30.632328 | T95: 421 | U95: =IF(T95=0,"NA",P95/T95) -> 1347.8941 | V95: =(L95*N95) -> 0.002597643 | W95: =IF(P95=0,0,R95/P95) -> 0.96838677 | X95: =IF(T95=0,0,Q95/T95) -> 42.611282 | Y95: =Q95*0.9 -> 16145.415 | Z95: =R95*1.05 -> 577000.25 | AA95: =Q95-Y95 -> 1793.935 | AB95: =R95-Z95 -> -27476.203
A96: MSN - US | B96: airfrance com | C96: Broad | D96: Air France Brand & French Destinations | E96: Air France Website | G96: 0 | H96: 1498 | I96: 951.31248 | J96: 0.63505506 | K96: 5490 | L96: 0.27285974 | M96: 1.1497505 | N96: 0.016021362 | O96: =I96/T96 -> 39.63802 | P96: 30053.45 | Q96: =I96 -> 951.31248 | R96: =P96-Q96 -> 29102.138 | S96: =IF(Q96=0,0,(P96-Q96)/Q96) -> 30.591565 | T96: 24 | U96: =IF(T96=0,"NA",P96/T96) -> 1252.2271 | V96: =(L96*N96) -> 0.0043715847 | W96: =IF(P96=0,0,R96/P96) -> 0.96834598 | X96: =IF(T96=0,0,Q96/T96) -> 39.63802 | Y96: =Q96*0.9 -> 856.18124 | Z96: =R96*1.05 -> 30557.244 | AA96: =Q96-Y96 -> 95.131248 | AB96: =R96-Z96 -> -1455.1069
A97: Overture - Global | B97: air france us | C97: Advanced | D97: Unassigned | E97: Unassigned | F97: Position 1-2 Target | G97: 7.5 | H97: 87 | I97: 38.687499 | J97: 0.4446839 | K97: 2505 | L97: 0.034730539 | M97: 1.1856687 | N97: 0.011494253 | O97: =I97/T97 -> 38.687499 | P97: 1202.75 | Q97: =I97 -> 38.687499 | R97: =P97-Q97 -> 1164.0625 | S97: =IF(Q97=0,0,(P97-Q97)/Q97) -> 30.088854 | T97: 1 | U97: =IF(T97=0,"NA",P97/T97) -> 1202.75 | V97: =(L97*N97) -> 0.0003992016 | W97: =IF(P97=0,0,R97/P97) -> 0.96783413 | X97: =IF(T97=0,0,Q97/T97) -> 38.687499 | Y97: =Q97*0.9 -> 34.818749 | Z97: =R97*1.05 -> 1222.2656 | AA97: =Q97-Y97 -> 3.8687499 | AB97: =R97-Z97 -> -58.203125
A98: Yahoo - US | B98: france flight | C98: Standard | D98: Paris & France Terms | E98: France | G98: 6.25 | H98: 107 | I98: 136.3 | J98: 1.2738318 | K98: 3137 | L98: 0.034109021 | M98: 1 | N98: 0.0093457944 | O98: =I98/T98 -> 136.3 | P98: 4148 | Q98: =I98 -> 136.3 | R98: =P98-Q98 -> 4011.7 | S98: =IF(Q98=0,0,(P98-Q98)/Q98) -> 29.432869 | T98: 1 | U98: =IF(T98=0,"NA",P98/T98) -> 4148 | V98: =(L98*N98) -> 0.0003187759 | W98: =IF(P98=0,0,R98/P98) -> 0.96714079 | X98: =IF(T98=0,0,Q98/T98) -> 136.3 | Y98: =Q98*0.9 -> 122.67 | Z98: =R98*1.05 -> 4212.285 | AA98: =Q98-Y98 -> 13.63 | AB98: =R98-Z98 -> -200.585
A99: Overture - US | B99: air france | C99: Standard | D99: Unassigned | E99: Unassigned | F99: Position 1-4 Bid Strategy | G99: 7.5 | H99: 2235 | I99: 1441.325 | J99: 0.64488814 | K99: 38432 | L99: 0.058154663 | M99: 1.373993 | N99: 0.017002237 | O99: =I99/T99 -> 37.929605 | P99: 43020.2 | Q99: =I99 -> 1441.325 | R99: =P99-Q99 -> 41578.875 | S99: =IF(Q99=0,0,(P99-Q99)/Q99) -> 28.847675 | T99: 38 | U99: =IF(T99=0,"NA",P99/T99) -> 1132.1105 | V99: =(L99*N99) -> 0.00098875937 | W99: =IF(P99=0,0,R99/P99) -> 0.96649655 | X99: =IF(T99=0,0,Q99/T99) -> 37.929605 | Y99: =Q99*0.9 -> 1297.1925 | Z99: =R99*1.05 -> 43657.819 | AA99: =Q99-Y99 -> 144.1325 | AB99: =R99-Z99 -> -2078.9438
A100: Google - US | B100: air france airlines | C100: Broad | D100: Air France Branded | E100: Air France Brand | F100: Position 1 -2 Target | G100: 18.75 | H100: 2454 | I100: 1050.7875 | J100: 0.42819376 | K100: 11128 | L100: 0.2205248 | M100: 1.1778774 | N100: 0.011409943 | O100: =I100/T100 -> 37.528125 | P100: 31200.1 | Q100: =I100 -> 1050.7875 | R100: =P100-Q100 -> 30149.313 | S100: =IF(Q100=0,0,(P100-Q100)/Q100) -> 28.692112 | T100: 28 | U100: =IF(T100=0,"NA",P100/T100) -> 1114.2893 | V100: =(L100*N100) -> 0.0025161754 | W100: =IF(P100=0,0,R100/P100) -> 0.96632102 | X100: =IF(T100=0,0,Q100/T100) -> 37.528125 | Y100: =Q100*0.9 -> 945.70874 | Z100: =R100*1.05 -> 31656.778 | AA100: =Q100-Y100 -> 105.07875 | AB100: =R100-Z100 -> -1507.4656
...

Sheet P&L Pivot Table
A3: Row Labels | B3: Sum of Net Revenue (Profit) | C3: Sum of Total Cost | D3: Sum of Total Volume of Bookings | E3: Sum of Budgeted Revenue | F3: Sum of Budgeted Cost | G3: Sum of Revenue Variance | H3: Sum of Cost Variance | I3: Average of Margin % | J3: Average of Engine Click Thru % | K3: Average of Cost per Booking | L3: Average of RevenuePerBooking
A4: Google - Global | B4: 808603.09 | C4: 120946.71 | D4: 797 | E4: 849033.24 | F4: 108852.04 | G4: -40430.154 | H4: 12094.671 | I4: 0.10474101 | J4: 0.089944849 | K4: 70.896472 | L4: 1166.3109
A5: Google - US | B5: 1391841.2 | C5: 353640.6 | D5: 1550 | E5: 1461433.3 | F5: 318276.54 | G5: -69592.06 | H5: 35364.06 | I5: 0.016028189 | J5: 0.15089745 | K5: 25.116883 | L5: 1126.1173
A6: MSN - Global | B6: 133363.89 | C6: 12160.362 | D6: 129 | E6: 140032.08 | F6: 10944.326 | G6: -6668.1944 | H6: 1216.0362 | I6: 0.089814572 | J6: 0.073356049 | K6: 11.165817 | L6: 1128.095
A7: MSN - US | B7: 165451.31 | C7: 16098.487 | D7: 140 | E7: 173723.88 | F7: 14488.639 | G7: -8272.5656 | H7: 1609.8487 | I7: 0.086432537 | J7: 0.08263521 | K7: 5.1577145 | L7: 1296.7843
A8: Overture - Global | B8: 365788.84 | C8: 64295.862 | D8: 372 | E8: 384078.28 | F8: 57866.276 | G8: -18289.442 | H8: 6429.5862 | I8: 0.057960813 | J8: 0.035478634 | K8: 16.468699 | L8: 1156.1417
A9: Overture - US | B9: 205457.18 | C9: 141976.07 | D9: 289 | E9: 215730.03 | F9: 127778.47 | G9: -10272.859 | H9: 14197.607 | I9: 0.015226643 | J9: 0.026728464 | K9: 43.660687 | L9: 1202.1912
A10: Yahoo - US | B10: 836091.13 | C10: 46197.825 | D10: 662 | E10: 877895.68 | F10: 41578.042 | G10: -41804.556 | H10: 4619.7825 | I10: 0.044443465 | J10: 0.16059019 | K10: 7.9565704 | L10: 1332.7628
A11: Grand Total | B11: 3906596.6 | C11: 755315.92 | D11: 3939 | E11: 4101926.5 | F11: 679784.33 | G11: -195329.83 | H11: 75531.592 | I11: 0.035933119 | J11: 0.11141451 | K11: 27.607445 | L11: 1183.5269

Sheet Top 10 Campaigns by Revenue
A3: Row Labels | B3: Average of Net Revenue (Profit)
A4: Air France Branded | B4: 30230.042
A5: Google - US | B5: 35086.965
A6: Yahoo - US | B6: 24342.863
A7: Air France Brand & French Destinations | B7: 2307.9847
A8: Google - Global | B8: 3627.753
A9: MSN - Global | B9: 1347.11
A10: MSN - US | B10: 1761.5201
A11: Air France Global Campaign | B11: 1439.4415
A12: Google - Global | B12: 1439.4415
A13: General Terms | B13: 1371.475
A14: Yahoo - US | B14: 1371.475
A15: Unassigned | B15: 470.54861
... A72: Google - US | B72: -114.58805

Sheet ROAS by Campaign
A3: Row Labels | B3: Average of Return on Ad Dollar Spent
A4: Air France Brand & French Destinations | B4: 5.4135137
A5: Air France Branded | B5: 30.494118
A6: Air France Global Campaign | B6: 4.8639168
A7: Business Class | B7: -0.99720645
A8: French Destinations | B8: -0.58365977
A9: General Terms | B9: 2.2613875
A10: Geo Targeted Atlanta | B10: -0.75380605
A11: Geo Targeted Boston | B11: 0.1083371
A12: Geo Targeted Chicago | B12: 0.45151159
A13: Geo Targeted Cincinnati | B13: -1
A14: Geo Targeted DC | B14: 17.724148
A15: Geo Targeted Detroit | B15: 0.33326118
... A27: Western Europe Destinations | B27: 9.0219604

Sheet Combo Chart
A3: Row Labels | B3: Average of Cost per Booking | C3: Average of Revenue per Booking
A4: Google - Global | B4: 70.896472 | C4: 1166.3109
A5: Google - US | B5: 25.116883 | C5: 1126.1173
A6: MSN - Global | B6: 11.165817 | C6: 1128.095
A7: MSN - US | B7: 5.1577145 | C7: 1296.7843
A8: Overture - Global | B8: 16.468699 | C8: 1156.1417
A9: Overture - US | B9: 43.660687 | C9: 1202.1912
A10: Yahoo - US | B10: 7.9565704 | C10: 1332.7628
A11: Grand Total | B11: 27.607445 | C11: 1183.5269

Sheet Pivot Table
A3: Row Labels | B3: Sum of Impressions | C3: Sum of Clicks | D3: Sum of Total Cost | E3: Sum of Net Revenue (Profit) | F3: Sum of Total Volume of Bookings | G3: Average of Cost per Click | H3: Sum of Trans. Conv. % | I3: Sum of Total Revenue
A4: Air France Brand & French Destinations | B4: 573159 | C4: 57674 | D4: 87014.537 | E4: 701627.36 | F4: 699 | G4: 1.5087307 | H4: 2.4989034 | I4: 788641.9
A5: Air France Branded | B5: 1263310 | C5: 143174 | D5: 143077.82 | E5: 2206793.1 | F5: 1932 | G5: 0.99932826 | H5: 1.3293698 | I5: 2349870.9
A6: Air France Global Campaign | B6: 1540074 | C6: 37221 | D6: 62059.45 | E6: 405922.5 | F6: 367 | G6: 1.6673235 | H6: 1.0403178 | I6: 467981.95
A7: Business Class | B7: 41878 | C7: 655 | D7: 3269.05 | E7: -3124.55 | F7: 1 | G7: 4.990916 | H7: 0.0034602076 | I7: 144.5
A8: French Destinations | B8: 59351 | C8: 3701 | D8: 8431.7375 | E8: -2208.0375 | F8: 14 | G8: 2.2782322 | H8: 0.17274532 | I8: 6223.7
A9: General Terms | B9: 144298 | C9: 518 | D9: 606.475 | E9: 1371.475 | F9: 1 | G9: 1.1708011 | H9: 0.0019305019 | I9: 1977.95
A10: Geo Targeted Atlanta | B10: 4428 | C10: 129 | D10: 265.25 | E10: -95.25 | F10: 1 | G10: 2.0562015 | H10: 0.16666667 | I10: 170
A11: Geo Targeted Boston | B11: 16137 | C11: 538 | D11: 1396.175 | E11: 1482.775 | F11: 4 | G11: 2.5951208 | H11: 0.40304487 | I11: 2878.95
A12: Geo Targeted Chicago | B12: 12690 | C12: 682 | D12: 1581.675 | E12: 5562.575 | F12: 5 | G12: 2.3191715 | H12: 0.25769709 | I12: 7144.25
A13: Geo Targeted Cincinnati | B13: 676 | C13: 16 | D13: 33.75 | E13: -33.75 | F13: 0 | G13: 2.109375 | H13: 0 | I13: 0
A14: Geo Targeted DC | B14: 19875 | C14: 512 | D14: 1271.3625 | E14: 3920.4375 | F14: 9 | G14: 2.4831299 | H14: 2.1969697 | I14: 5191.8
A15: Geo Targeted Detroit | B15: 9648 | C15: 295 | D15: 719.025 | E15: 204.925 | F15: 1 | G15: 2.4373729 | H15: 0.5 | I15: 923.95
... A28: Grand Total | B28: 41868674 | C28: 512849 | D28: 755315.92 | E28: 3906596.6 | F28: 3939 | G28: 1.4727842 | H28: 25.673404 | I28: 4661912.6

Sheet Scenario Analysis
A1: Campaign | B1: Impressions | C1: Cost per Click | D1: Trans. Conv. % | E1: Revenue per Booking | F1: Current CTR | G1: Current Profit | H1: Profit Target | I1: Required CTR | M1: Clicks | N1: Total Cost | O1: Bookings | P1: Total Revenue
A2: ='Pivot Table'!A4 -> Air France Brand & French Destinations | B2: =GETPIVOTDATA("Sum of Impressions",'Pivot Table'!$A$3,"Campaign",$A2) -> 573159 | C2: =$N2/$M2 -> 1.5087307 | D2: =GETPIVOTDATA("Sum of Trans. Conv. %",'Pivot Table'!$A$3,"Campaign",$A2) -> 2.4989034 | E2: =IF($O2=0, 0, $P2/$O2) -> 1128.2431 | F2: =$M2/$B2 -> 0.10062478 | G2: =GETPIVOTDATA("Sum of Net Revenue (Profit)",'Pivot Table'!$A$3,"Campaign",$A2) -> 701627.36 | H2: =IF($G2>0, G2*1.2, 0) -> 841952.84 | I2: =$H2 / ( $B2 * ( ($D2/100) * $E2 - $C2 ) ) -> 0.055048549 | M2: =GETPIVOTDATA("Sum of Clicks",'Pivot Table'!$A$3,"Campaign",$A2) -> 57674 | N2: =GETPIVOTDATA("Sum of Total Cost",'Pivot Table'!$A$3,"Campaign",$A2) -> 87014.537 | O2: =GETPIVOTDATA("Sum of Total Volume of Bookings",'Pivot Table'!$A$3,"Campaign",$A2) -> 699 | P2: =GETPIVOTDATA("Sum of Total Revenue",'Pivot Table'!$A$3,"Campaign",$A2) -> 788641.9
A3: ='Pivot Table'!A5 -> Air France Branded | B3: =GETPIVOTDATA("Sum of Impressions",'Pivot Table'!$A$3,"Campaign",$A3) -> 1263310 | C3: =$N3/$M3 -> 0.99932826 | D3: =GETPIVOTDATA("Sum of Trans. Conv. %",'Pivot Table'!$A$3,"Campaign",$A3) -> 1.3293698 | E3: =IF($O3=0, 0, $P3/$O3) -> 1216.2893 | F3: =$M3/$B3 -> 0.11333244 | G3: =GETPIVOTDATA("Sum of Net Revenue (Profit)",'Pivot Table'!$A$3,"Campaign",$A3) -> 2206793.1 | H3: =IF($G3>0, G3*1.2, 1000) -> 2648151.7 | I3: =$H3 / ( $B3 * ( ($D3/100) * $E3 - $C3 ) ) -> 0.13818383 | M3: =GETPIVOTDATA("Sum of Clicks",'Pivot Table'!$A$3,"Campaign",$A3) -> 143174 | N3: =GETPIVOTDATA("Sum of Total Cost",'Pivot Table'!$A$3,"Campaign",$A3) -> 143077.82 | O3: =GETPIVOTDATA("Sum of Total Volume of Bookings",'Pivot Table'!$A$3,"Campaign",$A3) -> 1932 | P3: =GETPIVOTDATA("Sum of Total Revenue",'Pivot Table'!$A$3,"Campaign",$A3) -> 2349870.9
A4: ='Pivot Table'!A6 -> Air France Global Campaign | B4: =GETPIVOTDATA("Sum of Impressions",'Pivot Table'!$A$3,"Campaign",$A4) -> 1540074 | C4: =$N4/$M4 -> 1.6673235 | D4: =GETPIVOTDATA("Sum of Trans. Conv. %",'Pivot Table'!$A$3,"Campaign",$A4) -> 1.0403178 | E4: =IF($O4=0, 0, $P4/$O4) -> 1275.1552 | F4: =$M4/$B4 -> 0.024168319 | G4: =GETPIVOTDATA("Sum of Net Revenue (Profit)",'Pivot Table'!$A$3,"Campaign",$A4) -> 405922.5 | H4: =IF($G4>0, G4*1.2, 1000) -> 487107 | I4: =$H4 / ( $B4 * ( ($D4/100) * $E4 - $C4 ) ) -> 0.027270106 | M4: =GETPIVOTDATA("Sum of Clicks",'Pivot Table'!$A$3,"Campaign",$A4) -> 37221 | N4: =GETPIVOTDATA("Sum of Total Cost",'Pivot Table'!$A$3,"Campaign",$A4) -> 62059.45 | O4: =GETPIVOTDATA("Sum of Total Volume of Bookings",'Pivot Table'!$A$3,"Campaign",$A4) -> 367 | P4: =GETPIVOTDATA("Sum of Total Revenue",'Pivot Table'!$A$3,"Campaign",$A4) -> 467981.95
A5: ='Pivot Table'!A7 -> Business Class | B5: =GETPIVOTDATA("Sum of Impressions",'Pivot Table'!$A$3,"Campaign",$A5) -> 41878 | C5: =$N5/$M5 -> 4.990916 | D5: =GETPIVOTDATA("Sum of Trans. Conv. %",'Pivot Table'!$A$3,"Campaign",$A5) -> 0.0034602076 | E5: =IF($O5=0, 0, $P5/$O5) -> 144.5 | F5: =$M5/$B5 -> 0.015640671 | G5: =GETPIVOTDATA("Sum of Net Revenue (Profit)",'Pivot Table'!$A$3,"Campaign",$A5) -> -3124.55 | H5: =IF($G5>0, G5*1.2, 1000) -> 1000 | I5: =$H5 / ( $B5 * ( ($D5/100) * $E5 - $C5 ) ) -> -0.0047892676 | M5: =GETPIVOTDATA("Sum of Clicks",'Pivot Table'!$A$3,"Campaign",$A5) -> 655 | N5: =GETPIVOTDATA("Sum of Total Cost",'Pivot Table'!$A$3,"Campaign",$A5) -> 3269.05 | O5: =GETPIVOTDATA("Sum of Total Volume of Bookings",'Pivot Table'!$A$3,"Campaign",$A5) -> 1 | P5: =GETPIVOTDATA("Sum of Total Revenue",'Pivot Table'!$A$3,"Campaign",$A5) -> 144.5
A6: ='Pivot Table'!A8 -> French Destinations | B6: =GETPIVOTDATA("Sum of Impressions",'Pivot Table'!$A$3,"Campaign",$A6) -> 59351 | C6: =$N6/$M6 -> 2.2782322 | D6: =GETPIVOTDATA("Sum of Trans. Conv. %",'Pivot Table'!$A$3,"Campaign",$A6) -> 0.17274532 | E6: =IF($O6=0, 0, $P6/$O6) -> 444.55 | F6: =$M6/$B6 -> 0.062357837 | G6: =GETPIVOTDATA("Sum of Net Revenue (Profit)",'Pivot Table'!$A$3,"Campaign",$A6) -> -2208.0375 | H6: =IF($G6>0, G6*1.2, 1000) -> 1000 | I6: =$H6 / ( $B6 * ( ($D6/100) * $E6 - $C6 ) ) -> -0.011156058 | M6: =GETPIVOTDATA("Sum of Clicks",'Pivot Table'!$A$3,"Campaign",$A6) -> 3701 | N6: =GETPIVOTDATA("Sum of Total Cost",'Pivot Table'!$A$3,"Campaign",$A6) -> 8431.7375 | O6: =GETPIVOTDATA("Sum of Total Volume of Bookings",'Pivot Table'!$A$3,"Campaign",$A6) -> 14 | P6: =GETPIVOTDATA("Sum of Total Revenue",'Pivot Table'!$A$3,"Campaign",$A6) -> 6223.7
A7: ='Pivot Table'!A9 -> General Terms | B7: =GETPIVOTDATA("Sum of Impressions",'Pivot Table'!$A$3,"Campaign",$A7) -> 144298 | C7: =$N7/$M7 -> 1.1708011 | D7: =GETPIVOTDATA("Sum of Trans. Conv. %",'Pivot Table'!$A$3,"Campaign",$A7) -> 0.0019305019 | E7: =IF($O7=0, 0, $P7/$O7) -> 1977.95 | F7: =$M7/$B7 -> 0.0035897933 | G7: =GETPIVOTDATA("Sum of Net Revenue (Profit)",'Pivot Table'!$A$3,"Campaign",$A7) -> 1371.475 | H7: =IF($G7>0, G7*1.2, 1000) -> 1645.77 | I7: =$H7 / ( $B7 * ( ($D7/100) * $E7 - $C7 ) ) -> -0.010069916 | M7: =GETPIVOTDATA("Sum of Clicks",'Pivot Table'!$A$3,"Campaign",$A7) -> 518 | N7: =GETPIVOTDATA("Sum of Total Cost",'Pivot Table'!$A$3,"Campaign",$A7) -> 606.475 | O7: =GETPIVOTDATA("Sum of Total Volume of Bookings",'Pivot Table'!$A$3,"Campaign",$A7) -> 1 | P7: =GETPIVOTDATA("Sum of Total Revenue",'Pivot Table'!$A$3,"Campaign",$A7) -> 1977.95
A8: ='Pivot Table'!A10 -> Geo Targeted Atlanta | B8: =GETPIVOTDATA("Sum of Impressions",'Pivot Table'!$A$3,"Campaign",$A8) -> 4428 | C8: =$N8/$M8 -> 2.0562015 | D8: =GETPIVOTDATA("Sum of Trans. Conv. %",'Pivot Table'!$A$3,"Campaign",$A8) -> 0.16666667 | E8: =IF($O8=0, 0, $P8/$O8) -> 170 | F8: =$M8/$B8 -> 0.029132791 | G8: =GETPIVOTDATA("Sum of Net Revenue (Profit)",'Pivot Table'!$A$3,"Campaign",$A8) -> -95.25 | H8: =IF($G8>0, G8*1.2, 1000) -> 1000 | I8: =$H8 / ( $B8 * ( ($D8/100) * $E8 - $C8 ) ) -> -0.12738431 | M8: =GETPIVOTDATA("Sum of Clicks",'Pivot Table'!$A$3,"Campaign",$A8) -> 129 | N8: =GETPIVOTDATA("Sum of Total Cost",'Pivot Table'!$A$3,"Campaign",$A8) -> 265.25 | O8: =GETPIVOTDATA("Sum of Total Volume of Bookings",'Pivot Table'!$A$3,"Campaign",$A8) -> 1 | P8: =GETPIVOTDATA("Sum of Total Revenue",'Pivot Table'!$A$3,"Campaign",$A8) -> 170
A9: ='Pivot Table'!A11 -> Geo Targeted Boston | B9: =GETPIVOTDATA("Sum of Impressions",'Pivot Table'!$A$3,"Campaign",$A9) -> 16137 | C9: =$N9/$M9 -> 2.5951208 | D9: =GETPIVOTDATA("Sum of Trans. Conv. %",'Pivot Table'!$A$3,"Campaign",$A9) -> 0.40304487 | E9: =IF($O9=0, 0, $P9/$O9) -> 719.7375 | F9: =$M9/$B9 -> 0.03333953 | G9: =GETPIVOTDATA("Sum of Net Revenue (Profit)",'Pivot Table'!$A$3,"Campaign",$A9) -> 1482.775 | H9: =IF($G9>0, G9*1.2, 1000) -> 1779.33 | I9: =$H9 / ( $B9 * ( ($D9/100) * $E9 - $C9 ) ) -> 0.36064123 | M9: =GETPIVOTDATA("Sum of Clicks",'Pivot Table'!$A$3,"Campaign",$A9) -> 538 | N9: =GETPIVOTDATA("Sum of Total Cost",'Pivot Table'!$A$3,"Campaign",$A9) -> 1396.175 | O9: =GETPIVOTDATA("Sum of Total Volume of Bookings",'Pivot Table'!$A$3,"Campaign",$A9) -> 4 | P9: =GETPIVOTDATA("Sum of Total Revenue",'Pivot Table'!$A$3,"Campaign",$A9) -> 2878.95
A10: ='Pivot Table'!A12 -> Geo Targeted Chicago | B10: =GETPIVOTDATA("Sum of Impressions",'Pivot Table'!$A$3,"Campaign",$A10) -> 12690 | C10: =$N10/$M10 -> 2.3191715 | D10: =GETPIVOTDATA("Sum of Trans. Conv. %",'Pivot Table'!$A$3,"Campaign",$A10) -> 0.25769709 | E10: =IF($O10=0, 0, $P10/$O10) -> 1428.85 | F10: =$M10/$B10 -> 0.053743105 | G10: =GETPIVOTDATA("Sum of Net Revenue (Profit)",'Pivot Table'!$A$3,"Campaign",$A10) -> 5562.575 | H10: =IF($G10>0, G10*1.2, 1000) -> 6675.09 | I10: =$H10 / ( $B10 * ( ($D10/100) * $E10 - $C10 ) ) -> 0.38594098 | M10: =GETPIVOTDATA("Sum of Clicks",'Pivot Table'!$A$3,"Campaign",$A10) -> 682 | N10: =GETPIVOTDATA("Sum of Total Cost",'Pivot Table'!$A$3,"Campaign",$A10) -> 1581.675 | O10: =GETPIVOTDATA("Sum of Total Volume of Bookings",'Pivot Table'!$A$3,"Campaign",$A10) -> 5 | P10: =GETPIVOTDATA("Sum of Total Revenue",'Pivot Table'!$A$3,"Campaign",$A10) -> 7144.25
A11: ='Pivot Table'!A13 -> Geo Targeted Cincinnati | B11: =GETPIVOTDATA("Sum of Impressions",'Pivot Table'!$A$3,"Campaign",$A11) -> 676 | C11: =$N11/$M11 -> 2.109375 | D11: =GETPIVOTDATA("Sum of Trans. Conv. %",'Pivot Table'!$A$3,"Campaign",$A11) -> 0 | E11: =IF($O11=0, 0, $P11/$O11) -> 0 | F11: =$M11/$B11 -> 0.023668639 | G11: =GETPIVOTDATA("Sum of Net Revenue (Profit)",'Pivot Table'!$A$3,"Campaign",$A11) -> -33.75 | H11: =IF($G11>0, G11*1.2, 1000) -> 1000 | I11: =$H11 / ( $B11 * ( ($D11/100) * $E11 - $C11 ) ) -> -0.70129301 | M11: =GETPIVOTDATA("Sum of Clicks",'Pivot Table'!$A$3,"Campaign",$A11) -> 16 | N11: =GETPIVOTDATA("Sum of Total Cost",'Pivot Table'!$A$3,"Campaign",$A11) -> 33.75 | O11: =GETPIVOTDATA("Sum of Total Volume of Bookings",'Pivot Table'!$A$3,"Campaign",$A11) -> 0 | P11: =GETPIVOTDATA("Sum of Total Revenue",'Pivot Table'!$A$3,"Campaign",$A11) -> 0
A12: ='Pivot Table'!A14 -> Geo Targeted DC | B12: =GETPIVOTDATA("Sum of Impressions",'Pivot Table'!$A$3,"Campaign",$A12) -> 19875 | C12: =$N12/$M12 -> 2.4831299 | D12: =GETPIVOTDATA("Sum of Trans. Conv. %",'Pivot Table'!$A$3,"Campaign",$A12) -> 2.1969697 | E12: =IF($O12=0, 0, $P12/$O12) -> 576.86667 | F12: =$M12/$B12 -> 0.025761006 | G12: =GETPIVOTDATA("Sum of Net Revenue (Profit)",'Pivot Table'!$A$3,"Campaign",$A12) -> 3920.4375 | H12: =IF($G12>0, G12*1.2, 1000) -> 4704.525 | I12: =$H12 / ( $B12 * ( ($D12/100) * $E12 - $C12 ) ) -> 0.023228172 | M12: =GETPIVOTDATA("Sum of Clicks",'Pivot Table'!$A$3,"Campaign",$A12) -> 512 | N12: =GETPIVOTDATA("Sum of Total Cost",'Pivot Table'!$A$3,"Campaign",$A12) -> 1271.3625 | O12: =GETPIVOTDATA("Sum of Total Volume of Bookings",'Pivot Table'!$A$3,"Campaign",$A12) -> 9 | P12: =GETPIVOTDATA("Sum of Total Revenue",'Pivot Table'!$A$3,"Campaign",$A12) -> 5191.8
A13: ='Pivot Table'!A15 -> Geo Targeted Detroit | B13: =GETPIVOTDATA("Sum of Impressions",'Pivot Table'!$A$3,"Campaign",$A13) -> 9648 | C13: =$N13/$M13 -> 2.4373729 | D13: =GETPIVOTDATA("Sum of Trans. Conv. %",'Pivot Table'!$A$3,"Campaign",$A13) -> 0.5 | E13: =IF($O13=0, 0, $P13/$O13) -> 923.95 | F13: =$M13/$B13 -> 0.030576285 | G13: =GETPIVOTDATA("Sum of Net Revenue (Profit)",'Pivot Table'!$A$3,"Campaign",$A13) -> 204.925 | H13: =IF($G13>0, G13*1.2, 1000) -> 245.91 | I13: =$H13 / ( $B13 * ( ($D13/100) * $E13 - $C13 ) ) -> 0.011679092 | M13: =GETPIVOTDATA("Sum of Clicks",'Pivot Table'!$A$3,"Campaign",$A13) -> 295 | N13: =GETPIVOTDATA("Sum of Total Cost",'Pivot Table'!$A$3,"Campaign",$A13) -> 719.025 | O13: =GETPIVOTDATA("Sum of Total Volume of Bookings",'Pivot Table'!$A$3,"Campaign",$A13) -> 1 | P13: =GETPIVOTDATA("Sum of Total Revenue",'Pivot Table'!$A$3,"Campaign",$A13) -> 923.95
A14: ='Pivot Table'!A16 -> Geo Targeted Houston | B14: =GETPIVOTDATA("Sum of Impressions",'Pivot Table'!$A$3,"Campaign",$A14) -> 25338 | C14: =$N14/$M14 -> 2.956658 | D14: =GETPIVOTDATA("Sum of Trans. Conv. %",'Pivot Table'!$A$3,"Campaign",$A14) -> 0.41103896 | E14: =IF($O14=0, 0, $P14/$O14) -> 1413.04 | F14: =$M14/$B14 -> 0.026600363 | G14: =GETPIVOTDATA("Sum of Net Revenue (Profit)",'Pivot Table'!$A$3,"Campaign",$A14) -> 5072.4125 | H14: =IF($G14>0, G14*1.2, 1000) -> 6086.895 | I14: =$H14 / ( $B14 * ( ($D14/100) * $E14 - $C14 ) ) -> 0.084246544 | M14: =GETPIVOTDATA("Sum of Clicks",'Pivot Table'!$A$3,"Campaign",$A14) -> 674 | N14: =GETPIVOTDATA("Sum of Total Cost",'Pivot Table'!$A$3,"Campaign",$A14) -> 1992.7875 | O14: =GETPIVOTDATA("Sum of Total Volume of Bookings",'Pivot Table'!$A$3,"Campaign",$A14) -> 5 | P14: =GETPIVOTDATA("Sum of Total Revenue",'Pivot Table'!$A$3,"Campaign",$A14) -> 7065.2
... A25: ='Pivot Table'!A27 -> Western Europe Destinations | B25: =GETPIVOTDATA("Sum of Impressions",'Pivot Table'!$A$3,"Campaign",$A25) -> 588324 | C25: =$N25/$M25 -> 2.1748129 | D25: =GETPIVOTDATA("Sum of Trans. Conv. %",'Pivot Table'!$A$3,"Campaign",$A25) -> 9.3064647 | E25: =IF($O25=0, 0, $P25/$O25) -> 935.64222 | F25: =$M25/$B25 -> 0.028278636 | G25: =GETPIVOTDATA("Sum of Net Revenue (Profit)",'Pivot Table'!$A$3,"Campaign",$A25) -> 5921.5376 | H25: =IF($G25>0, G25*1.2, 1000) -> 7105.8451 | I25: =$H25 / ( $B25 * ( ($D25/100) * $E25 - $C25 ) ) -> 0.00014226217 | M25: =GETPIVOTDATA("Sum of Clicks",'Pivot Table'!$A$3,"Campaign",$A25) -> 16637 | N25: =GETPIVOTDATA("Sum of Total Cost",'Pivot Table'!$A$3,"Campaign",$A25) -> 36182.362 | O25: =GETPIVOTDATA("Sum of Total Volume of Bookings",'Pivot Table'!$A$3,"Campaign",$A25) -> 45 | P25: =GETPIVOTDATA("Sum of Total Revenue",'Pivot Table'!$A$3,"Campaign",$A25) -> 42103.9
